Workbook

Sheet Agenda Draft 01
A1: Day | B1: Time | C1: Topic | D1: Presenter | E1: Key Content
A2: 1 | C2: Opening & Objectives | D2: Mr. Saleh & Sameh Khalil | E2: • Purpose of meeting • 2030 ambition • What limits growth • Need for new verticals • Growth mindset • Brainstorming rules & scoring model intro.
C3: Brainstorming Method & Framework | D3: Dr Samy Katar | E3: • Opportunity Scoring Model • Brainstorming rules • How to think about opportunities (Data-based logic) • Simple scoring model intro
C5: Wound Care Business | D5: Mahmoud Younis | E5: • Vision 2030 • Market • Growth drivers • Portfolio • Top opportunities • Competition • Risks • Support needed
C6: Tender Analysis and Dialysis business | D6: Weal Korashi | E6: Same structure as above
C7: Classic Business | D7: BU Manager | E7: Same structure as above
C8: Cardiology Business | D8: Ayman Kaddah | E8: Same structure as above
C9: Equipment Business | D9: BU Manager | E9: Same structure as above
C10: Open Brainstorming Session # Day 1 | D10: All | E10: • Cross-BU synergies • What Worked / Didn’t • Enablers (Role, Responsibility, Timeline, Review Freqancy • Action Planning (12–18–24 Months) • Cross-Functional Priorities
C11: Open Brainstorming Session # Day 2 | D11: All | E11: Same structure as above
C12: Open Brainstorming Session # Day 3 | D12: All | E12: Same structure as above
C13: 2030 Final Alignment Discussion | D13: CEO + All | E13: • Summary • Alignment • Next steps
A14: 3 | C14: Operations Enabler Update | D14: Faizan Rao | E14: • Effectivnes of Change. • Next Step (Ops support to sales) • Inventory visibility • MRP Demo • KPI Review (OTIF, A3 Report, Dashboard). • Budget 2026

Sheet Title
A1: <<2026>> Year of Excellence (YoE) YoE 4 1b Y 05

Sheet Agenda V01
B1: Year of Excellence ~ Journey to 1 Billion
B2: Offsite Strategy Meeting - Egypt 2025
B4: Time | C4: Subject | D4: Presenter | E4: Key Content
B5: Day 01 (07 Dec, 2025)
B6: 9:00 – 9:30 | C6: Opening & Objectives | D6: Mr. Saleh & Dr. Sameh | E6: • Purpose of Egypt strategy meeting • 2030 ambition • Expectations from each BU • Why new verticals matter • How this meeting will run • Importance of alignment
B7: 9:30 – 10:00 | C7: Brainstorming Methodology | D7: Dr. Sameh | E7: • Opportunity Scoring Model (OSM) • Brainstorming rules • How to think about opportunities (Data-based logic) • Simple scoring model intro
B8: 10:00 – 11:00 | C8: Wound Care / Diabetes / Rehabilitation / Tenders | D8: Mahmoud Younis | E8: • Market opportunities • Current Pipeline • Partner opportunities • High-potential SKUs & High Value Tender Timelines • Required support • Competition analysis • Historical challenges in tender pricing • Key wins/losses • Market gaps
B9: 11:00 – 11:30 | C9: Break
B10: 11:30 – 13:30 | C10: Dialysis Business | D10: Wael Korashi | E10: • Market opportunities • Current Pipeline • Partner opportunities • High-potential SKUs & High Value Tender Timelines • Required support • Competition analysis • Historical challenges in tender pricing • Key wins/losses • Market gaps
B11: 13:30 – 14:30 | C11: Lunch + Prayer Break
B12: 14:30 – 17:30 | C12: Open Discussion & Brainstorming Day-01 | D12: All | E12: • Day Summary (Idea collection) • What opportunities can be combined? • Review OSM
B15: Day 02 (08 Dec, 2025)
B16: 9:00 – 11:00 | C16: Classic Business | D16: Mohamed Samir | E16: • Market opportunities • Current Pipeline • Partner opportunities • High-potential SKUs & High Value Tender Timelines • Required support • Competition analysis • Historical challenges in tender pricing • Key wins/losses • Market gaps
B17: 11:00 – 11:30 | C17: Break
B18: 11:30 – 13:00 | C18: Cardiology Business | D18: Ayman Kaddah | E18: • Market opportunities • Current Pipeline • Partner opportunities • Tender readiness (High Value) • High-potential SKUs • Required support • Competition analysis • Historical challenges in tender pricing • Key wins/losses • Market gaps
B19: 13:30 – 14:30 | C19: Lunch + Prayer Break
B20: 15:30 – 17:00 | C20: Open Discussion & Brainstorming Day-02 | D20: All | E20: • Day Summary (Idea collection) • What opportunities can be combined? • Review OSM
B22: Day 03 (09 Dec, 2025)
B23: 9:00 – 11:00 | C23: Equipment Business | D23: Ahmad Awad | E23: • Market opportunities • Current Pipeline • Partner opportunities • Tender readiness (High Value) • High-potential SKUs • Required support • Competition analysis • Historical challenges in tender pricing • Key wins/losses • Market gaps • Post-sales requirements
B24: 11:00 – 11:30 | C24: Break
B25: 11:30 – 13:30 | C25: Open Discussion & Brainstorming Day-03 | D25: All | E25: • Day Summary (Idea collection) • What opportunities can be combined? • Review OSM
B26: 13:30 – 14:30 | C26: Lunch + Prayer Break
B27: 14:30 – 15:30 | C27: Ops 4 Months Performance Review and Next Step | D27: Faizan Rao | E27: • Performance Reivew and Sales Feedback. • Next Year Operational Calander & SOP. • OTIF & A3 Report & DashBoard. • MRP v1 Demo & MRP v2 timeline. • Inventory Classification (ABC/XYZ). • Inventory Review Meeting (Monthly). • Inventory 2026 Action Plan. • Supplier follow-up system. • NUPCO changing tracking. • NUPCO portal changes MGMT.
B28: 15:30 – 17:30 | C28: 2030 Final Alignment Discussion | D28: All | E28: • Finalize opportunity shortlist • Assign owners • Prepare input for action plan
B29: 18:30 – XX:XX | C29: Dinner @ Khan Khalili

Sheet WS
F3: SBU
F4: Classic
F5: Wound-Care
F6: Equipments
F7: Cardiology
F8: Dialysis
F9: Surgical Inst.
B19: Thing to Ask
B21: Critical Drop Zone
B22: Regulatory | C22: Complex
B23: Tender feasibility | C23: Low
B24: Product complexity | C24: Very difficult
B25: Supplier availability | C25: Very Low
B26: Entry barriers | C26: Very High
B29: Category | C29: Weight | D29: Field
B30: Market Attractiveness | C30: 0.4 | D30: Y01 Revenues, 5Y CAGR, Margin, Market Awareness
B31: Ease of Entry | C31: 0.3 | D31: Product, Operational, BD, Regulatory, Tender
B32: Strategic Fit | C32: 0.2 | D32: Localization potential, JMI capabilities
B33: Risk | C33: 0.1 | D33: Entry barriers, complexity
B36: Weight
B37: Market Awareness & Capability
B38: Rating | C38: Score | D38: Weight | E38: Description
B39: Yes – Very High | C39: 5 | D39: 0.05 | E39: Market fully understands the product
B40: Yes – High | C40: 4 | D40: 0.05 | E40: Good awareness; some education needed
B41: Partial | C41: 3 | D41: 0.05 | E41: Mixed understanding; requires effort
B42: Low Awareness | C42: 2 | D42: 0.05 | E42: Limited knowledge in market
B43: No – Minimal | C43: 1 | D43: 0.05 | E43: No awareness; heavy education needed
B44: To Be Assessed | C44: 0 | D44: 0.05 | E44: Information not available
B47: Field Name | C47: Weight
B48: Market Awareness & Capability | C48: 0.05
B49: Entry Barriers | C49: 0.05
B50: Supplier Availability / Partnership Readiness | C50: 0.05
B51: Gross Margin Potential | C51: 0.1
B52: Ease of Entry – Tender Feasibility (NUPCO likelihood) | C52: 0.05
B53: Ease of Entry – Private Market | C53: 0.05
B54: Ease of Entry – Business Development | C54: 0.05
B55: Ease of Entry – Regulatory | C55: 0.05
B56: Ease of Entry – Product Complexity | C56: 0.1
B57: Ease of Entry – Operational Complexity | C57: 0.1
B58: Localization Opportunities | C58: 0.1
B59: JMI’s Current Capabilities – Regulatory | C59: 0.05
... B62: Time to Market | C62: 0.1
C63: =SUM(C48:C62) -> 1

Sheet Opportunity Scoring Model
I2: Market | W2: Financial | AK2: Ease of Entry | BM2: Market | CA2: Financial | CO2: Ease of Entry
C4: # | E4: SBU | G4: Business Segment | I4: Opportunity | K4: Awareness & Capability | M4: Entry Barriers | Q4: Strategic Fit With JMI Portfolio | S4: Commercial Readiness | U4: Sales Force Readiness | W4: Total Market Size (in SAR Millions) | Y4: JMI Target & Growth (In SAR Millions) | AE4: Gross Margin Potential | AG4: Export Potential | AI4: Capital Requirement (in SAR Millions) | AK4: Tender Feasibility (NUPCO likelihood) | AM4: Private Market | AO4: Business Development | AQ4: Regulatory Complexity | AS4: Product Complexity | AU4: Operational Complexity | AW4: Localization Opportunities | AY4: Time To Market | BA4: Check | BC4: Score | BM4: Opportunity | BO4: Awareness & Capability | BQ4: Entry Barriers | BU4: Strategic Fit With JMI Portfolio | BW4: Commercial Readiness | BY4: Sales Force Readiness | CA4: Total Market Size (in SAR Millions) | CC4: JMI Target & Growth (In SAR Millions) | CI4: Gross Margin Potential | CK4: Export Potential | CM4: Capital Requirement | CO4: Tender Feasibility (NUPCO likelihood) | CQ4: Private Market | CS4: Business Development | CU4: Regulatory Complexity | CW4: Product Complexity | CY4: Operational Complexity | DA4: Localization Opportunities | DC4: Time To Market
M6: Remarks | Y6: Y01 | AA6: CAGR | AC6: T-Y05 | BM6: =VLOOKUP(BM4,'OSM Field'!$C$4:$E$26,3,0) -> 0 | BO6: =VLOOKUP(BO4,'OSM Field'!$C$4:$E$26,3,0) -> 0.05 | BQ6: Remarks | BS6: =VLOOKUP(BQ4,'OSM Field'!$C$4:$E$26,3,0) -> 0.05 | BU6: =VLOOKUP(BU4,'OSM Field'!$C$4:$E$26,3,0) -> 0.07 | BW6: =VLOOKUP(BW4,'OSM Field'!$C$4:$E$26,3,0) -> 0.05 | BY6: =VLOOKUP(BY4,'OSM Field'!$C$4:$E$26,3,0) -> 0.07 | CA6: =VLOOKUP(CA4,'OSM Field'!$C$4:$E$26,3,0) -> 0 | CC6: ='OSM Field'!E13 -> 0.1 | CE6: ='OSM Field'!E14 -> 0.08 | CG6: ='OSM Field'!E15 -> 0.1 | CI6: =VLOOKUP(CI4,'OSM Field'!$C$4:$E$26,3,0) -> 0.1 | CK6: =VLOOKUP(CK4,'OSM Field'!$C$4:$E$26,3,0) -> 0.04 | CM6: =VLOOKUP(CM4,'OSM Field'!$C$4:$E$26,3,0) -> 0 | CO6: =VLOOKUP(CO4,'OSM Field'!$C$4:$E$26,3,0) -> 0.07 | CQ6: =VLOOKUP(CQ4,'OSM Field'!$C$4:$E$26,3,0) -> 0.05 | CS6: =VLOOKUP(CS4,'OSM Field'!$C$4:$E$26,3,0) -> 0.05 | CU6: =VLOOKUP(CU4,'OSM Field'!$C$4:$E$26,3,0) -> 0.05 | CW6: =VLOOKUP(CW4,'OSM Field'!$C$4:$E$26,3,0) -> 0.07 | CY6: =VLOOKUP(CY4,'OSM Field'!$C$4:$E$26,3,0) -> 0.05 | DA6: =VLOOKUP(DA4,'OSM Field'!$C$4:$E$26,3,0) -> 0 | DC6: =VLOOKUP(DC4,'OSM Field'!$C$4:$E$26,3,0) -> 0.05
C8: 1 | E8: Surgical Inst. | G8: Surgical instruments | I8: High | K8: High | M8: Proper supplier | O8: Medium Barriers | Q8: Strong Fit | S8: Partially Ready | U8: Minor Additions | W8: 100 | Y8: 4 | AA8: 0.15 | AC8: =ROUND(Y8*(1+AA8)^5,0) -> 8 | AE8: High | AG8: Minimal | AI8: 0 | AK8: High | AM8: Difficult | AO8: Easy | AQ8: Easy | AS8: Moderate | AU8: Moderate | AW8: Minimal | AY8: Medium | BA8: =IF(COUNTA(AY8,AW8,AU8,AS8,AQ8,AO8,AM8,AK8,AI8,AG8,AE8,AC8,AA8,Y8,W8,U8,S8,Q8,O8,K8,I8)=21,"✓","✗") -> ✓ | BC8: =IFERROR(SUM(BM8:DC8),"") -> 3.17 | BE8: =IFERROR(LOOKUP(BC8,'OSM - Rating and Score'!$G$103:$I$108,'OSM - Rating and Score'!$C$103:$C$108),"") -> Moderate | BM8: =ROUND(VLOOKUP(I8,'OSM - Rating and Score'!$C$8:$D$13,2,0)*BM$6,2) -> 0 | BO8: =ROUND(VLOOKUP(K8,'OSM - Rating and Score'!$C$8:$D$13,2,0)*BO$6,2) -> 0.2 | BS8: =ROUND(VLOOKUP(O8,'OSM - Rating and Score'!$C$17:$D$22,2,0)*BS$6,2) -> 0.15 | BU8: =ROUND(VLOOKUP(Q8,'OSM - Rating and Score'!$C$56:$D$61,2,0)*BU$6,2) -> 0.28 | BW8: =ROUND(VLOOKUP(S8,'OSM - Rating and Score'!$C$26:$D$31,2,0)*BW$6,2) -> 0.15 | BY8: =ROUND(VLOOKUP(U8,'OSM - Rating and Score'!$C$35:$D$40,2,0)*BY$6,2) -> 0.28 | CC8: =ROUND(LOOKUP(Y8,'OSM - Rating and Score'!$G$85:$I$90,'OSM - Rating and Score'!$D$85:$D$90)*CC$6,2) -> 0.2 | CE8: =ROUND(LOOKUP(AA8,'OSM - Rating and Score'!$G$113:$I$118,'OSM - Rating and Score'!$D$113:$D$118)*CE$6,2) -> 0.08 | CG8: =ROUND(LOOKUP(AC8,'OSM - Rating and Score'!$G$94:$I$99,'OSM - Rating and Score'!$D$85:$D$90)*CG$6,2) -> 0.1 | CI8: =ROUND(VLOOKUP(AE8,'OSM - Rating and Score'!$C$8:$D$13,2,0)*CI$6,2) -> 0.4 | CK8: =ROUND(VLOOKUP(AG8,'OSM - Rating and Score'!$C$8:$D$13,2,0)*CK$6,2) -> 0.04 | CM8: 0 | CO8: =ROUND(VLOOKUP(AK8,'OSM - Rating and Score'!$C$8:$D$13,2,0)*CO$6,2) -> 0.28 | CQ8: =ROUND(VLOOKUP(AM8,'OSM - Rating and Score'!$C$47:$D$52,2,0)*CQ$6,2) -> 0.1 | CS8: =ROUND(VLOOKUP(AO8,'OSM - Rating and Score'!$C$47:$D$52,2,0)*CS$6,2) -> 0.2 | CU8: =ROUND(VLOOKUP(AQ8,'OSM - Rating and Score'!$C$47:$D$52,2,0)*CU$6,2) -> 0.2 | CW8: =ROUND(VLOOKUP(AS8,'OSM - Rating and Score'!$C$47:$D$52,2,0)*CW$6,2) -> 0.21 | CY8: =ROUND(VLOOKUP(AU8,'OSM - Rating and Score'!$C$65:$D$70,2,0)*CY$6,2) -> 0.15 | DA8: =ROUND(VLOOKUP(AW8,'OSM - Rating and Score'!$C$8:$D$13,2,0)*DA$6,2) -> 0 | DC8: =ROUND(VLOOKUP(AY8,'OSM - Rating and Score'!$C$75:$D$80,2,0)*DC$6,2) -> 0.15
C10: 2 | E10: Cardiology | G10: Cardiology intervention | I10: High | K10: High | O10: Low Barriers | Q10: Moderate Fit | S10: Partially Ready | U10: Full New Setup | W10: 350 | Y10: 5 | AA10: 0.4 | AC10: =ROUND(Y10*(1+AA10)^5,0) -> 27 | AE10: Medium | AG10: Minimal | AI10: 0 | AK10: High | AM10: Easy | AO10: Easy | AQ10: Moderate | AS10: Moderate | AU10: Moderate | AW10: Medium | AY10: Fast | BA10: =IF(COUNTA(AY10,AW10,AU10,AS10,AQ10,AO10,AM10,AK10,AI10,AG10,AE10,AC10,AA10,Y10,W10,U10,S10,Q10,O10,K10,I10)=21,"✓","✗") -> ✓ | BC10: =IFERROR(SUM(BM10:DC10),"") -> 3.48 | BE10: =IFERROR(LOOKUP(BC10,'OSM - Rating and Score'!$G$103:$I$108,'OSM - Rating and Score'!$C$103:$C$108),"") -> Moderate | BM10: =ROUND(VLOOKUP(I10,'OSM - Rating and Score'!$C$8:$D$13,2,0)*BM$6,2) -> 0 | BO10: =ROUND(VLOOKUP(K10,'OSM - Rating and Score'!$C$8:$D$13,2,0)*BO$6,2) -> 0.2 | BS10: =ROUND(VLOOKUP(O10,'OSM - Rating and Score'!$C$17:$D$22,2,0)*BS$6,2) -> 0.2 | BU10: =ROUND(VLOOKUP(Q10,'OSM - Rating and Score'!$C$56:$D$61,2,0)*BU$6,2) -> 0.21 | BW10: =ROUND(VLOOKUP(S10,'OSM - Rating and Score'!$C$26:$D$31,2,0)*BW$6,2) -> 0.15 | BY10: =ROUND(VLOOKUP(U10,'OSM - Rating and Score'!$C$35:$D$40,2,0)*BY$6,2) -> 0.07 | CC10: =ROUND(LOOKUP(Y10,'OSM - Rating and Score'!$G$85:$I$90,'OSM - Rating and Score'!$D$85:$D$90)*CC$6,2) -> 0.3 | CE10: =ROUND(LOOKUP(AA10,'OSM - Rating and Score'!$G$113:$I$118,'OSM - Rating and Score'!$D$113:$D$118)*CE$6,2) -> 0.32 | CG10: =ROUND(LOOKUP(AC10,'OSM - Rating and Score'!$G$94:$I$99,'OSM - Rating and Score'!$D$85:$D$90)*CG$6,2) -> 0.3 | CI10: =ROUND(VLOOKUP(AE10,'OSM - Rating and Score'!$C$8:$D$13,2,0)*CI$6,2) -> 0.3 | CK10: =ROUND(VLOOKUP(AG10,'OSM - Rating and Score'!$C$8:$D$13,2,0)*CK$6,2) -> 0.04 | CM10: 0 | CO10: =ROUND(VLOOKUP(AK10,'OSM - Rating and Score'!$C$8:$D$13,2,0)*CO$6,2) -> 0.28 | CQ10: =ROUND(VLOOKUP(AM10,'OSM - Rating and Score'!$C$47:$D$52,2,0)*CQ$6,2) -> 0.2 | CS10: =ROUND(VLOOKUP(AO10,'OSM - Rating and Score'!$C$47:$D$52,2,0)*CS$6,2) -> 0.2 | CU10: =ROUND(VLOOKUP(AQ10,'OSM - Rating and Score'!$C$47:$D$52,2,0)*CU$6,2) -> 0.15 | CW10: =ROUND(VLOOKUP(AS10,'OSM - Rating and Score'!$C$47:$D$52,2,0)*CW$6,2) -> 0.21 | CY10: =ROUND(VLOOKUP(AU10,'OSM - Rating and Score'!$C$65:$D$70,2,0)*CY$6,2) -> 0.15 | DA10: =ROUND(VLOOKUP(AW10,'OSM - Rating and Score'!$C$8:$D$13,2,0)*DA$6,2) -> 0 | DC10: =ROUND(VLOOKUP(AY10,'OSM - Rating and Score'!$C$75:$D$80,2,0)*DC$6,2) -> 0.2
C12: 3 | E12: Rehabilitation | G12: Rehabilitation Consumables | I12: Medium | K12: Low | O12: Low Barriers | Q12: Low Fit | S12: Limited Readiness | U12: Major New Team | W12: 60 | Y12: 2 | AA12: 0.15 | AC12: =ROUND(Y12*(1+AA12)^5,0) -> 4 | AE12: High | AG12: Minimal | AI12: 0 | AK12: Medium | AM12: Moderate | AO12: Moderate | AQ12: Easy | AS12: Moderate | AU12: Low Complex | AW12: To Be Assessed | AY12: Fast | BA12: =IF(COUNTA(AY12,AW12,AU12,AS12,AQ12,AO12,AM12,AK12,AI12,AG12,AE12,AC12,AA12,Y12,W12,U12,S12,Q12,O12,K12,I12)=21,"✓","✗") -> ✓ | BC12: =IFERROR(SUM(BM12:DC12),"") -> 2.72 | BE12: =IFERROR(LOOKUP(BC12,'OSM - Rating and Score'!$G$103:$I$108,'OSM - Rating and Score'!$C$103:$C$108),"") -> Moderate | BG12: Market size from Different source | BH12: Number of Patients | BI12: start with the Accoat essentially | BM12: =ROUND(VLOOKUP(I12,'OSM - Rating and Score'!$C$8:$D$13,2,0)*BM$6,2) -> 0 | BO12: =ROUND(VLOOKUP(K12,'OSM - Rating and Score'!$C$8:$D$13,2,0)*BO$6,2) -> 0.1 | BS12: =ROUND(VLOOKUP(O12,'OSM - Rating and Score'!$C$17:$D$22,2,0)*BS$6,2) -> 0.2 | BU12: =ROUND(VLOOKUP(Q12,'OSM - Rating and Score'!$C$56:$D$61,2,0)*BU$6,2) -> 0.14 | BW12: =ROUND(VLOOKUP(S12,'OSM - Rating and Score'!$C$26:$D$31,2,0)*BW$6,2) -> 0.1 | BY12: =ROUND(VLOOKUP(U12,'OSM - Rating and Score'!$C$35:$D$40,2,0)*BY$6,2) -> 0.14 | CC12: =ROUND(LOOKUP(Y12,'OSM - Rating and Score'!$G$85:$I$90,'OSM - Rating and Score'!$D$85:$D$90)*CC$6,2) -> 0.2 | CE12: =ROUND(LOOKUP(AA12,'OSM - Rating and Score'!$G$113:$I$118,'OSM - Rating and Score'!$D$113:$D$118)*CE$6,2) -> 0.08 | CG12: =ROUND(LOOKUP(AC12,'OSM - Rating and Score'!$G$94:$I$99,'OSM - Rating and Score'!$D$85:$D$90)*CG$6,2) -> 0 | CI12: =ROUND(VLOOKUP(AE12,'OSM - Rating and Score'!$C$8:$D$13,2,0)*CI$6,2) -> 0.4 | CK12: =ROUND(VLOOKUP(AG12,'OSM - Rating and Score'!$C$8:$D$13,2,0)*CK$6,2) -> 0.04 | CM12: 0 | CO12: =ROUND(VLOOKUP(AK12,'OSM - Rating and Score'!$C$8:$D$13,2,0)*CO$6,2) -> 0.21 | CQ12: =ROUND(VLOOKUP(AM12,'OSM - Rating and Score'!$C$47:$D$52,2,0)*CQ$6,2) -> 0.15 | CS12: =ROUND(VLOOKUP(AO12,'OSM - Rating and Score'!$C$47:$D$52,2,0)*CS$6,2) -> 0.15 | CU12: =ROUND(VLOOKUP(AQ12,'OSM - Rating and Score'!$C$47:$D$52,2,0)*CU$6,2) -> 0.2 | CW12: =ROUND(VLOOKUP(AS12,'OSM - Rating and Score'!$C$47:$D$52,2,0)*CW$6,2) -> 0.21 | CY12: =ROUND(VLOOKUP(AU12,'OSM - Rating and Score'!$C$65:$D$70,2,0)*CY$6,2) -> 0.2 | DA12: =ROUND(VLOOKUP(AW12,'OSM - Rating and Score'!$C$8:$D$13,2,0)*DA$6,2) -> 0 | DC12: =ROUND(VLOOKUP(AY12,'OSM - Rating and Score'!$C$75:$D$80,2,0)*DC$6,2) -> 0.2
C14: 4 | E14: Rehabiltation | G14: Rehabilitation Device | BA14: =IF(COUNTA(AY14,AW14,AU14,AS14,AQ14,AO14,AM14,AK14,AI14,AG14,AE14,AC14,AA14,Y14,W14,U14,S14,Q14,O14,K14,I14)=21,"✓","✗") -> ✗ | BC14: =IFERROR(SUM(BM14:DC14),"") | BE14: =IFERROR(LOOKUP(BC14,'OSM - Rating and Score'!$G$103:$I$108,'OSM - Rating and Score'!$C$103:$C$108),"") | BM14: =ROUND(VLOOKUP(I14,'OSM - Rating and Score'!$C$8:$D$13,2,0)*BM$6,2) -> #N/A | BO14: =ROUND(VLOOKUP(K14,'OSM - Rating and Score'!$C$8:$D$13,2,0)*BO$6,2) -> #N/A | BS14: =ROUND(VLOOKUP(O14,'OSM - Rating and Score'!$C$17:$D$22,2,0)*BS$6,2) -> #N/A | BU14: =ROUND(VLOOKUP(Q14,'OSM - Rating and Score'!$C$56:$D$61,2,0)*BU$6,2) -> #N/A | BW14: =ROUND(VLOOKUP(S14,'OSM - Rating and Score'!$C$26:$D$31,2,0)*BW$6,2) -> #N/A | BY14: =ROUND(VLOOKUP(U14,'OSM - Rating and Score'!$C$35:$D$40,2,0)*BY$6,2) -> #N/A | CC14: =ROUND(LOOKUP(Y14,'OSM - Rating and Score'!$G$85:$I$90,'OSM - Rating and Score'!$D$85:$D$90)*CC$6,2) -> 0 | CE14: =ROUND(LOOKUP(AA14,'OSM - Rating and Score'!$G$113:$I$118,'OSM - Rating and Score'!$D$113:$D$118)*CE$6,2) -> 0 | CG14: =ROUND(LOOKUP(AC14,'OSM - Rating and Score'!$G$94:$I$99,'OSM - Rating and Score'!$D$85:$D$90)*CG$6,2) -> 0 | CI14: =ROUND(VLOOKUP(AE14,'OSM - Rating and Score'!$C$8:$D$13,2,0)*CI$6,2) -> #N/A | CK14: =ROUND(VLOOKUP(AG14,'OSM - Rating and Score'!$C$8:$D$13,2,0)*CK$6,2) -> #N/A | CM14: 0 | CO14: =ROUND(VLOOKUP(AK14,'OSM - Rating and Score'!$C$8:$D$13,2,0)*CO$6,2) -> #N/A | CQ14: =ROUND(VLOOKUP(AM14,'OSM - Rating and Score'!$C$47:$D$52,2,0)*CQ$6,2) -> #N/A | CS14: =ROUND(VLOOKUP(AO14,'OSM - Rating and Score'!$C$47:$D$52,2,0)*CS$6,2) -> #N/A | CU14: =ROUND(VLOOKUP(AQ14,'OSM - Rating and Score'!$C$47:$D$52,2,0)*CU$6,2) -> #N/A | CW14: =ROUND(VLOOKUP(AS14,'OSM - Rating and Score'!$C$47:$D$52,2,0)*CW$6,2) -> #N/A | CY14: =ROUND(VLOOKUP(AU14,'OSM - Rating and Score'!$C$65:$D$70,2,0)*CY$6,2) -> #N/A | DA14: =ROUND(VLOOKUP(AW14,'OSM - Rating and Score'!$C$8:$D$13,2,0)*DA$6,2) -> #N/A | DC14: =ROUND(VLOOKUP(AY14,'OSM - Rating and Score'!$C$75:$D$80,2,0)*DC$6,2) -> #N/A
C16: 5 | E16: Wound care | G16: negative pressure therapy | I16: High | K16: High | O16: Low Barriers | Q16: Strong Fit | S16: Partially Ready | U16: Some New Staff | W16: 60 | Y16: 4 | AA16: 0.2 | AC16: =ROUND(Y16*(1+AA16)^5,0) -> 10 | AE16: High | AG16: Minimal | AI16: 0 | AK16: Very High | AM16: Very Difficult | AO16: Easy | AQ16: Moderate | AS16: Easy | AU16: Moderate | AW16: Medium | AY16: Very Fast | BA16: =IF(COUNTA(AY16,AW16,AU16,AS16,AQ16,AO16,AM16,AK16,AI16,AG16,AE16,AC16,AA16,Y16,W16,U16,S16,Q16,O16,K16,I16)=21,"✓","✗") -> ✓ | BC16: =IFERROR(SUM(BM16:DC16),"") -> 3.37 | BE16: =IFERROR(LOOKUP(BC16,'OSM - Rating and Score'!$G$103:$I$108,'OSM - Rating and Score'!$C$103:$C$108),"") -> Moderate | BG16: Contarcted with Sunmedic | BH16: we can partcipate in coming tender | BM16: =ROUND(VLOOKUP(I16,'OSM - Rating and Score'!$C$8:$D$13,2,0)*BM$6,2) -> 0 | BO16: =ROUND(VLOOKUP(K16,'OSM - Rating and Score'!$C$8:$D$13,2,0)*BO$6,2) -> 0.2 | BS16: =ROUND(VLOOKUP(O16,'OSM - Rating and Score'!$C$17:$D$22,2,0)*BS$6,2) -> 0.2 | BU16: =ROUND(VLOOKUP(Q16,'OSM - Rating and Score'!$C$56:$D$61,2,0)*BU$6,2) -> 0.28 | BW16: =ROUND(VLOOKUP(S16,'OSM - Rating and Score'!$C$26:$D$31,2,0)*BW$6,2) -> 0.15 | BY16: =ROUND(VLOOKUP(U16,'OSM - Rating and Score'!$C$35:$D$40,2,0)*BY$6,2) -> 0.21 | CC16: =ROUND(LOOKUP(Y16,'OSM - Rating and Score'!$G$85:$I$90,'OSM - Rating and Score'!$D$85:$D$90)*CC$6,2) -> 0.2 | CE16: =ROUND(LOOKUP(AA16,'OSM - Rating and Score'!$G$113:$I$118,'OSM - Rating and Score'!$D$113:$D$118)*CE$6,2) -> 0.16 | CG16: =ROUND(LOOKUP(AC16,'OSM - Rating and Score'!$G$94:$I$99,'OSM - Rating and Score'!$D$85:$D$90)*CG$6,2) -> 0.1 | CI16: =ROUND(VLOOKUP(AE16,'OSM - Rating and Score'!$C$8:$D$13,2,0)*CI$6,2) -> 0.4 | CK16: =ROUND(VLOOKUP(AG16,'OSM - Rating and Score'!$C$8:$D$13,2,0)*CK$6,2) -> 0.04 | CM16: 0 | CO16: =ROUND(VLOOKUP(AK16,'OSM - Rating and Score'!$C$8:$D$13,2,0)*CO$6,2) -> 0.35 | CQ16: =ROUND(VLOOKUP(AM16,'OSM - Rating and Score'!$C$47:$D$52,2,0)*CQ$6,2) -> 0.05 | CS16: =ROUND(VLOOKUP(AO16,'OSM - Rating and Score'!$C$47:$D$52,2,0)*CS$6,2) -> 0.2 | CU16: =ROUND(VLOOKUP(AQ16,'OSM - Rating and Score'!$C$47:$D$52,2,0)*CU$6,2) -> 0.15 | CW16: =ROUND(VLOOKUP(AS16,'OSM - Rating and Score'!$C$47:$D$52,2,0)*CW$6,2) -> 0.28 | CY16: =ROUND(VLOOKUP(AU16,'OSM - Rating and Score'!$C$65:$D$70,2,0)*CY$6,2) -> 0.15 | DA16: =ROUND(VLOOKUP(AW16,'OSM - Rating and Score'!$C$8:$D$13,2,0)*DA$6,2) -> 0 | DC16: =ROUND(VLOOKUP(AY16,'OSM - Rating and Score'!$C$75:$D$80,2,0)*DC$6,2) -> 0.25
C18: 6 | E18: wound care | G18: Regenerative skin | I18: High | K18: High | O18: Low Barriers | Q18: Strong Fit | S18: Partially Ready | U18: Some New Staff | W18: 40 | Y18: 3 | AA18: 0.3 | AC18: =ROUND(Y18*(1+AA18)^5,0) -> 11 | AE18: High | AG18: Medium | AK18: High | AM18: Moderate | AO18: Moderate | AQ18: Easy | AS18: Easy | AU18: Moderate | AW18: To Be Assessed | AY18: Fast | BA18: =IF(COUNTA(AY18,AW18,AU18,AS18,AQ18,AO18,AM18,AK18,AI18,AG18,AE18,AC18,AA18,Y18,W18,U18,S18,Q18,O18,K18,I18)=21,"✓","✗") -> ✗ | BC18: =IFERROR(SUM(BM18:DC18),"") -> 3.51 | BE18: =IFERROR(LOOKUP(BC18,'OSM - Rating and Score'!$G$103:$I$108,'OSM - Rating and Score'!$C$103:$C$108),"") -> Attractive | BG18: under negotation with LifeCell | BH18: if we finaliz the contract in March will catch the tender | BM18: =ROUND(VLOOKUP(I18,'OSM - Rating and Score'!$C$8:$D$13,2,0)*BM$6,2) -> 0 | BO18: =ROUND(VLOOKUP(K18,'OSM - Rating and Score'!$C$8:$D$13,2,0)*BO$6,2) -> 0.2 | BS18: =ROUND(VLOOKUP(O18,'OSM - Rating and Score'!$C$17:$D$22,2,0)*BS$6,2) -> 0.2 | BU18: =ROUND(VLOOKUP(Q18,'OSM - Rating and Score'!$C$56:$D$61,2,0)*BU$6,2) -> 0.28 | BW18: =ROUND(VLOOKUP(S18,'OSM - Rating and Score'!$C$26:$D$31,2,0)*BW$6,2) -> 0.15 | BY18: =ROUND(VLOOKUP(U18,'OSM - Rating and Score'!$C$35:$D$40,2,0)*BY$6,2) -> 0.21 | CC18: =ROUND(LOOKUP(Y18,'OSM - Rating and Score'!$G$85:$I$90,'OSM - Rating and Score'!$D$85:$D$90)*CC$6,2) -> 0.2 | CE18: =ROUND(LOOKUP(AA18,'OSM - Rating and Score'!$G$113:$I$118,'OSM - Rating and Score'!$D$113:$D$118)*CE$6,2) -> 0.24 | CG18: =ROUND(LOOKUP(AC18,'OSM - Rating and Score'!$G$94:$I$99,'OSM - Rating and Score'!$D$85:$D$90)*CG$6,2) -> 0.1 | CI18: =ROUND(VLOOKUP(AE18,'OSM - Rating and Score'!$C$8:$D$13,2,0)*CI$6,2) -> 0.4 | CK18: =ROUND(VLOOKUP(AG18,'OSM - Rating and Score'!$C$8:$D$13,2,0)*CK$6,2) -> 0.12 | CM18: 0 | CO18: =ROUND(VLOOKUP(AK18,'OSM - Rating and Score'!$C$8:$D$13,2,0)*CO$6,2) -> 0.28 | CQ18: =ROUND(VLOOKUP(AM18,'OSM - Rating and Score'!$C$47:$D$52,2,0)*CQ$6,2) -> 0.15 | CS18: =ROUND(VLOOKUP(AO18,'OSM - Rating and Score'!$C$47:$D$52,2,0)*CS$6,2) -> 0.15 | CU18: =ROUND(VLOOKUP(AQ18,'OSM - Rating and Score'!$C$47:$D$52,2,0)*CU$6,2) -> 0.2 | CW18: =ROUND(VLOOKUP(AS18,'OSM - Rating and Score'!$C$47:$D$52,2,0)*CW$6,2) -> 0.28 | CY18: =ROUND(VLOOKUP(AU18,'OSM - Rating and Score'!$C$65:$D$70,2,0)*CY$6,2) -> 0.15 | DA18: =ROUND(VLOOKUP(AW18,'OSM - Rating and Score'!$C$8:$D$13,2,0)*DA$6,2) -> 0 | DC18: =ROUND(VLOOKUP(AY18,'OSM - Rating and Score'!$C$75:$D$80,2,0)*DC$6,2) -> 0.2
C20: 7 | E20: Wound care | G20: Wound Irrigation | I20: Medium | K20: High | O20: Low Barriers | Q20: Strong Fit | S20: Partially Ready | U20: Some New Staff | W20: 30 | Y20: 2 | AA20: 0.3 | AC20: =ROUND(Y20*(1+AA20)^5,0) -> 7 | AE20: High | AG20: Minimal | AI20: 0 | AK20: Medium | AM20: Difficult | AO20: Easy | AQ20: Moderate | AS20: Very Easy | AU20: Moderate | AW20: Minimal | AY20: Medium | BA20: =IF(COUNTA(AY20,AW20,AU20,AS20,AQ20,AO20,AM20,AK20,AI20,AG20,AE20,AC20,AA20,Y20,W20,U20,S20,Q20,O20,K20,I20)=21,"✓","✗") -> ✓ | BC20: =IFERROR(SUM(BM20:DC20),"") -> 3.33 | BE20: =IFERROR(LOOKUP(BC20,'OSM - Rating and Score'!$G$103:$I$108,'OSM - Rating and Score'!$C$103:$C$108),"") -> Moderate | BG20: Pending till June eith Schulke Mayer | BM20: =ROUND(VLOOKUP(I20,'OSM - Rating and Score'!$C$8:$D$13,2,0)*BM$6,2) -> 0 | BO20: =ROUND(VLOOKUP(K20,'OSM - Rating and Score'!$C$8:$D$13,2,0)*BO$6,2) -> 0.2 | BS20: =ROUND(VLOOKUP(O20,'OSM - Rating and Score'!$C$17:$D$22,2,0)*BS$6,2) -> 0.2 | BU20: =ROUND(VLOOKUP(Q20,'OSM - Rating and Score'!$C$56:$D$61,2,0)*BU$6,2) -> 0.28 | BW20: =ROUND(VLOOKUP(S20,'OSM - Rating and Score'!$C$26:$D$31,2,0)*BW$6,2) -> 0.15 | BY20: =ROUND(VLOOKUP(U20,'OSM - Rating and Score'!$C$35:$D$40,2,0)*BY$6,2) -> 0.21 | CC20: =ROUND(LOOKUP(Y20,'OSM - Rating and Score'!$G$85:$I$90,'OSM - Rating and Score'!$D$85:$D$90)*CC$6,2) -> 0.2 | CE20: =ROUND(LOOKUP(AA20,'OSM - Rating and Score'!$G$113:$I$118,'OSM - Rating and Score'!$D$113:$D$118)*CE$6,2) -> 0.24 | CG20: =ROUND(LOOKUP(AC20,'OSM - Rating and Score'!$G$94:$I$99,'OSM - Rating and Score'!$D$85:$D$90)*CG$6,2) -> 0.1 | CI20: =ROUND(VLOOKUP(AE20,'OSM - Rating and Score'!$C$8:$D$13,2,0)*CI$6,2) -> 0.4 | CK20: =ROUND(VLOOKUP(AG20,'OSM - Rating and Score'!$C$8:$D$13,2,0)*CK$6,2) -> 0.04 | CM20: 0 | CO20: =ROUND(VLOOKUP(AK20,'OSM - Rating and Score'!$C$8:$D$13,2,0)*CO$6,2) -> 0.21 | CQ20: =ROUND(VLOOKUP(AM20,'OSM - Rating and Score'!$C$47:$D$52,2,0)*CQ$6,2) -> 0.1 | CS20: =ROUND(VLOOKUP(AO20,'OSM - Rating and Score'!$C$47:$D$52,2,0)*CS$6,2) -> 0.2 | CU20: =ROUND(VLOOKUP(AQ20,'OSM - Rating and Score'!$C$47:$D$52,2,0)*CU$6,2) -> 0.15 | CW20: =ROUND(VLOOKUP(AS20,'OSM - Rating and Score'!$C$47:$D$52,2,0)*CW$6,2) -> 0.35 | CY20: =ROUND(VLOOKUP(AU20,'OSM - Rating and Score'!$C$65:$D$70,2,0)*CY$6,2) -> 0.15 | DA20: =ROUND(VLOOKUP(AW20,'OSM - Rating and Score'!$C$8:$D$13,2,0)*DA$6,2) -> 0 | DC20: =ROUND(VLOOKUP(AY20,'OSM - Rating and Score'!$C$75:$D$80,2,0)*DC$6,2) -> 0.15
C23: 8 | E23: Nebulization | G23: Mesh Nebulizer | I23: Medium | K23: Medium | O23: Medium Barriers | Q23: Strong Fit | S23: Partially Ready | U23: Minor Additions | W23: 80 | Y23: 4 | AA23: 0.2 | AC23: =ROUND(Y23*(1+AA23)^5,0) -> 10 | AE23: High | AG23: Minimal | AK23: High | AM23: Difficult | AO23: Moderate | AQ23: Moderate | AS23: Moderate | AU23: Low Complex | AW23: Minimal | AY23: Medium | BA23: =IF(COUNTA(AY23,AW23,AU23,AS23,AQ23,AO23,AM23,AK23,AI23,AG23,AE23,AC23,AA23,Y23,W23,U23,S23,Q23,O23,K23,I23)=21,"✓","✗") -> ✗ | BC23: =IFERROR(SUM(BM23:DC23),"") -> 3.15 | BE23: =IFERROR(LOOKUP(BC23,'OSM - Rating and Score'!$G$103:$I$108,'OSM - Rating and Score'!$C$103:$C$108),"") -> Moderate | BG23: Abeer consultation | BM23: =ROUND(VLOOKUP(I23,'OSM - Rating and Score'!$C$8:$D$13,2,0)*BM$6,2) -> 0 | BO23: =ROUND(VLOOKUP(K23,'OSM - Rating and Score'!$C$8:$D$13,2,0)*BO$6,2) -> 0.15 | BS23: =ROUND(VLOOKUP(O23,'OSM - Rating and Score'!$C$17:$D$22,2,0)*BS$6,2) -> 0.15 | BU23: =ROUND(VLOOKUP(Q23,'OSM - Rating and Score'!$C$56:$D$61,2,0)*BU$6,2) -> 0.28 | BW23: =ROUND(VLOOKUP(S23,'OSM - Rating and Score'!$C$26:$D$31,2,0)*BW$6,2) -> 0.15 | BY23: =ROUND(VLOOKUP(U23,'OSM - Rating and Score'!$C$35:$D$40,2,0)*BY$6,2) -> 0.28 | CC23: =ROUND(LOOKUP(Y23,'OSM - Rating and Score'!$G$85:$I$90,'OSM - Rating and Score'!$D$85:$D$90)*CC$6,2) -> 0.2 | CE23: =ROUND(LOOKUP(AA23,'OSM - Rating and Score'!$G$113:$I$118,'OSM - Rating and Score'!$D$113:$D$118)*CE$6,2) -> 0.16 | CG23: =ROUND(LOOKUP(AC23,'OSM - Rating and Score'!$G$94:$I$99,'OSM - Rating and Score'!$D$85:$D$90)*CG$6,2) -> 0.1 | CI23: =ROUND(VLOOKUP(AE23,'OSM - Rating and Score'!$C$8:$D$13,2,0)*CI$6,2) -> 0.4 | CK23: =ROUND(VLOOKUP(AG23,'OSM - Rating and Score'!$C$8:$D$13,2,0)*CK$6,2) -> 0.04 | CM23: 0 | CO23: =ROUND(VLOOKUP(AK23,'OSM - Rating and Score'!$C$8:$D$13,2,0)*CO$6,2) -> 0.28 | CQ23: =ROUND(VLOOKUP(AM23,'OSM - Rating and Score'!$C$47:$D$52,2,0)*CQ$6,2) -> 0.1 | CS23: =ROUND(VLOOKUP(AO23,'OSM - Rating and Score'!$C$47:$D$52,2,0)*CS$6,2) -> 0.15 | CU23: =ROUND(VLOOKUP(AQ23,'OSM - Rating and Score'!$C$47:$D$52,2,0)*CU$6,2) -> 0.15 | CW23: =ROUND(VLOOKUP(AS23,'OSM - Rating and Score'!$C$47:$D$52,2,0)*CW$6,2) -> 0.21 | CY23: =ROUND(VLOOKUP(AU23,'OSM - Rating and Score'!$C$65:$D$70,2,0)*CY$6,2) -> 0.2 | DA23: =ROUND(VLOOKUP(AW23,'OSM - Rating and Score'!$C$8:$D$13,2,0)*DA$6,2) -> 0 | DC23: =ROUND(VLOOKUP(AY23,'OSM - Rating and Score'!$C$75:$D$80,2,0)*DC$6,2) -> 0.15
C25: 9 | E25: Drug delivery | G25: Atomizer | M25: need further investigation | AC25: =ROUND(Y25*(1+AA25)^5,0) -> 0 | BA25: =IF(COUNTA(AY25,AW25,AU25,AS25,AQ25,AO25,AM25,AK25,AI25,AG25,AE25,AC25,AA25,Y25,W25,U25,S25,Q25,O25,K25,I25)=21,"✓","✗") -> ✗ | BC25: =IFERROR(SUM(BM25:DC25),"") | BE25: =IFERROR(LOOKUP(BC25,'OSM - Rating and Score'!$G$103:$I$108,'OSM - Rating and Score'!$C$103:$C$108),"") | BG25: Intersurgical | BM25: =ROUND(VLOOKUP(I25,'OSM - Rating and Score'!$C$8:$D$13,2,0)*BM$6,2) -> #N/A | BO25: =ROUND(VLOOKUP(K25,'OSM - Rating and Score'!$C$8:$D$13,2,0)*BO$6,2) -> #N/A | BS25: =ROUND(VLOOKUP(O25,'OSM - Rating and Score'!$C$17:$D$22,2,0)*BS$6,2) -> #N/A | BU25: =ROUND(VLOOKUP(Q25,'OSM - Rating and Score'!$C$56:$D$61,2,0)*BU$6,2) -> #N/A | BW25: =ROUND(VLOOKUP(S25,'OSM - Rating and Score'!$C$26:$D$31,2,0)*BW$6,2) -> #N/A | BY25: =ROUND(VLOOKUP(U25,'OSM - Rating and Score'!$C$35:$D$40,2,0)*BY$6,2) -> #N/A | CC25: =ROUND(LOOKUP(Y25,'OSM - Rating and Score'!$G$85:$I$90,'OSM - Rating and Score'!$D$85:$D$90)*CC$6,2) -> 0 | CE25: =ROUND(LOOKUP(AA25,'OSM - Rating and Score'!$G$113:$I$118,'OSM - Rating and Score'!$D$113:$D$118)*CE$6,2) -> 0 | CG25: =ROUND(LOOKUP(AC25,'OSM - Rating and Score'!$G$94:$I$99,'OSM - Rating and Score'!$D$85:$D$90)*CG$6,2) -> 0 | CI25: =ROUND(VLOOKUP(AE25,'OSM - Rating and Score'!$C$8:$D$13,2,0)*CI$6,2) -> #N/A | CK25: =ROUND(VLOOKUP(AG25,'OSM - Rating and Score'!$C$8:$D$13,2,0)*CK$6,2) -> #N/A | CM25: 0 | CO25: =ROUND(VLOOKUP(AK25,'OSM - Rating and Score'!$C$8:$D$13,2,0)*CO$6,2) -> #N/A | CQ25: =ROUND(VLOOKUP(AM25,'OSM - Rating and Score'!$C$47:$D$52,2,0)*CQ$6,2) -> #N/A | CS25: =ROUND(VLOOKUP(AO25,'OSM - Rating and Score'!$C$47:$D$52,2,0)*CS$6,2) -> #N/A | CU25: =ROUND(VLOOKUP(AQ25,'OSM - Rating and Score'!$C$47:$D$52,2,0)*CU$6,2) -> #N/A | CW25: =ROUND(VLOOKUP(AS25,'OSM - Rating and Score'!$C$47:$D$52,2,0)*CW$6,2) -> #N/A | CY25: =ROUND(VLOOKUP(AU25,'OSM - Rating and Score'!$C$65:$D$70,2,0)*CY$6,2) -> #N/A | DA25: =ROUND(VLOOKUP(AW25,'OSM - Rating and Score'!$C$8:$D$13,2,0)*DA$6,2) -> #N/A | DC25: =ROUND(VLOOKUP(AY25,'OSM - Rating and Score'!$C$75:$D$80,2,0)*DC$6,2) -> #N/A
C27: 10 | E27: Surgical glue | I27: High | K27: Low | O27: High Barriers | Q27: Strong Fit | S27: Limited Readiness | U27: Some New Staff | W27: 35 | Y27: 4 | AA27: 0.1 | AC27: =ROUND(Y27*(1+AA27)^5,0) -> 6 | AE27: High | AG27: Minimal | AI27: 0 | AK27: High | AM27: Moderate | AO27: Moderate | AQ27: Moderate | AS27: Moderate | AU27: Low Complex | AW27: Minimal | AY27: Medium | BA27: =IF(COUNTA(AY27,AW27,AU27,AS27,AQ27,AO27,AM27,AK27,AI27,AG27,AE27,AC27,AA27,Y27,W27,U27,S27,Q27,O27,K27,I27)=21,"✓","✗") -> ✓ | BC27: =IFERROR(SUM(BM27:DC27),"") -> 2.9 | BE27: =IFERROR(LOOKUP(BC27,'OSM - Rating and Score'!$G$103:$I$108,'OSM - Rating and Score'!$C$103:$C$108),"") -> Moderate | BM27: =ROUND(VLOOKUP(I27,'OSM - Rating and Score'!$C$8:$D$13,2,0)*BM$6,2) -> 0 | BO27: =ROUND(VLOOKUP(K27,'OSM - Rating and Score'!$C$8:$D$13,2,0)*BO$6,2) -> 0.1 | BS27: =ROUND(VLOOKUP(O27,'OSM - Rating and Score'!$C$17:$D$22,2,0)*BS$6,2) -> 0.1 | BU27: =ROUND(VLOOKUP(Q27,'OSM - Rating and Score'!$C$56:$D$61,2,0)*BU$6,2) -> 0.28 | BW27: =ROUND(VLOOKUP(S27,'OSM - Rating and Score'!$C$26:$D$31,2,0)*BW$6,2) -> 0.1 | BY27: =ROUND(VLOOKUP(U27,'OSM - Rating and Score'!$C$35:$D$40,2,0)*BY$6,2) -> 0.21 | CC27: =ROUND(LOOKUP(Y27,'OSM - Rating and Score'!$G$85:$I$90,'OSM - Rating and Score'!$D$85:$D$90)*CC$6,2) -> 0.2 | CE27: =ROUND(LOOKUP(AA27,'OSM - Rating and Score'!$G$113:$I$118,'OSM - Rating and Score'!$D$113:$D$118)*CE$6,2) -> 0.08 | CG27: =ROUND(LOOKUP(AC27,'OSM - Rating and Score'!$G$94:$I$99,'OSM - Rating and Score'!$D$85:$D$90)*CG$6,2) -> 0.1 | CI27: =ROUND(VLOOKUP(AE27,'OSM - Rating and Score'!$C$8:$D$13,2,0)*CI$6,2) -> 0.4 | CK27: =ROUND(VLOOKUP(AG27,'OSM - Rating and Score'!$C$8:$D$13,2,0)*CK$6,2) -> 0.04 | CM27: 0 | CO27: =ROUND(VLOOKUP(AK27,'OSM - Rating and Score'!$C$8:$D$13,2,0)*CO$6,2) -> 0.28 | CQ27: =ROUND(VLOOKUP(AM27,'OSM - Rating and Score'!$C$47:$D$52,2,0)*CQ$6,2) -> 0.15 | CS27: =ROUND(VLOOKUP(AO27,'OSM - Rating and Score'!$C$47:$D$52,2,0)*CS$6,2) -> 0.15 | CU27: =ROUND(VLOOKUP(AQ27,'OSM - Rating and Score'!$C$47:$D$52,2,0)*CU$6,2) -> 0.15 | CW27: =ROUND(VLOOKUP(AS27,'OSM - Rating and Score'!$C$47:$D$52,2,0)*CW$6,2) -> 0.21 | CY27: =ROUND(VLOOKUP(AU27,'OSM - Rating and Score'!$C$65:$D$70,2,0)*CY$6,2) -> 0.2 | DA27: =ROUND(VLOOKUP(AW27,'OSM - Rating and Score'!$C$8:$D$13,2,0)*DA$6,2) -> 0 | DC27: =ROUND(VLOOKUP(AY27,'OSM - Rating and Score'!$C$75:$D$80,2,0)*DC$6,2) -> 0.15
C29: 11 | E29: Chyme reinfusion | AC29: =ROUND(Y29*(1+AA29)^5,0) -> 0 | BA29: =IF(COUNTA(AY29,AW29,AU29,AS29,AQ29,AO29,AM29,AK29,AI29,AG29,AE29,AC29,AA29,Y29,W29,U29,S29,Q29,O29,K29,I29)=21,"✓","✗") -> ✗ | BC29: =IFERROR(SUM(BM29:DC29),"") | BE29: =IFERROR(LOOKUP(BC29,'OSM - Rating and Score'!$G$103:$I$108,'OSM - Rating and Score'!$C$103:$C$108),"") | BG29: Communicate with the customer (Nutrient , Colerectal ) | BM29: =ROUND(VLOOKUP(I29,'OSM - Rating and Score'!$C$8:$D$13,2,0)*BM$6,2) -> #N/A | BO29: =ROUND(VLOOKUP(K29,'OSM - Rating and Score'!$C$8:$D$13,2,0)*BO$6,2) -> #N/A | BS29: =ROUND(VLOOKUP(O29,'OSM - Rating and Score'!$C$17:$D$22,2,0)*BS$6,2) -> #N/A | BU29: =ROUND(VLOOKUP(Q29,'OSM - Rating and Score'!$C$56:$D$61,2,0)*BU$6,2) -> #N/A | BW29: =ROUND(VLOOKUP(S29,'OSM - Rating and Score'!$C$26:$D$31,2,0)*BW$6,2) -> #N/A | BY29: =ROUND(VLOOKUP(U29,'OSM - Rating and Score'!$C$35:$D$40,2,0)*BY$6,2) -> #N/A | CC29: =ROUND(LOOKUP(Y29,'OSM - Rating and Score'!$G$85:$I$90,'OSM - Rating and Score'!$D$85:$D$90)*CC$6,2) -> 0 | CE29: =ROUND(LOOKUP(AA29,'OSM - Rating and Score'!$G$113:$I$118,'OSM - Rating and Score'!$D$113:$D$118)*CE$6,2) -> 0 | CG29: =ROUND(LOOKUP(AC29,'OSM - Rating and Score'!$G$94:$I$99,'OSM - Rating and Score'!$D$85:$D$90)*CG$6,2) -> 0 | CI29: =ROUND(VLOOKUP(AE29,'OSM - Rating and Score'!$C$8:$D$13,2,0)*CI$6,2) -> #N/A | CK29: =ROUND(VLOOKUP(AG29,'OSM - Rating and Score'!$C$8:$D$13,2,0)*CK$6,2) -> #N/A | CM29: 0 | CO29: =ROUND(VLOOKUP(AK29,'OSM - Rating and Score'!$C$8:$D$13,2,0)*CO$6,2) -> #N/A | CQ29: =ROUND(VLOOKUP(AM29,'OSM - Rating and Score'!$C$47:$D$52,2,0)*CQ$6,2) -> #N/A | CS29: =ROUND(VLOOKUP(AO29,'OSM - Rating and Score'!$C$47:$D$52,2,0)*CS$6,2) -> #N/A | CU29: =ROUND(VLOOKUP(AQ29,'OSM - Rating and Score'!$C$47:$D$52,2,0)*CU$6,2) -> #N/A | CW29: =ROUND(VLOOKUP(AS29,'OSM - Rating and Score'!$C$47:$D$52,2,0)*CW$6,2) -> #N/A | CY29: =ROUND(VLOOKUP(AU29,'OSM - Rating and Score'!$C$65:$D$70,2,0)*CY$6,2) -> #N/A | DA29: =ROUND(VLOOKUP(AW29,'OSM - Rating and Score'!$C$8:$D$13,2,0)*DA$6,2) -> #N/A | DC29: =ROUND(VLOOKUP(AY29,'OSM - Rating and Score'!$C$75:$D$80,2,0)*DC$6,2) -> #N/A
C31: 12 | E31: Peripeheral intervention intervention | I31: High | K31: Medium | O31: Medium Barriers | Q31: Low Fit | S31: Partially Ready | U31: Some New Staff | W31: 250 | Y31: 2 | AA31: 0.5 | AC31: =ROUND(Y31*(1+AA31)^5,0) -> 15 | AE31: Medium | AG31: Minimal | AK31: High | AM31: Easy | AO31: Moderate | AQ31: Moderate | AS31: Moderate | AU31: Complex | AW31: Medium | AY31: Fast | BA31: =IF(COUNTA(AY31,AW31,AU31,AS31,AQ31,AO31,AM31,AK31,AI31,AG31,AE31,AC31,AA31,Y31,W31,U31,S31,Q31,O31,K31,I31)=21,"✓","✗") -> ✗ | BC31: =IFERROR(SUM(BM31:DC31),"") -> 3.23 | BE31: =IFERROR(LOOKUP(BC31,'OSM - Rating and Score'!$G$103:$I$108,'OSM - Rating and Score'!$C$103:$C$108),"") -> Moderate | BM31: =ROUND(VLOOKUP(I31,'OSM - Rating and Score'!$C$8:$D$13,2,0)*BM$6,2) -> 0 | BO31: =ROUND(VLOOKUP(K31,'OSM - Rating and Score'!$C$8:$D$13,2,0)*BO$6,2) -> 0.15 | BS31: =ROUND(VLOOKUP(O31,'OSM - Rating and Score'!$C$17:$D$22,2,0)*BS$6,2) -> 0.15 | BU31: =ROUND(VLOOKUP(Q31,'OSM - Rating and Score'!$C$56:$D$61,2,0)*BU$6,2) -> 0.14 | BW31: =ROUND(VLOOKUP(S31,'OSM - Rating and Score'!$C$26:$D$31,2,0)*BW$6,2) -> 0.15 | BY31: =ROUND(VLOOKUP(U31,'OSM - Rating and Score'!$C$35:$D$40,2,0)*BY$6,2) -> 0.21 | CC31: =ROUND(LOOKUP(Y31,'OSM - Rating and Score'!$G$85:$I$90,'OSM - Rating and Score'!$D$85:$D$90)*CC$6,2) -> 0.2 | CE31: =ROUND(LOOKUP(AA31,'OSM - Rating and Score'!$G$113:$I$118,'OSM - Rating and Score'!$D$113:$D$118)*CE$6,2) -> 0.4 | CG31: =ROUND(LOOKUP(AC31,'OSM - Rating and Score'!$G$94:$I$99,'OSM - Rating and Score'!$D$85:$D$90)*CG$6,2) -> 0.2 | CI31: =ROUND(VLOOKUP(AE31,'OSM - Rating and Score'!$C$8:$D$13,2,0)*CI$6,2) -> 0.3 | CK31: =ROUND(VLOOKUP(AG31,'OSM - Rating and Score'!$C$8:$D$13,2,0)*CK$6,2) -> 0.04 | CM31: 0 | CO31: =ROUND(VLOOKUP(AK31,'OSM - Rating and Score'!$C$8:$D$13,2,0)*CO$6,2) -> 0.28 | CQ31: =ROUND(VLOOKUP(AM31,'OSM - Rating and Score'!$C$47:$D$52,2,0)*CQ$6,2) -> 0.2 | CS31: =ROUND(VLOOKUP(AO31,'OSM - Rating and Score'!$C$47:$D$52,2,0)*CS$6,2) -> 0.15 | CU31: =ROUND(VLOOKUP(AQ31,'OSM - Rating and Score'!$C$47:$D$52,2,0)*CU$6,2) -> 0.15 | CW31: =ROUND(VLOOKUP(AS31,'OSM - Rating and Score'!$C$47:$D$52,2,0)*CW$6,2) -> 0.21 | CY31: =ROUND(VLOOKUP(AU31,'OSM - Rating and Score'!$C$65:$D$70,2,0)*CY$6,2) -> 0.1 | DA31: =ROUND(VLOOKUP(AW31,'OSM - Rating and Score'!$C$8:$D$13,2,0)*DA$6,2) -> 0 | DC31: =ROUND(VLOOKUP(AY31,'OSM - Rating and Score'!$C$75:$D$80,2,0)*DC$6,2) -> 0.2
C33: 14 | E33: Neurovascular | I33: High | K33: Medium | O33: High Barriers | Q33: Low Fit | S33: Limited Readiness | U33: Minor Additions | W33: 150 | Y33: 2 | AA33: 0.4 | AC33: =ROUND(Y33*(1+AA33)^5,0) -> 11 | AE33: High | AG33: Minimal | AK33: Low | AM33: Moderate | AO33: Moderate | AQ33: Moderate | AS33: Moderate | AU33: Complex | AW33: Minimal | AY33: Medium | BA33: =IF(COUNTA(AY33,AW33,AU33,AS33,AQ33,AO33,AM33,AK33,AI33,AG33,AE33,AC33,AA33,Y33,W33,U33,S33,Q33,O33,K33,I33)=21,"✓","✗") -> ✗ | BC33: =IFERROR(SUM(BM33:DC33),"") -> 2.88 | BE33: =IFERROR(LOOKUP(BC33,'OSM - Rating and Score'!$G$103:$I$108,'OSM - Rating and Score'!$C$103:$C$108),"") -> Moderate | BG33: Exploring COOK medical | BM33: =ROUND(VLOOKUP(I33,'OSM - Rating and Score'!$C$8:$D$13,2,0)*BM$6,2) -> 0 | BO33: =ROUND(VLOOKUP(K33,'OSM - Rating and Score'!$C$8:$D$13,2,0)*BO$6,2) -> 0.15 | BS33: =ROUND(VLOOKUP(O33,'OSM - Rating and Score'!$C$17:$D$22,2,0)*BS$6,2) -> 0.1 | BU33: =ROUND(VLOOKUP(Q33,'OSM - Rating and Score'!$C$56:$D$61,2,0)*BU$6,2) -> 0.14 | BW33: =ROUND(VLOOKUP(S33,'OSM - Rating and Score'!$C$26:$D$31,2,0)*BW$6,2) -> 0.1 | BY33: =ROUND(VLOOKUP(U33,'OSM - Rating and Score'!$C$35:$D$40,2,0)*BY$6,2) -> 0.28 | CC33: =ROUND(LOOKUP(Y33,'OSM - Rating and Score'!$G$85:$I$90,'OSM - Rating and Score'!$D$85:$D$90)*CC$6,2) -> 0.2 | CE33: =ROUND(LOOKUP(AA33,'OSM - Rating and Score'!$G$113:$I$118,'OSM - Rating and Score'!$D$113:$D$118)*CE$6,2) -> 0.32 | CG33: =ROUND(LOOKUP(AC33,'OSM - Rating and Score'!$G$94:$I$99,'OSM - Rating and Score'!$D$85:$D$90)*CG$6,2) -> 0.1 | CI33: =ROUND(VLOOKUP(AE33,'OSM - Rating and Score'!$C$8:$D$13,2,0)*CI$6,2) -> 0.4 | CK33: =ROUND(VLOOKUP(AG33,'OSM - Rating and Score'!$C$8:$D$13,2,0)*CK$6,2) -> 0.04 | CM33: 0 | CO33: =ROUND(VLOOKUP(AK33,'OSM - Rating and Score'!$C$8:$D$13,2,0)*CO$6,2) -> 0.14 | CQ33: =ROUND(VLOOKUP(AM33,'OSM - Rating and Score'!$C$47:$D$52,2,0)*CQ$6,2) -> 0.15 | CS33: =ROUND(VLOOKUP(AO33,'OSM - Rating and Score'!$C$47:$D$52,2,0)*CS$6,2) -> 0.15 | CU33: =ROUND(VLOOKUP(AQ33,'OSM - Rating and Score'!$C$47:$D$52,2,0)*CU$6,2) -> 0.15 | CW33: =ROUND(VLOOKUP(AS33,'OSM - Rating and Score'!$C$47:$D$52,2,0)*CW$6,2) -> 0.21 | CY33: =ROUND(VLOOKUP(AU33,'OSM - Rating and Score'!$C$65:$D$70,2,0)*CY$6,2) -> 0.1 | DA33: =ROUND(VLOOKUP(AW33,'OSM - Rating and Score'!$C$8:$D$13,2,0)*DA$6,2) -> 0 | DC33: =ROUND(VLOOKUP(AY33,'OSM - Rating and Score'!$C$75:$D$80,2,0)*DC$6,2) -> 0.15
C35: 15 | E35: Strcture haert disease | I35: High | K35: Medium | O35: Medium Barriers | Q35: Low Fit | S35: Limited Readiness | U35: Some New Staff | W35: 160 | Y35: 2 | AA35: 0.5 | AC35: =ROUND(Y35*(1+AA35)^5,0) -> 15 | AE35: High | AG35: Minimal | AK35: Medium | AM35: Difficult | AO35: Moderate | AQ35: Moderate | AS35: Difficult | AU35: Moderate | AW35: Minimal | AY35: Medium | BA35: =IF(COUNTA(AY35,AW35,AU35,AS35,AQ35,AO35,AM35,AK35,AI35,AG35,AE35,AC35,AA35,Y35,W35,U35,S35,Q35,O35,K35,I35)=21,"✓","✗") -> ✗ | BC35: =IFERROR(SUM(BM35:DC35),"") -> 3.04 | BE35: =IFERROR(LOOKUP(BC35,'OSM - Rating and Score'!$G$103:$I$108,'OSM - Rating and Score'!$C$103:$C$108),"") -> Moderate | BG35: Connect with BALT | BM35: =ROUND(VLOOKUP(I35,'OSM - Rating and Score'!$C$8:$D$13,2,0)*BM$6,2) -> 0 | BO35: =ROUND(VLOOKUP(K35,'OSM - Rating and Score'!$C$8:$D$13,2,0)*BO$6,2) -> 0.15 | BS35: =ROUND(VLOOKUP(O35,'OSM - Rating and Score'!$C$17:$D$22,2,0)*BS$6,2) -> 0.15 | BU35: =ROUND(VLOOKUP(Q35,'OSM - Rating and Score'!$C$56:$D$61,2,0)*BU$6,2) -> 0.14 | BW35: =ROUND(VLOOKUP(S35,'OSM - Rating and Score'!$C$26:$D$31,2,0)*BW$6,2) -> 0.1 | BY35: =ROUND(VLOOKUP(U35,'OSM - Rating and Score'!$C$35:$D$40,2,0)*BY$6,2) -> 0.21 | CC35: =ROUND(LOOKUP(Y35,'OSM - Rating and Score'!$G$85:$I$90,'OSM - Rating and Score'!$D$85:$D$90)*CC$6,2) -> 0.2 | CE35: =ROUND(LOOKUP(AA35,'OSM - Rating and Score'!$G$113:$I$118,'OSM - Rating and Score'!$D$113:$D$118)*CE$6,2) -> 0.4 | CG35: =ROUND(LOOKUP(AC35,'OSM - Rating and Score'!$G$94:$I$99,'OSM - Rating and Score'!$D$85:$D$90)*CG$6,2) -> 0.2 | CI35: =ROUND(VLOOKUP(AE35,'OSM - Rating and Score'!$C$8:$D$13,2,0)*CI$6,2) -> 0.4 | CK35: =ROUND(VLOOKUP(AG35,'OSM - Rating and Score'!$C$8:$D$13,2,0)*CK$6,2) -> 0.04 | CM35: 0 | CO35: =ROUND(VLOOKUP(AK35,'OSM - Rating and Score'!$C$8:$D$13,2,0)*CO$6,2) -> 0.21 | CQ35: =ROUND(VLOOKUP(AM35,'OSM - Rating and Score'!$C$47:$D$52,2,0)*CQ$6,2) -> 0.1 | CS35: =ROUND(VLOOKUP(AO35,'OSM - Rating and Score'!$C$47:$D$52,2,0)*CS$6,2) -> 0.15 | CU35: =ROUND(VLOOKUP(AQ35,'OSM - Rating and Score'!$C$47:$D$52,2,0)*CU$6,2) -> 0.15 | CW35: =ROUND(VLOOKUP(AS35,'OSM - Rating and Score'!$C$47:$D$52,2,0)*CW$6,2) -> 0.14 | CY35: =ROUND(VLOOKUP(AU35,'OSM - Rating and Score'!$C$65:$D$70,2,0)*CY$6,2) -> 0.15 | DA35: =ROUND(VLOOKUP(AW35,'OSM - Rating and Score'!$C$8:$D$13,2,0)*DA$6,2) -> 0 | DC35: =ROUND(VLOOKUP(AY35,'OSM - Rating and Score'!$C$75:$D$80,2,0)*DC$6,2) -> 0.15
C37: 16 | E37: Vascular Surgery | I37: Medium | K37: Medium | O37: Medium Barriers | Q37: Low Fit | S37: Limited Readiness | U37: Some New Staff | W37: 100 | Y37: 1 | AA37: 0.2 | AC37: =ROUND(Y37*(1+AA37)^5,0) -> 2 | AE37: Medium | AG37: Minimal | AK37: Medium | AM37: Moderate | AO37: Moderate | AQ37: Easy | AS37: Easy | AU37: Moderate | AW37: Minimal | AY37: Fast | BA37: =IF(COUNTA(AY37,AW37,AU37,AS37,AQ37,AO37,AM37,AK37,AI37,AG37,AE37,AC37,AA37,Y37,W37,U37,S37,Q37,O37,K37,I37)=21,"✓","✗") -> ✗ | BC37: =IFERROR(SUM(BM37:DC37),"") -> 2.79 | BE37: =IFERROR(LOOKUP(BC37,'OSM - Rating and Score'!$G$103:$I$108,'OSM - Rating and Score'!$C$103:$C$108),"") -> Moderate | BG37: Explore the Dialysis | BM37: =ROUND(VLOOKUP(I37,'OSM - Rating and Score'!$C$8:$D$13,2,0)*BM$6,2) -> 0 | BO37: =ROUND(VLOOKUP(K37,'OSM - Rating and Score'!$C$8:$D$13,2,0)*BO$6,2) -> 0.15 | BS37: =ROUND(VLOOKUP(O37,'OSM - Rating and Score'!$C$17:$D$22,2,0)*BS$6,2) -> 0.15 | BU37: =ROUND(VLOOKUP(Q37,'OSM - Rating and Score'!$C$56:$D$61,2,0)*BU$6,2) -> 0.14 | BW37: =ROUND(VLOOKUP(S37,'OSM - Rating and Score'!$C$26:$D$31,2,0)*BW$6,2) -> 0.1 | BY37: =ROUND(VLOOKUP(U37,'OSM - Rating and Score'!$C$35:$D$40,2,0)*BY$6,2) -> 0.21 | CC37: =ROUND(LOOKUP(Y37,'OSM - Rating and Score'!$G$85:$I$90,'OSM - Rating and Score'!$D$85:$D$90)*CC$6,2) -> 0.2 | CE37: =ROUND(LOOKUP(AA37,'OSM - Rating and Score'!$G$113:$I$118,'OSM - Rating and Score'!$D$113:$D$118)*CE$6,2) -> 0.16 | CG37: =ROUND(LOOKUP(AC37,'OSM - Rating and Score'!$G$94:$I$99,'OSM - Rating and Score'!$D$85:$D$90)*CG$6,2) -> 0 | CI37: =ROUND(VLOOKUP(AE37,'OSM - Rating and Score'!$C$8:$D$13,2,0)*CI$6,2) -> 0.3 | CK37: =ROUND(VLOOKUP(AG37,'OSM - Rating and Score'!$C$8:$D$13,2,0)*CK$6,2) -> 0.04 | CM37: 0 | CO37: =ROUND(VLOOKUP(AK37,'OSM - Rating and Score'!$C$8:$D$13,2,0)*CO$6,2) -> 0.21 | CQ37: =ROUND(VLOOKUP(AM37,'OSM - Rating and Score'!$C$47:$D$52,2,0)*CQ$6,2) -> 0.15 | CS37: =ROUND(VLOOKUP(AO37,'OSM - Rating and Score'!$C$47:$D$52,2,0)*CS$6,2) -> 0.15 | CU37: =ROUND(VLOOKUP(AQ37,'OSM - Rating and Score'!$C$47:$D$52,2,0)*CU$6,2) -> 0.2 | CW37: =ROUND(VLOOKUP(AS37,'OSM - Rating and Score'!$C$47:$D$52,2,0)*CW$6,2) -> 0.28 | CY37: =ROUND(VLOOKUP(AU37,'OSM - Rating and Score'!$C$65:$D$70,2,0)*CY$6,2) -> 0.15 | DA37: =ROUND(VLOOKUP(AW37,'OSM - Rating and Score'!$C$8:$D$13,2,0)*DA$6,2) -> 0 | DC37: =ROUND(VLOOKUP(AY37,'OSM - Rating and Score'!$C$75:$D$80,2,0)*DC$6,2) -> 0.2
C39: 17 | E39: Cardiothoracic Surgery | I39: High | K39: Medium | O39: Medium Barriers | Q39: Low Fit | S39: Limited Readiness | U39: Some New Staff | W39: 300 | Y39: 3 | AA39: 0.4 | AC39: =ROUND(Y39*(1+AA39)^5,0) -> 16 | AE39: High | AG39: Minimal | AK39: Medium | AM39: Moderate | AO39: Moderate | AQ39: Easy | AS39: Moderate | AU39: Low Complex | AW39: Low | AY39: Medium | BA39: =IF(COUNTA(AY39,AW39,AU39,AS39,AQ39,AO39,AM39,AK39,AI39,AG39,AE39,AC39,AA39,Y39,W39,U39,S39,Q39,O39,K39,I39)=21,"✓","✗") -> ✗ | BC39: =IFERROR(SUM(BM39:DC39),"") -> 3.18 | BE39: =IFERROR(LOOKUP(BC39,'OSM - Rating and Score'!$G$103:$I$108,'OSM - Rating and Score'!$C$103:$C$108),"") -> Moderate | BM39: =ROUND(VLOOKUP(I39,'OSM - Rating and Score'!$C$8:$D$13,2,0)*BM$6,2) -> 0 | BO39: =ROUND(VLOOKUP(K39,'OSM - Rating and Score'!$C$8:$D$13,2,0)*BO$6,2) -> 0.15 | BS39: =ROUND(VLOOKUP(O39,'OSM - Rating and Score'!$C$17:$D$22,2,0)*BS$6,2) -> 0.15 | BU39: =ROUND(VLOOKUP(Q39,'OSM - Rating and Score'!$C$56:$D$61,2,0)*BU$6,2) -> 0.14 | BW39: =ROUND(VLOOKUP(S39,'OSM - Rating and Score'!$C$26:$D$31,2,0)*BW$6,2) -> 0.1 | BY39: =ROUND(VLOOKUP(U39,'OSM - Rating and Score'!$C$35:$D$40,2,0)*BY$6,2) -> 0.21 | CC39: =ROUND(LOOKUP(Y39,'OSM - Rating and Score'!$G$85:$I$90,'OSM - Rating and Score'!$D$85:$D$90)*CC$6,2) -> 0.2 | CE39: =ROUND(LOOKUP(AA39,'OSM - Rating and Score'!$G$113:$I$118,'OSM - Rating and Score'!$D$113:$D$118)*CE$6,2) -> 0.32 | CG39: =ROUND(LOOKUP(AC39,'OSM - Rating and Score'!$G$94:$I$99,'OSM - Rating and Score'!$D$85:$D$90)*CG$6,2) -> 0.2 | CI39: =ROUND(VLOOKUP(AE39,'OSM - Rating and Score'!$C$8:$D$13,2,0)*CI$6,2) -> 0.4 | CK39: =ROUND(VLOOKUP(AG39,'OSM - Rating and Score'!$C$8:$D$13,2,0)*CK$6,2) -> 0.04 | CM39: 0 | CO39: =ROUND(VLOOKUP(AK39,'OSM - Rating and Score'!$C$8:$D$13,2,0)*CO$6,2) -> 0.21 | CQ39: =ROUND(VLOOKUP(AM39,'OSM - Rating and Score'!$C$47:$D$52,2,0)*CQ$6,2) -> 0.15 | CS39: =ROUND(VLOOKUP(AO39,'OSM - Rating and Score'!$C$47:$D$52,2,0)*CS$6,2) -> 0.15 | CU39: =ROUND(VLOOKUP(AQ39,'OSM - Rating and Score'!$C$47:$D$52,2,0)*CU$6,2) -> 0.2 | CW39: =ROUND(VLOOKUP(AS39,'OSM - Rating and Score'!$C$47:$D$52,2,0)*CW$6,2) -> 0.21 | CY39: =ROUND(VLOOKUP(AU39,'OSM - Rating and Score'!$C$65:$D$70,2,0)*CY$6,2) -> 0.2 | DA39: =ROUND(VLOOKUP(AW39,'OSM - Rating and Score'!$C$8:$D$13,2,0)*DA$6,2) -> 0 | DC39: =ROUND(VLOOKUP(AY39,'OSM - Rating and Score'!$C$75:$D$80,2,0)*DC$6,2) -> 0.15
AA40: 20
C41: 18 | E41: Vascular access | I41: High | K41: High | O41: Low Barriers | Q41: Strong Fit | S41: Ready | U41: No New Team | W41: 80 | Y41: 5 | AA41: 0.2 | AC41: =ROUND(Y41*(1+AA41)^5,0) -> 12 | AE41: Medium | AG41: Minimal | AK41: High | AM41: Easy | AO41: Moderate | AQ41: Moderate | AS41: Easy | AU41: Low Complex | AW41: Medium | AY41: Fast | BA41: =IF(COUNTA(AY41,AW41,AU41,AS41,AQ41,AO41,AM41,AK41,AI41,AG41,AE41,AC41,AA41,Y41,W41,U41,S41,Q41,O41,K41,I41)=21,"✓","✗") -> ✗ | BC41: =IFERROR(SUM(BM41:DC41),"") -> 3.59 | BE41: =IFERROR(LOOKUP(BC41,'OSM - Rating and Score'!$G$103:$I$108,'OSM - Rating and Score'!$C$103:$C$108),"") -> Attractive | BG41: CVS in the tender communication | BM41: =ROUND(VLOOKUP(I41,'OSM - Rating and Score'!$C$8:$D$13,2,0)*BM$6,2) -> 0 | BO41: =ROUND(VLOOKUP(K41,'OSM - Rating and Score'!$C$8:$D$13,2,0)*BO$6,2) -> 0.2 | BS41: =ROUND(VLOOKUP(O41,'OSM - Rating and Score'!$C$17:$D$22,2,0)*BS$6,2) -> 0.2 | BU41: =ROUND(VLOOKUP(Q41,'OSM - Rating and Score'!$C$56:$D$61,2,0)*BU$6,2) -> 0.28 | BW41: =ROUND(VLOOKUP(S41,'OSM - Rating and Score'!$C$26:$D$31,2,0)*BW$6,2) -> 0.2 | BY41: =ROUND(VLOOKUP(U41,'OSM - Rating and Score'!$C$35:$D$40,2,0)*BY$6,2) -> 0.35 | CC41: =ROUND(LOOKUP(Y41,'OSM - Rating and Score'!$G$85:$I$90,'OSM - Rating and Score'!$D$85:$D$90)*CC$6,2) -> 0.3 | CE41: =ROUND(LOOKUP(AA41,'OSM - Rating and Score'!$G$113:$I$118,'OSM - Rating and Score'!$D$113:$D$118)*CE$6,2) -> 0.16 | CG41: =ROUND(LOOKUP(AC41,'OSM - Rating and Score'!$G$94:$I$99,'OSM - Rating and Score'!$D$85:$D$90)*CG$6,2) -> 0.1 | CI41: =ROUND(VLOOKUP(AE41,'OSM - Rating and Score'!$C$8:$D$13,2,0)*CI$6,2) -> 0.3 | CK41: =ROUND(VLOOKUP(AG41,'OSM - Rating and Score'!$C$8:$D$13,2,0)*CK$6,2) -> 0.04 | CM41: 0 | CO41: =ROUND(VLOOKUP(AK41,'OSM - Rating and Score'!$C$8:$D$13,2,0)*CO$6,2) -> 0.28 | CQ41: =ROUND(VLOOKUP(AM41,'OSM - Rating and Score'!$C$47:$D$52,2,0)*CQ$6,2) -> 0.2 | CS41: =ROUND(VLOOKUP(AO41,'OSM - Rating and Score'!$C$47:$D$52,2,0)*CS$6,2) -> 0.15 | CU41: =ROUND(VLOOKUP(AQ41,'OSM - Rating and Score'!$C$47:$D$52,2,0)*CU$6,2) -> 0.15 | CW41: =ROUND(VLOOKUP(AS41,'OSM - Rating and Score'!$C$47:$D$52,2,0)*CW$6,2) -> 0.28 | CY41: =ROUND(VLOOKUP(AU41,'OSM - Rating and Score'!$C$65:$D$70,2,0)*CY$6,2) -> 0.2 | DA41: =ROUND(VLOOKUP(AW41,'OSM - Rating and Score'!$C$8:$D$13,2,0)*DA$6,2) -> 0 | DC41: =ROUND(VLOOKUP(AY41,'OSM - Rating and Score'!$C$75:$D$80,2,0)*DC$6,2) -> 0.2
C43: 19 | E43: Cath Lock Solution | G43: Theradial | I43: High | K43: High | O43: Medium Barriers | Q43: Moderate Fit | S43: Partially Ready | U43: Major New Team | W43: 100 | Y43: 5 | AA43: 0.4 | AC43: =ROUND(Y43*(1+AA43)^5,0) -> 27 | AE43: High | AG43: To Be Assessed | AK43: High | AM43: Moderate | AO43: Moderate | AQ43: Difficult | AS43: Moderate | AU43: Low Complex | AW43: High | AY43: Fast | BA43: =IF(COUNTA(AY43,AW43,AU43,AS43,AQ43,AO43,AM43,AK43,AI43,AG43,AE43,AC43,AA43,Y43,W43,U43,S43,Q43,O43,K43,I43)=21,"✓","✗") -> ✗ | BC43: =IFERROR(SUM(BM43:DC43),"") -> 3.46 | BE43: =IFERROR(LOOKUP(BC43,'OSM - Rating and Score'!$G$103:$I$108,'OSM - Rating and Score'!$C$103:$C$108),"") -> Moderate | BG43: Contarcting with Thredial / Starting Regsiteration with RA | BM43: =ROUND(VLOOKUP(I43,'OSM - Rating and Score'!$C$8:$D$13,2,0)*BM$6,2) -> 0 | BO43: =ROUND(VLOOKUP(K43,'OSM - Rating and Score'!$C$8:$D$13,2,0)*BO$6,2) -> 0.2 | BS43: =ROUND(VLOOKUP(O43,'OSM - Rating and Score'!$C$17:$D$22,2,0)*BS$6,2) -> 0.15 | BU43: =ROUND(VLOOKUP(Q43,'OSM - Rating and Score'!$C$56:$D$61,2,0)*BU$6,2) -> 0.21 | BW43: =ROUND(VLOOKUP(S43,'OSM - Rating and Score'!$C$26:$D$31,2,0)*BW$6,2) -> 0.15 | BY43: =ROUND(VLOOKUP(U43,'OSM - Rating and Score'!$C$35:$D$40,2,0)*BY$6,2) -> 0.14 | CC43: =ROUND(LOOKUP(Y43,'OSM - Rating and Score'!$G$85:$I$90,'OSM - Rating and Score'!$D$85:$D$90)*CC$6,2) -> 0.3 | CE43: =ROUND(LOOKUP(AA43,'OSM - Rating and Score'!$G$113:$I$118,'OSM - Rating and Score'!$D$113:$D$118)*CE$6,2) -> 0.32 | CG43: =ROUND(LOOKUP(AC43,'OSM - Rating and Score'!$G$94:$I$99,'OSM - Rating and Score'!$D$85:$D$90)*CG$6,2) -> 0.3 | CI43: =ROUND(VLOOKUP(AE43,'OSM - Rating and Score'!$C$8:$D$13,2,0)*CI$6,2) -> 0.4 | CK43: =ROUND(VLOOKUP(AG43,'OSM - Rating and Score'!$C$8:$D$13,2,0)*CK$6,2) -> 0 | CM43: 0 | CO43: =ROUND(VLOOKUP(AK43,'OSM - Rating and Score'!$C$8:$D$13,2,0)*CO$6,2) -> 0.28 | CQ43: =ROUND(VLOOKUP(AM43,'OSM - Rating and Score'!$C$47:$D$52,2,0)*CQ$6,2) -> 0.15 | CS43: =ROUND(VLOOKUP(AO43,'OSM - Rating and Score'!$C$47:$D$52,2,0)*CS$6,2) -> 0.15 | CU43: =ROUND(VLOOKUP(AQ43,'OSM - Rating and Score'!$C$47:$D$52,2,0)*CU$6,2) -> 0.1 | CW43: =ROUND(VLOOKUP(AS43,'OSM - Rating and Score'!$C$47:$D$52,2,0)*CW$6,2) -> 0.21 | CY43: =ROUND(VLOOKUP(AU43,'OSM - Rating and Score'!$C$65:$D$70,2,0)*CY$6,2) -> 0.2 | DA43: =ROUND(VLOOKUP(AW43,'OSM - Rating and Score'!$C$8:$D$13,2,0)*DA$6,2) -> 0 | DC43: =ROUND(VLOOKUP(AY43,'OSM - Rating and Score'!$C$75:$D$80,2,0)*DC$6,2) -> 0.2
C45: 20 | E45: POC -Blood gas | G45: Medcaptain/ Fortress Diagnostic IVD | I45: High | K45: Low | O45: High Barriers | Q45: Low Fit | S45: Limited Readiness | U45: Major New Team | W45: 200 | Y45: 5 | AA45: 0.2 | AC45: =ROUND(Y45*(1+AA45)^5,0) -> 12 | AE45: High | AG45: Minimal | AI45: 0.5 | AK45: High | AM45: Easy | AO45: Moderate | AQ45: Moderate | AS45: Moderate | AU45: Moderate | AW45: Minimal | AY45: Fast | BA45: =IF(COUNTA(AY45,AW45,AU45,AS45,AQ45,AO45,AM45,AK45,AI45,AG45,AE45,AC45,AA45,Y45,W45,U45,S45,Q45,O45,K45,I45)=21,"✓","✗") -> ✓ | BC45: =IFERROR(SUM(BM45:DC45),"") -> 2.92 | BE45: =IFERROR(LOOKUP(BC45,'OSM - Rating and Score'!$G$103:$I$108,'OSM - Rating and Score'!$C$103:$C$108),"") -> Moderate | BG45: Poland company | BM45: =ROUND(VLOOKUP(I45,'OSM - Rating and Score'!$C$8:$D$13,2,0)*BM$6,2) -> 0 | BO45: =ROUND(VLOOKUP(K45,'OSM - Rating and Score'!$C$8:$D$13,2,0)*BO$6,2) -> 0.1 | BS45: =ROUND(VLOOKUP(O45,'OSM - Rating and Score'!$C$17:$D$22,2,0)*BS$6,2) -> 0.1 | BU45: =ROUND(VLOOKUP(Q45,'OSM - Rating and Score'!$C$56:$D$61,2,0)*BU$6,2) -> 0.14 | BW45: =ROUND(VLOOKUP(S45,'OSM - Rating and Score'!$C$26:$D$31,2,0)*BW$6,2) -> 0.1 | BY45: =ROUND(VLOOKUP(U45,'OSM - Rating and Score'!$C$35:$D$40,2,0)*BY$6,2) -> 0.14 | CC45: =ROUND(LOOKUP(Y45,'OSM - Rating and Score'!$G$85:$I$90,'OSM - Rating and Score'!$D$85:$D$90)*CC$6,2) -> 0.3 | CE45: =ROUND(LOOKUP(AA45,'OSM - Rating and Score'!$G$113:$I$118,'OSM - Rating and Score'!$D$113:$D$118)*CE$6,2) -> 0.16 | CG45: =ROUND(LOOKUP(AC45,'OSM - Rating and Score'!$G$94:$I$99,'OSM - Rating and Score'!$D$85:$D$90)*CG$6,2) -> 0.1 | CI45: =ROUND(VLOOKUP(AE45,'OSM - Rating and Score'!$C$8:$D$13,2,0)*CI$6,2) -> 0.4 | CK45: =ROUND(VLOOKUP(AG45,'OSM - Rating and Score'!$C$8:$D$13,2,0)*CK$6,2) -> 0.04 | CM45: 0 | CO45: =ROUND(VLOOKUP(AK45,'OSM - Rating and Score'!$C$8:$D$13,2,0)*CO$6,2) -> 0.28 | CQ45: =ROUND(VLOOKUP(AM45,'OSM - Rating and Score'!$C$47:$D$52,2,0)*CQ$6,2) -> 0.2 | CS45: =ROUND(VLOOKUP(AO45,'OSM - Rating and Score'!$C$47:$D$52,2,0)*CS$6,2) -> 0.15 | CU45: =ROUND(VLOOKUP(AQ45,'OSM - Rating and Score'!$C$47:$D$52,2,0)*CU$6,2) -> 0.15 | CW45: =ROUND(VLOOKUP(AS45,'OSM - Rating and Score'!$C$47:$D$52,2,0)*CW$6,2) -> 0.21 | CY45: =ROUND(VLOOKUP(AU45,'OSM - Rating and Score'!$C$65:$D$70,2,0)*CY$6,2) -> 0.15 | DA45: =ROUND(VLOOKUP(AW45,'OSM - Rating and Score'!$C$8:$D$13,2,0)*DA$6,2) -> 0 | DC45: =ROUND(VLOOKUP(AY45,'OSM - Rating and Score'!$C$75:$D$80,2,0)*DC$6,2) -> 0.2
C47: 21 | E47: blood Bank | I47: High | K47: Low | O47: High Barriers | Q47: Low Fit | S47: Limited Readiness | U47: Major New Team | W47: 250 | Y47: 5 | AA47: 0.25 | AC47: =ROUND(Y47*(1+AA47)^5,0) -> 15 | AE47: Medium | AG47: Minimal | AK47: High | AM47: Easy | AO47: Moderate | AQ47: Moderate | AS47: Moderate | AU47: Moderate | AW47: Medium | AY47: Medium | BA47: =IF(COUNTA(AY47,AW47,AU47,AS47,AQ47,AO47,AM47,AK47,AI47,AG47,AE47,AC47,AA47,Y47,W47,U47,S47,Q47,O47,K47,I47)=21,"✓","✗") -> ✗ | BC47: =IFERROR(SUM(BM47:DC47),"") -> 2.87 | BE47: =IFERROR(LOOKUP(BC47,'OSM - Rating and Score'!$G$103:$I$108,'OSM - Rating and Score'!$C$103:$C$108),"") -> Moderate | BM47: =ROUND(VLOOKUP(I47,'OSM - Rating and Score'!$C$8:$D$13,2,0)*BM$6,2) -> 0 | BO47: =ROUND(VLOOKUP(K47,'OSM - Rating and Score'!$C$8:$D$13,2,0)*BO$6,2) -> 0.1 | BS47: =ROUND(VLOOKUP(O47,'OSM - Rating and Score'!$C$17:$D$22,2,0)*BS$6,2) -> 0.1 | BU47: =ROUND(VLOOKUP(Q47,'OSM - Rating and Score'!$C$56:$D$61,2,0)*BU$6,2) -> 0.14 | BW47: =ROUND(VLOOKUP(S47,'OSM - Rating and Score'!$C$26:$D$31,2,0)*BW$6,2) -> 0.1 | BY47: =ROUND(VLOOKUP(U47,'OSM - Rating and Score'!$C$35:$D$40,2,0)*BY$6,2) -> 0.14 | CC47: =ROUND(LOOKUP(Y47,'OSM - Rating and Score'!$G$85:$I$90,'OSM - Rating and Score'!$D$85:$D$90)*CC$6,2) -> 0.3 | CE47: =ROUND(LOOKUP(AA47,'OSM - Rating and Score'!$G$113:$I$118,'OSM - Rating and Score'!$D$113:$D$118)*CE$6,2) -> 0.16 | CG47: =ROUND(LOOKUP(AC47,'OSM - Rating and Score'!$G$94:$I$99,'OSM - Rating and Score'!$D$85:$D$90)*CG$6,2) -> 0.2 | CI47: =ROUND(VLOOKUP(AE47,'OSM - Rating and Score'!$C$8:$D$13,2,0)*CI$6,2) -> 0.3 | CK47: =ROUND(VLOOKUP(AG47,'OSM - Rating and Score'!$C$8:$D$13,2,0)*CK$6,2) -> 0.04 | CM47: 0 | CO47: =ROUND(VLOOKUP(AK47,'OSM - Rating and Score'!$C$8:$D$13,2,0)*CO$6,2) -> 0.28 | CQ47: =ROUND(VLOOKUP(AM47,'OSM - Rating and Score'!$C$47:$D$52,2,0)*CQ$6,2) -> 0.2 | CS47: =ROUND(VLOOKUP(AO47,'OSM - Rating and Score'!$C$47:$D$52,2,0)*CS$6,2) -> 0.15 | CU47: =ROUND(VLOOKUP(AQ47,'OSM - Rating and Score'!$C$47:$D$52,2,0)*CU$6,2) -> 0.15 | CW47: =ROUND(VLOOKUP(AS47,'OSM - Rating and Score'!$C$47:$D$52,2,0)*CW$6,2) -> 0.21 | CY47: =ROUND(VLOOKUP(AU47,'OSM - Rating and Score'!$C$65:$D$70,2,0)*CY$6,2) -> 0.15 | DA47: =ROUND(VLOOKUP(AW47,'OSM - Rating and Score'!$C$8:$D$13,2,0)*DA$6,2) -> 0 | DC47: =ROUND(VLOOKUP(AY47,'OSM - Rating and Score'!$C$75:$D$80,2,0)*DC$6,2) -> 0.15
C49: 22 | E49: Equipment | G49: Monitors-Government | I49: High | K49: Very High | O49: Medium Barriers | Q49: Strong Fit | S49: Ready | U49: Some New Staff | W49: 150 | Y49: 10 | AA49: 0.2 | AC49: =ROUND(Y49*(1+AA49)^5,0) -> 25 | AE49: Medium | AG49: Minimal | AK49: Medium | AM49: Moderate | AO49: Moderate | AQ49: Easy | AS49: Moderate | AU49: Low Complex | AW49: Minimal | AY49: Medium | BA49: =IF(COUNTA(AY49,AW49,AU49,AS49,AQ49,AO49,AM49,AK49,AI49,AG49,AE49,AC49,AA49,Y49,W49,U49,S49,Q49,O49,K49,I49)=21,"✓","✗") -> ✗ | BC49: =IFERROR(SUM(BM49:DC49),"") -> 3.46 | BE49: =IFERROR(LOOKUP(BC49,'OSM - Rating and Score'!$G$103:$I$108,'OSM - Rating and Score'!$C$103:$C$108),"") -> Moderate | BG49: hold | BM49: =ROUND(VLOOKUP(I49,'OSM - Rating and Score'!$C$8:$D$13,2,0)*BM$6,2) -> 0 | BO49: =ROUND(VLOOKUP(K49,'OSM - Rating and Score'!$C$8:$D$13,2,0)*BO$6,2) -> 0.25 | BS49: =ROUND(VLOOKUP(O49,'OSM - Rating and Score'!$C$17:$D$22,2,0)*BS$6,2) -> 0.15 | BU49: =ROUND(VLOOKUP(Q49,'OSM - Rating and Score'!$C$56:$D$61,2,0)*BU$6,2) -> 0.28 | BW49: =ROUND(VLOOKUP(S49,'OSM - Rating and Score'!$C$26:$D$31,2,0)*BW$6,2) -> 0.2 | BY49: =ROUND(VLOOKUP(U49,'OSM - Rating and Score'!$C$35:$D$40,2,0)*BY$6,2) -> 0.21 | CC49: =ROUND(LOOKUP(Y49,'OSM - Rating and Score'!$G$85:$I$90,'OSM - Rating and Score'!$D$85:$D$90)*CC$6,2) -> 0.3 | CE49: =ROUND(LOOKUP(AA49,'OSM - Rating and Score'!$G$113:$I$118,'OSM - Rating and Score'!$D$113:$D$118)*CE$6,2) -> 0.16 | CG49: =ROUND(LOOKUP(AC49,'OSM - Rating and Score'!$G$94:$I$99,'OSM - Rating and Score'!$D$85:$D$90)*CG$6,2) -> 0.3 | CI49: =ROUND(VLOOKUP(AE49,'OSM - Rating and Score'!$C$8:$D$13,2,0)*CI$6,2) -> 0.3 | CK49: =ROUND(VLOOKUP(AG49,'OSM - Rating and Score'!$C$8:$D$13,2,0)*CK$6,2) -> 0.04 | CM49: 0 | CO49: =ROUND(VLOOKUP(AK49,'OSM - Rating and Score'!$C$8:$D$13,2,0)*CO$6,2) -> 0.21 | CQ49: =ROUND(VLOOKUP(AM49,'OSM - Rating and Score'!$C$47:$D$52,2,0)*CQ$6,2) -> 0.15 | CS49: =ROUND(VLOOKUP(AO49,'OSM - Rating and Score'!$C$47:$D$52,2,0)*CS$6,2) -> 0.15 | CU49: =ROUND(VLOOKUP(AQ49,'OSM - Rating and Score'!$C$47:$D$52,2,0)*CU$6,2) -> 0.2 | CW49: =ROUND(VLOOKUP(AS49,'OSM - Rating and Score'!$C$47:$D$52,2,0)*CW$6,2) -> 0.21 | CY49: =ROUND(VLOOKUP(AU49,'OSM - Rating and Score'!$C$65:$D$70,2,0)*CY$6,2) -> 0.2 | DA49: =ROUND(VLOOKUP(AW49,'OSM - Rating and Score'!$C$8:$D$13,2,0)*DA$6,2) -> 0 | DC49: =ROUND(VLOOKUP(AY49,'OSM - Rating and Score'!$C$75:$D$80,2,0)*DC$6,2) -> 0.15
C51: 23 | E51: Equipment | G51: Ventilator-Government | I51: High | K51: High | O51: Medium Barriers | Q51: Strong Fit | S51: Partially Ready | U51: Some New Staff | W51: 180 | Y51: 10 | AA51: 0.15 | AC51: =ROUND(Y51*(1+AA51)^5,0) -> 20 | AE51: Medium | AG51: Minimal | AK51: Medium | AM51: Moderate | AO51: Moderate | AQ51: Easy | AS51: Moderate | AU51: Low Complex | AW51: Minimal | AY51: Medium | BA51: =IF(COUNTA(AY51,AW51,AU51,AS51,AQ51,AO51,AM51,AK51,AI51,AG51,AE51,AC51,AA51,Y51,W51,U51,S51,Q51,O51,K51,I51)=21,"✓","✗") -> ✗ | BC51: =IFERROR(SUM(BM51:DC51),"") -> 3.18 | BE51: =IFERROR(LOOKUP(BC51,'OSM - Rating and Score'!$G$103:$I$108,'OSM - Rating and Score'!$C$103:$C$108),"") -> Moderate | BG51: hold | BM51: =ROUND(VLOOKUP(I51,'OSM - Rating and Score'!$C$8:$D$13,2,0)*BM$6,2) -> 0 | BO51: =ROUND(VLOOKUP(K51,'OSM - Rating and Score'!$C$8:$D$13,2,0)*BO$6,2) -> 0.2 | BS51: =ROUND(VLOOKUP(O51,'OSM - Rating and Score'!$C$17:$D$22,2,0)*BS$6,2) -> 0.15 | BU51: =ROUND(VLOOKUP(Q51,'OSM - Rating and Score'!$C$56:$D$61,2,0)*BU$6,2) -> 0.28 | BW51: =ROUND(VLOOKUP(S51,'OSM - Rating and Score'!$C$26:$D$31,2,0)*BW$6,2) -> 0.15 | BY51: =ROUND(VLOOKUP(U51,'OSM - Rating and Score'!$C$35:$D$40,2,0)*BY$6,2) -> 0.21 | CC51: =ROUND(LOOKUP(Y51,'OSM - Rating and Score'!$G$85:$I$90,'OSM - Rating and Score'!$D$85:$D$90)*CC$6,2) -> 0.3 | CE51: =ROUND(LOOKUP(AA51,'OSM - Rating and Score'!$G$113:$I$118,'OSM - Rating and Score'!$D$113:$D$118)*CE$6,2) -> 0.08 | CG51: =ROUND(LOOKUP(AC51,'OSM - Rating and Score'!$G$94:$I$99,'OSM - Rating and Score'!$D$85:$D$90)*CG$6,2) -> 0.2 | CI51: =ROUND(VLOOKUP(AE51,'OSM - Rating and Score'!$C$8:$D$13,2,0)*CI$6,2) -> 0.3 | CK51: =ROUND(VLOOKUP(AG51,'OSM - Rating and Score'!$C$8:$D$13,2,0)*CK$6,2) -> 0.04 | CM51: 0 | CO51: =ROUND(VLOOKUP(AK51,'OSM - Rating and Score'!$C$8:$D$13,2,0)*CO$6,2) -> 0.21 | CQ51: =ROUND(VLOOKUP(AM51,'OSM - Rating and Score'!$C$47:$D$52,2,0)*CQ$6,2) -> 0.15 | CS51: =ROUND(VLOOKUP(AO51,'OSM - Rating and Score'!$C$47:$D$52,2,0)*CS$6,2) -> 0.15 | CU51: =ROUND(VLOOKUP(AQ51,'OSM - Rating and Score'!$C$47:$D$52,2,0)*CU$6,2) -> 0.2 | CW51: =ROUND(VLOOKUP(AS51,'OSM - Rating and Score'!$C$47:$D$52,2,0)*CW$6,2) -> 0.21 | CY51: =ROUND(VLOOKUP(AU51,'OSM - Rating and Score'!$C$65:$D$70,2,0)*CY$6,2) -> 0.2 | DA51: =ROUND(VLOOKUP(AW51,'OSM - Rating and Score'!$C$8:$D$13,2,0)*DA$6,2) -> 0 | DC51: =ROUND(VLOOKUP(AY51,'OSM - Rating and Score'!$C$75:$D$80,2,0)*DC$6,2) -> 0.15
C53: 24 | E53: Equipment | G53: Anesthesia -Gevernment | I53: High | K53: High | O53: Medium Barriers | Q53: Strong Fit | S53: Partially Ready | U53: Some New Staff | W53: 45 | Y53: 5 | AA53: 0.1 | AC53: =ROUND(Y53*(1+AA53)^5,0) -> 8 | AE53: Medium | AG53: Minimal | AK53: Medium | AM53: Moderate | AO53: Moderate | AQ53: Easy | AS53: Moderate | AU53: Low Complex | AW53: Minimal | AY53: Medium | BA53: =IF(COUNTA(AY53,AW53,AU53,AS53,AQ53,AO53,AM53,AK53,AI53,AG53,AE53,AC53,AA53,Y53,W53,U53,S53,Q53,O53,K53,I53)=21,"✓","✗") -> ✗ | BC53: =IFERROR(SUM(BM53:DC53),"") -> 3.08 | BE53: =IFERROR(LOOKUP(BC53,'OSM - Rating and Score'!$G$103:$I$108,'OSM - Rating and Score'!$C$103:$C$108),"") -> Moderate | BG53: hold | BM53: =ROUND(VLOOKUP(I53,'OSM - Rating and Score'!$C$8:$D$13,2,0)*BM$6,2) -> 0 | BO53: =ROUND(VLOOKUP(K53,'OSM - Rating and Score'!$C$8:$D$13,2,0)*BO$6,2) -> 0.2 | BS53: =ROUND(VLOOKUP(O53,'OSM - Rating and Score'!$C$17:$D$22,2,0)*BS$6,2) -> 0.15 | BU53: =ROUND(VLOOKUP(Q53,'OSM - Rating and Score'!$C$56:$D$61,2,0)*BU$6,2) -> 0.28 | BW53: =ROUND(VLOOKUP(S53,'OSM - Rating and Score'!$C$26:$D$31,2,0)*BW$6,2) -> 0.15 | BY53: =ROUND(VLOOKUP(U53,'OSM - Rating and Score'!$C$35:$D$40,2,0)*BY$6,2) -> 0.21 | CC53: =ROUND(LOOKUP(Y53,'OSM - Rating and Score'!$G$85:$I$90,'OSM - Rating and Score'!$D$85:$D$90)*CC$6,2) -> 0.3 | CE53: =ROUND(LOOKUP(AA53,'OSM - Rating and Score'!$G$113:$I$118,'OSM - Rating and Score'!$D$113:$D$118)*CE$6,2) -> 0.08 | CG53: =ROUND(LOOKUP(AC53,'OSM - Rating and Score'!$G$94:$I$99,'OSM - Rating and Score'!$D$85:$D$90)*CG$6,2) -> 0.1 | CI53: =ROUND(VLOOKUP(AE53,'OSM - Rating and Score'!$C$8:$D$13,2,0)*CI$6,2) -> 0.3 | CK53: =ROUND(VLOOKUP(AG53,'OSM - Rating and Score'!$C$8:$D$13,2,0)*CK$6,2) -> 0.04 | CM53: 0 | CO53: =ROUND(VLOOKUP(AK53,'OSM - Rating and Score'!$C$8:$D$13,2,0)*CO$6,2) -> 0.21 | CQ53: =ROUND(VLOOKUP(AM53,'OSM - Rating and Score'!$C$47:$D$52,2,0)*CQ$6,2) -> 0.15 | CS53: =ROUND(VLOOKUP(AO53,'OSM - Rating and Score'!$C$47:$D$52,2,0)*CS$6,2) -> 0.15 | CU53: =ROUND(VLOOKUP(AQ53,'OSM - Rating and Score'!$C$47:$D$52,2,0)*CU$6,2) -> 0.2 | CW53: =ROUND(VLOOKUP(AS53,'OSM - Rating and Score'!$C$47:$D$52,2,0)*CW$6,2) -> 0.21 | CY53: =ROUND(VLOOKUP(AU53,'OSM - Rating and Score'!$C$65:$D$70,2,0)*CY$6,2) -> 0.2 | DA53: =ROUND(VLOOKUP(AW53,'OSM - Rating and Score'!$C$8:$D$13,2,0)*DA$6,2) -> 0 | DC53: =ROUND(VLOOKUP(AY53,'OSM - Rating and Score'!$C$75:$D$80,2,0)*DC$6,2) -> 0.15
C55: 25 | G55: Ultrasound | I55: High | K55: Medium | O55: Medium Barriers | Q55: Moderate Fit | S55: Partially Ready | U55: Minor Additions | W55: 40 | Y55: 3 | AA55: 0.35 | AC55: =ROUND(Y55*(1+AA55)^5,0) -> 13 | AE55: Medium | AG55: Minimal | AK55: Medium | AM55: Easy | AO55: Easy | AQ55: Easy | AS55: Moderate | AU55: Low Complex | AW55: Minimal | AY55: Fast | BA55: =IF(COUNTA(AY55,AW55,AU55,AS55,AQ55,AO55,AM55,AK55,AI55,AG55,AE55,AC55,AA55,Y55,W55,U55,S55,Q55,O55,K55,I55)=21,"✓","✗") -> ✗ | BC55: =IFERROR(SUM(BM55:DC55),"") -> 3.24 | BE55: =IFERROR(LOOKUP(BC55,'OSM - Rating and Score'!$G$103:$I$108,'OSM - Rating and Score'!$C$103:$C$108),"") -> Moderate | BG55: Samsung Follow up | BM55: =ROUND(VLOOKUP(I55,'OSM - Rating and Score'!$C$8:$D$13,2,0)*BM$6,2) -> 0 | BO55: =ROUND(VLOOKUP(K55,'OSM - Rating and Score'!$C$8:$D$13,2,0)*BO$6,2) -> 0.15 | BS55: =ROUND(VLOOKUP(O55,'OSM - Rating and Score'!$C$17:$D$22,2,0)*BS$6,2) -> 0.15 | BU55: =ROUND(VLOOKUP(Q55,'OSM - Rating and Score'!$C$56:$D$61,2,0)*BU$6,2) -> 0.21 | BW55: =ROUND(VLOOKUP(S55,'OSM - Rating and Score'!$C$26:$D$31,2,0)*BW$6,2) -> 0.15 | BY55: =ROUND(VLOOKUP(U55,'OSM - Rating and Score'!$C$35:$D$40,2,0)*BY$6,2) -> 0.28 | CC55: =ROUND(LOOKUP(Y55,'OSM - Rating and Score'!$G$85:$I$90,'OSM - Rating and Score'!$D$85:$D$90)*CC$6,2) -> 0.2 | CE55: =ROUND(LOOKUP(AA55,'OSM - Rating and Score'!$G$113:$I$118,'OSM - Rating and Score'!$D$113:$D$118)*CE$6,2) -> 0.24 | CG55: =ROUND(LOOKUP(AC55,'OSM - Rating and Score'!$G$94:$I$99,'OSM - Rating and Score'!$D$85:$D$90)*CG$6,2) -> 0.1 | CI55: =ROUND(VLOOKUP(AE55,'OSM - Rating and Score'!$C$8:$D$13,2,0)*CI$6,2) -> 0.3 | CK55: =ROUND(VLOOKUP(AG55,'OSM - Rating and Score'!$C$8:$D$13,2,0)*CK$6,2) -> 0.04 | CM55: 0 | CO55: =ROUND(VLOOKUP(AK55,'OSM - Rating and Score'!$C$8:$D$13,2,0)*CO$6,2) -> 0.21 | CQ55: =ROUND(VLOOKUP(AM55,'OSM - Rating and Score'!$C$47:$D$52,2,0)*CQ$6,2) -> 0.2 | CS55: =ROUND(VLOOKUP(AO55,'OSM - Rating and Score'!$C$47:$D$52,2,0)*CS$6,2) -> 0.2 | CU55: =ROUND(VLOOKUP(AQ55,'OSM - Rating and Score'!$C$47:$D$52,2,0)*CU$6,2) -> 0.2 | CW55: =ROUND(VLOOKUP(AS55,'OSM - Rating and Score'!$C$47:$D$52,2,0)*CW$6,2) -> 0.21 | CY55: =ROUND(VLOOKUP(AU55,'OSM - Rating and Score'!$C$65:$D$70,2,0)*CY$6,2) -> 0.2 | DA55: =ROUND(VLOOKUP(AW55,'OSM - Rating and Score'!$C$8:$D$13,2,0)*DA$6,2) -> 0 | DC55: =ROUND(VLOOKUP(AY55,'OSM - Rating and Score'!$C$75:$D$80,2,0)*DC$6,2) -> 0.2
C57: 26 | G57: GIT Capsule | I57: Medium | K57: High | O57: Medium Barriers | Q57: Strong Fit | S57: Partially Ready | U57: No New Team | W57: 20 | Y57: 2 | AA57: 0.2 | AC57: =ROUND(Y57*(1+AA57)^5,0) -> 5 | AE57: High | AG57: Minimal | AK57: Medium | AM57: Easy | AO57: Easy | AQ57: Easy | AS57: Moderate | AU57: Low Complex | AW57: Minimal | AY57: Fast | BA57: =IF(COUNTA(AY57,AW57,AU57,AS57,AQ57,AO57,AM57,AK57,AI57,AG57,AE57,AC57,AA57,Y57,W57,U57,S57,Q57,O57,K57,I57)=21,"✓","✗") -> ✗ | BC57: =IFERROR(SUM(BM57:DC57),"") -> 3.45 | BE57: =IFERROR(LOOKUP(BC57,'OSM - Rating and Score'!$G$103:$I$108,'OSM - Rating and Score'!$C$103:$C$108),"") -> Moderate | BG57: Enditax | BM57: =ROUND(VLOOKUP(I57,'OSM - Rating and Score'!$C$8:$D$13,2,0)*BM$6,2) -> 0 | BO57: =ROUND(VLOOKUP(K57,'OSM - Rating and Score'!$C$8:$D$13,2,0)*BO$6,2) -> 0.2 | BS57: =ROUND(VLOOKUP(O57,'OSM - Rating and Score'!$C$17:$D$22,2,0)*BS$6,2) -> 0.15 | BU57: =ROUND(VLOOKUP(Q57,'OSM - Rating and Score'!$C$56:$D$61,2,0)*BU$6,2) -> 0.28 | BW57: =ROUND(VLOOKUP(S57,'OSM - Rating and Score'!$C$26:$D$31,2,0)*BW$6,2) -> 0.15 | BY57: =ROUND(VLOOKUP(U57,'OSM - Rating and Score'!$C$35:$D$40,2,0)*BY$6,2) -> 0.35 | CC57: =ROUND(LOOKUP(Y57,'OSM - Rating and Score'!$G$85:$I$90,'OSM - Rating and Score'!$D$85:$D$90)*CC$6,2) -> 0.2 | CE57: =ROUND(LOOKUP(AA57,'OSM - Rating and Score'!$G$113:$I$118,'OSM - Rating and Score'!$D$113:$D$118)*CE$6,2) -> 0.16 | CG57: =ROUND(LOOKUP(AC57,'OSM - Rating and Score'!$G$94:$I$99,'OSM - Rating and Score'!$D$85:$D$90)*CG$6,2) -> 0.1 | CI57: =ROUND(VLOOKUP(AE57,'OSM - Rating and Score'!$C$8:$D$13,2,0)*CI$6,2) -> 0.4 | CK57: =ROUND(VLOOKUP(AG57,'OSM - Rating and Score'!$C$8:$D$13,2,0)*CK$6,2) -> 0.04 | CM57: 0 | CO57: =ROUND(VLOOKUP(AK57,'OSM - Rating and Score'!$C$8:$D$13,2,0)*CO$6,2) -> 0.21 | CQ57: =ROUND(VLOOKUP(AM57,'OSM - Rating and Score'!$C$47:$D$52,2,0)*CQ$6,2) -> 0.2 | CS57: =ROUND(VLOOKUP(AO57,'OSM - Rating and Score'!$C$47:$D$52,2,0)*CS$6,2) -> 0.2 | CU57: =ROUND(VLOOKUP(AQ57,'OSM - Rating and Score'!$C$47:$D$52,2,0)*CU$6,2) -> 0.2 | CW57: =ROUND(VLOOKUP(AS57,'OSM - Rating and Score'!$C$47:$D$52,2,0)*CW$6,2) -> 0.21 | CY57: =ROUND(VLOOKUP(AU57,'OSM - Rating and Score'!$C$65:$D$70,2,0)*CY$6,2) -> 0.2 | DA57: =ROUND(VLOOKUP(AW57,'OSM - Rating and Score'!$C$8:$D$13,2,0)*DA$6,2) -> 0 | DC57: =ROUND(VLOOKUP(AY57,'OSM - Rating and Score'!$C$75:$D$80,2,0)*DC$6,2) -> 0.2
C58: 27
G59: POC Ultrsound | I59: Medium | K59: Medium | O59: Medium Barriers | Q59: Moderate Fit | S59: Limited Readiness | U59: Minor Additions | W59: 25 | Y59: 2 | AA59: 0.2 | AC59: =ROUND(Y59*(1+AA59)^5,0) -> 5 | AE59: Medium | AG59: Minimal | AK59: Medium | AM59: Easy | AO59: Moderate | AQ59: Easy | AS59: Moderate | AU59: Low Complex | AW59: Minimal | AY59: Fast | BA59: =IF(COUNTA(AY59,AW59,AU59,AS59,AQ59,AO59,AM59,AK59,AI59,AG59,AE59,AC59,AA59,Y59,W59,U59,S59,Q59,O59,K59,I59)=21,"✓","✗") -> ✗ | BC59: =IFERROR(SUM(BM59:DC59),"") -> 3.06 | BE59: =IFERROR(LOOKUP(BC59,'OSM - Rating and Score'!$G$103:$I$108,'OSM - Rating and Score'!$C$103:$C$108),"") -> Moderate | BM59: =ROUND(VLOOKUP(I59,'OSM - Rating and Score'!$C$8:$D$13,2,0)*BM$6,2) -> 0 | BO59: =ROUND(VLOOKUP(K59,'OSM - Rating and Score'!$C$8:$D$13,2,0)*BO$6,2) -> 0.15 | BS59: =ROUND(VLOOKUP(O59,'OSM - Rating and Score'!$C$17:$D$22,2,0)*BS$6,2) -> 0.15 | BU59: =ROUND(VLOOKUP(Q59,'OSM - Rating and Score'!$C$56:$D$61,2,0)*BU$6,2) -> 0.21 | BW59: =ROUND(VLOOKUP(S59,'OSM - Rating and Score'!$C$26:$D$31,2,0)*BW$6,2) -> 0.1 | BY59: =ROUND(VLOOKUP(U59,'OSM - Rating and Score'!$C$35:$D$40,2,0)*BY$6,2) -> 0.28 | CC59: =ROUND(LOOKUP(Y59,'OSM - Rating and Score'!$G$85:$I$90,'OSM - Rating and Score'!$D$85:$D$90)*CC$6,2) -> 0.2 | CE59: =ROUND(LOOKUP(AA59,'OSM - Rating and Score'!$G$113:$I$118,'OSM - Rating and Score'!$D$113:$D$118)*CE$6,2) -> 0.16 | CG59: =ROUND(LOOKUP(AC59,'OSM - Rating and Score'!$G$94:$I$99,'OSM - Rating and Score'!$D$85:$D$90)*CG$6,2) -> 0.1 | CI59: =ROUND(VLOOKUP(AE59,'OSM - Rating and Score'!$C$8:$D$13,2,0)*CI$6,2) -> 0.3 | CK59: =ROUND(VLOOKUP(AG59,'OSM - Rating and Score'!$C$8:$D$13,2,0)*CK$6,2) -> 0.04 | CM59: 0 | CO59: =ROUND(VLOOKUP(AK59,'OSM - Rating and Score'!$C$8:$D$13,2,0)*CO$6,2) -> 0.21 | CQ59: =ROUND(VLOOKUP(AM59,'OSM - Rating and Score'!$C$47:$D$52,2,0)*CQ$6,2) -> 0.2 | CS59: =ROUND(VLOOKUP(AO59,'OSM - Rating and Score'!$C$47:$D$52,2,0)*CS$6,2) -> 0.15 | CU59: =ROUND(VLOOKUP(AQ59,'OSM - Rating and Score'!$C$47:$D$52,2,0)*CU$6,2) -> 0.2 | CW59: =ROUND(VLOOKUP(AS59,'OSM - Rating and Score'!$C$47:$D$52,2,0)*CW$6,2) -> 0.21 | CY59: =ROUND(VLOOKUP(AU59,'OSM - Rating and Score'!$C$65:$D$70,2,0)*CY$6,2) -> 0.2 | DA59: =ROUND(VLOOKUP(AW59,'OSM - Rating and Score'!$C$8:$D$13,2,0)*DA$6,2) -> 0 | DC59: =ROUND(VLOOKUP(AY59,'OSM - Rating and Score'!$C$75:$D$80,2,0)*DC$6,2) -> 0.2
C60: 28 | G60: Mobile X-ray | I60: Medium | K60: Low | O60: High Barriers | Q60: Moderate Fit | S60: Limited Readiness | U60: Minor Additions | W60: 180 | Y60: 4 | AA60: 0.25 | AC60: =ROUND(Y60*(1+AA60)^5,0) -> 12 | AE60: Low | AG60: Minimal | AK60: Medium | AM60: Easy | AO60: Moderate | AQ60: Moderate | AS60: Difficult | AU60: Moderate | AW60: Minimal | AY60: Fast | BA60: =IF(COUNTA(AY60,AW60,AU60,AS60,AQ60,AO60,AM60,AK60,AI60,AG60,AE60,AC60,AA60,Y60,W60,U60,S60,Q60,O60,K60,I60)=21,"✓","✗") -> ✗ | BC60: =IFERROR(SUM(BM60:DC60),"") -> 2.69 | BE60: =IFERROR(LOOKUP(BC60,'OSM - Rating and Score'!$G$103:$I$108,'OSM - Rating and Score'!$C$103:$C$108),"") -> Moderate | BG60: Eurocol/brainlab | BM60: =ROUND(VLOOKUP(I60,'OSM - Rating and Score'!$C$8:$D$13,2,0)*BM$6,2) -> 0 | BO60: =ROUND(VLOOKUP(K60,'OSM - Rating and Score'!$C$8:$D$13,2,0)*BO$6,2) -> 0.1 | BS60: =ROUND(VLOOKUP(O60,'OSM - Rating and Score'!$C$17:$D$22,2,0)*BS$6,2) -> 0.1 | BU60: =ROUND(VLOOKUP(Q60,'OSM - Rating and Score'!$C$56:$D$61,2,0)*BU$6,2) -> 0.21 | BW60: =ROUND(VLOOKUP(S60,'OSM - Rating and Score'!$C$26:$D$31,2,0)*BW$6,2) -> 0.1 | BY60: =ROUND(VLOOKUP(U60,'OSM - Rating and Score'!$C$35:$D$40,2,0)*BY$6,2) -> 0.28 | CC60: =ROUND(LOOKUP(Y60,'OSM - Rating and Score'!$G$85:$I$90,'OSM - Rating and Score'!$D$85:$D$90)*CC$6,2) -> 0.2 | CE60: =ROUND(LOOKUP(AA60,'OSM - Rating and Score'!$G$113:$I$118,'OSM - Rating and Score'!$D$113:$D$118)*CE$6,2) -> 0.16 | CG60: =ROUND(LOOKUP(AC60,'OSM - Rating and Score'!$G$94:$I$99,'OSM - Rating and Score'!$D$85:$D$90)*CG$6,2) -> 0.1 | CI60: =ROUND(VLOOKUP(AE60,'OSM - Rating and Score'!$C$8:$D$13,2,0)*CI$6,2) -> 0.2 | CK60: =ROUND(VLOOKUP(AG60,'OSM - Rating and Score'!$C$8:$D$13,2,0)*CK$6,2) -> 0.04 | CM60: 0 | CO60: =ROUND(VLOOKUP(AK60,'OSM - Rating and Score'!$C$8:$D$13,2,0)*CO$6,2) -> 0.21 | CQ60: =ROUND(VLOOKUP(AM60,'OSM - Rating and Score'!$C$47:$D$52,2,0)*CQ$6,2) -> 0.2 | CS60: =ROUND(VLOOKUP(AO60,'OSM - Rating and Score'!$C$47:$D$52,2,0)*CS$6,2) -> 0.15 | CU60: =ROUND(VLOOKUP(AQ60,'OSM - Rating and Score'!$C$47:$D$52,2,0)*CU$6,2) -> 0.15 | CW60: =ROUND(VLOOKUP(AS60,'OSM - Rating and Score'!$C$47:$D$52,2,0)*CW$6,2) -> 0.14 | CY60: =ROUND(VLOOKUP(AU60,'OSM - Rating and Score'!$C$65:$D$70,2,0)*CY$6,2) -> 0.15 | DA60: =ROUND(VLOOKUP(AW60,'OSM - Rating and Score'!$C$8:$D$13,2,0)*DA$6,2) -> 0 | DC60: =ROUND(VLOOKUP(AY60,'OSM - Rating and Score'!$C$75:$D$80,2,0)*DC$6,2) -> 0.2
G61: Infusion pump | I61: Medium | K61: Medium | O61: High Barriers | Q61: Strong Fit | S61: Limited Readiness | U61: Some New Staff | W61: 200 | Y61: 5 | AA61: 0.3 | AC61: =ROUND(Y61*(1+AA61)^5,0) -> 19 | AE61: High | AG61: Minimal | AI61: 3 | AK61: Medium | AM61: Easy | AO61: Moderate | AQ61: Easy | AS61: Easy | AU61: Moderate | AW61: Medium | AY61: Fast | BA61: =IF(COUNTA(AY61,AW61,AU61,AS61,AQ61,AO61,AM61,AK61,AI61,AG61,AE61,AC61,AA61,Y61,W61,U61,S61,Q61,O61,K61,I61)=21,"✓","✗") -> ✓ | BC61: =IFERROR(SUM(BM61:DC61),"") -> 3.41 | BE61: =IFERROR(LOOKUP(BC61,'OSM - Rating and Score'!$G$103:$I$108,'OSM - Rating and Score'!$C$103:$C$108),"") -> Moderate | BG61: ICU Medical | BM61: =ROUND(VLOOKUP(I61,'OSM - Rating and Score'!$C$8:$D$13,2,0)*BM$6,2) -> 0 | BO61: =ROUND(VLOOKUP(K61,'OSM - Rating and Score'!$C$8:$D$13,2,0)*BO$6,2) -> 0.15 | BS61: =ROUND(VLOOKUP(O61,'OSM - Rating and Score'!$C$17:$D$22,2,0)*BS$6,2) -> 0.1 | BU61: =ROUND(VLOOKUP(Q61,'OSM - Rating and Score'!$C$56:$D$61,2,0)*BU$6,2) -> 0.28 | BW61: =ROUND(VLOOKUP(S61,'OSM - Rating and Score'!$C$26:$D$31,2,0)*BW$6,2) -> 0.1 | BY61: =ROUND(VLOOKUP(U61,'OSM - Rating and Score'!$C$35:$D$40,2,0)*BY$6,2) -> 0.21 | CC61: =ROUND(LOOKUP(Y61,'OSM - Rating and Score'!$G$85:$I$90,'OSM - Rating and Score'!$D$85:$D$90)*CC$6,2) -> 0.3 | CE61: =ROUND(LOOKUP(AA61,'OSM - Rating and Score'!$G$113:$I$118,'OSM - Rating and Score'!$D$113:$D$118)*CE$6,2) -> 0.24 | CG61: =ROUND(LOOKUP(AC61,'OSM - Rating and Score'!$G$94:$I$99,'OSM - Rating and Score'!$D$85:$D$90)*CG$6,2) -> 0.2 | CI61: =ROUND(VLOOKUP(AE61,'OSM - Rating and Score'!$C$8:$D$13,2,0)*CI$6,2) -> 0.4 | CK61: =ROUND(VLOOKUP(AG61,'OSM - Rating and Score'!$C$8:$D$13,2,0)*CK$6,2) -> 0.04 | CM61: 0 | CO61: =ROUND(VLOOKUP(AK61,'OSM - Rating and Score'!$C$8:$D$13,2,0)*CO$6,2) -> 0.21 | CQ61: =ROUND(VLOOKUP(AM61,'OSM - Rating and Score'!$C$47:$D$52,2,0)*CQ$6,2) -> 0.2 | CS61: =ROUND(VLOOKUP(AO61,'OSM - Rating and Score'!$C$47:$D$52,2,0)*CS$6,2) -> 0.15 | CU61: =ROUND(VLOOKUP(AQ61,'OSM - Rating and Score'!$C$47:$D$52,2,0)*CU$6,2) -> 0.2 | CW61: =ROUND(VLOOKUP(AS61,'OSM - Rating and Score'!$C$47:$D$52,2,0)*CW$6,2) -> 0.28 | CY61: =ROUND(VLOOKUP(AU61,'OSM - Rating and Score'!$C$65:$D$70,2,0)*CY$6,2) -> 0.15 | DA61: =ROUND(VLOOKUP(AW61,'OSM - Rating and Score'!$C$8:$D$13,2,0)*DA$6,2) -> 0 | DC61: =ROUND(VLOOKUP(AY61,'OSM - Rating and Score'!$C$75:$D$80,2,0)*DC$6,2) -> 0.2
C62: 29 | G62: GIT EUS accessories | I62: Medium | K62: High | O62: Low Barriers | Q62: Strong Fit | S62: Ready | U62: No New Team | W62: 30 | Y62: 1 | AA62: 0.4 | AC62: =ROUND(Y62*(1+AA62)^5,0) -> 5 | AE62: Very High | AG62: Minimal | AK62: High | AM62: Easy | AO62: Easy | AQ62: Easy | AS62: Moderate | AU62: Low Complex | AW62: Minimal | AY62: Fast | BA62: =IF(COUNTA(AY62,AW62,AU62,AS62,AQ62,AO62,AM62,AK62,AI62,AG62,AE62,AC62,AA62,Y62,W62,U62,S62,Q62,O62,K62,I62)=21,"✓","✗") -> ✗ | BC62: =IFERROR(SUM(BM62:DC62),"") -> 3.88 | BE62: =IFERROR(LOOKUP(BC62,'OSM - Rating and Score'!$G$103:$I$108,'OSM - Rating and Score'!$C$103:$C$108),"") -> Attractive | BG62: Finmedex /Done | BM62: =ROUND(VLOOKUP(I62,'OSM - Rating and Score'!$C$8:$D$13,2,0)*BM$6,2) -> 0 | BO62: =ROUND(VLOOKUP(K62,'OSM - Rating and Score'!$C$8:$D$13,2,0)*BO$6,2) -> 0.2 | BS62: =ROUND(VLOOKUP(O62,'OSM - Rating and Score'!$C$17:$D$22,2,0)*BS$6,2) -> 0.2 | BU62: =ROUND(VLOOKUP(Q62,'OSM - Rating and Score'!$C$56:$D$61,2,0)*BU$6,2) -> 0.28 | BW62: =ROUND(VLOOKUP(S62,'OSM - Rating and Score'!$C$26:$D$31,2,0)*BW$6,2) -> 0.2 | BY62: =ROUND(VLOOKUP(U62,'OSM - Rating and Score'!$C$35:$D$40,2,0)*BY$6,2) -> 0.35 | CC62: =ROUND(LOOKUP(Y62,'OSM - Rating and Score'!$G$85:$I$90,'OSM - Rating and Score'!$D$85:$D$90)*CC$6,2) -> 0.2 | CE62: =ROUND(LOOKUP(AA62,'OSM - Rating and Score'!$G$113:$I$118,'OSM - Rating and Score'!$D$113:$D$118)*CE$6,2) -> 0.32 | CG62: =ROUND(LOOKUP(AC62,'OSM - Rating and Score'!$G$94:$I$99,'OSM - Rating and Score'!$D$85:$D$90)*CG$6,2) -> 0.1 | CI62: =ROUND(VLOOKUP(AE62,'OSM - Rating and Score'!$C$8:$D$13,2,0)*CI$6,2) -> 0.5 | CK62: =ROUND(VLOOKUP(AG62,'OSM - Rating and Score'!$C$8:$D$13,2,0)*CK$6,2) -> 0.04 | CM62: 0 | CO62: =ROUND(VLOOKUP(AK62,'OSM - Rating and Score'!$C$8:$D$13,2,0)*CO$6,2) -> 0.28 | CQ62: =ROUND(VLOOKUP(AM62,'OSM - Rating and Score'!$C$47:$D$52,2,0)*CQ$6,2) -> 0.2 | CS62: =ROUND(VLOOKUP(AO62,'OSM - Rating and Score'!$C$47:$D$52,2,0)*CS$6,2) -> 0.2 | CU62: =ROUND(VLOOKUP(AQ62,'OSM - Rating and Score'!$C$47:$D$52,2,0)*CU$6,2) -> 0.2 | CW62: =ROUND(VLOOKUP(AS62,'OSM - Rating and Score'!$C$47:$D$52,2,0)*CW$6,2) -> 0.21 | CY62: =ROUND(VLOOKUP(AU62,'OSM - Rating and Score'!$C$65:$D$70,2,0)*CY$6,2) -> 0.2 | DA62: =ROUND(VLOOKUP(AW62,'OSM - Rating and Score'!$C$8:$D$13,2,0)*DA$6,2) -> 0 | DC62: =ROUND(VLOOKUP(AY62,'OSM - Rating and Score'!$C$75:$D$80,2,0)*DC$6,2) -> 0.2
G63: GIT Stents | I63: High | K63: High | O63: Medium Barriers | Q63: Strong Fit | S63: Limited Readiness | U63: No New Team | W63: 50 | Y63: 2 | AA63: 0.25 | AC63: =ROUND(Y63*(1+AA63)^5,0) -> 6 | AE63: Very High | AG63: Minimal | AK63: High | AM63: Difficult | AO63: Easy | AQ63: Moderate | AS63: Easy | AU63: Moderate | AW63: Minimal | AY63: Fast | BA63: =IF(COUNTA(AY63,AW63,AU63,AS63,AQ63,AO63,AM63,AK63,AI63,AG63,AE63,AC63,AA63,Y63,W63,U63,S63,Q63,O63,K63,I63)=21,"✓","✗") -> ✗ | BC63: =IFERROR(SUM(BM63:DC63),"") -> 3.44 | BE63: =IFERROR(LOOKUP(BC63,'OSM - Rating and Score'!$G$103:$I$108,'OSM - Rating and Score'!$C$103:$C$108),"") -> Moderate | BG63: nothing | BM63: =ROUND(VLOOKUP(I63,'OSM - Rating and Score'!$C$8:$D$13,2,0)*BM$6,2) -> 0 | BO63: =ROUND(VLOOKUP(K63,'OSM - Rating and Score'!$C$8:$D$13,2,0)*BO$6,2) -> 0.2 | BS63: =ROUND(VLOOKUP(O63,'OSM - Rating and Score'!$C$17:$D$22,2,0)*BS$6,2) -> 0.15 | BU63: =ROUND(VLOOKUP(Q63,'OSM - Rating and Score'!$C$56:$D$61,2,0)*BU$6,2) -> 0.28 | BW63: =ROUND(VLOOKUP(S63,'OSM - Rating and Score'!$C$26:$D$31,2,0)*BW$6,2) -> 0.1 | BY63: =ROUND(VLOOKUP(U63,'OSM - Rating and Score'!$C$35:$D$40,2,0)*BY$6,2) -> 0.35 | CC63: =ROUND(LOOKUP(Y63,'OSM - Rating and Score'!$G$85:$I$90,'OSM - Rating and Score'!$D$85:$D$90)*CC$6,2) -> 0.2 | CE63: =ROUND(LOOKUP(AA63,'OSM - Rating and Score'!$G$113:$I$118,'OSM - Rating and Score'!$D$113:$D$118)*CE$6,2) -> 0.16 | CG63: =ROUND(LOOKUP(AC63,'OSM - Rating and Score'!$G$94:$I$99,'OSM - Rating and Score'!$D$85:$D$90)*CG$6,2) -> 0.1 | CI63: =ROUND(VLOOKUP(AE63,'OSM - Rating and Score'!$C$8:$D$13,2,0)*CI$6,2) -> 0.5 | CK63: =ROUND(VLOOKUP(AG63,'OSM - Rating and Score'!$C$8:$D$13,2,0)*CK$6,2) -> 0.04 | CM63: 0 | CO63: =ROUND(VLOOKUP(AK63,'OSM - Rating and Score'!$C$8:$D$13,2,0)*CO$6,2) -> 0.28 | CQ63: =ROUND(VLOOKUP(AM63,'OSM - Rating and Score'!$C$47:$D$52,2,0)*CQ$6,2) -> 0.1 | CS63: =ROUND(VLOOKUP(AO63,'OSM - Rating and Score'!$C$47:$D$52,2,0)*CS$6,2) -> 0.2 | CU63: =ROUND(VLOOKUP(AQ63,'OSM - Rating and Score'!$C$47:$D$52,2,0)*CU$6,2) -> 0.15 | CW63: =ROUND(VLOOKUP(AS63,'OSM - Rating and Score'!$C$47:$D$52,2,0)*CW$6,2) -> 0.28 | CY63: =ROUND(VLOOKUP(AU63,'OSM - Rating and Score'!$C$65:$D$70,2,0)*CY$6,2) -> 0.15 | DA63: =ROUND(VLOOKUP(AW63,'OSM - Rating and Score'!$C$8:$D$13,2,0)*DA$6,2) -> 0 | DC63: =ROUND(VLOOKUP(AY63,'OSM - Rating and Score'!$C$75:$D$80,2,0)*DC$6,2) -> 0.2
C64: 30 | G64: Endoscopy washer | I64: High | K64: High | O64: High Barriers | Q64: Moderate Fit | S64: Limited Readiness | U64: Minor Additions | W64: 50 | Y64: 3 | AA64: 0.25 | AC64: =ROUND(Y64*(1+AA64)^5,0) -> 9 | AE64: High | AG64: Minimal | AK64: Medium | AM64: Moderate | AO64: Moderate | AQ64: Difficult | AS64: Moderate | AU64: Complex | AW64: Medium | AY64: Fast | BA64: =IF(COUNTA(AY64,AW64,AU64,AS64,AQ64,AO64,AM64,AK64,AI64,AG64,AE64,AC64,AA64,Y64,W64,U64,S64,Q64,O64,K64,I64)=21,"✓","✗") -> ✗ | BC64: =IFERROR(SUM(BM64:DC64),"") -> 2.91 | BE64: =IFERROR(LOOKUP(BC64,'OSM - Rating and Score'!$G$103:$I$108,'OSM - Rating and Score'!$C$103:$C$108),"") -> Moderate | BG64: Shinva | BM64: =ROUND(VLOOKUP(I64,'OSM - Rating and Score'!$C$8:$D$13,2,0)*BM$6,2) -> 0 | BO64: =ROUND(VLOOKUP(K64,'OSM - Rating and Score'!$C$8:$D$13,2,0)*BO$6,2) -> 0.2 | BS64: =ROUND(VLOOKUP(O64,'OSM - Rating and Score'!$C$17:$D$22,2,0)*BS$6,2) -> 0.1 | BU64: =ROUND(VLOOKUP(Q64,'OSM - Rating and Score'!$C$56:$D$61,2,0)*BU$6,2) -> 0.21 | BW64: =ROUND(VLOOKUP(S64,'OSM - Rating and Score'!$C$26:$D$31,2,0)*BW$6,2) -> 0.1 | BY64: =ROUND(VLOOKUP(U64,'OSM - Rating and Score'!$C$35:$D$40,2,0)*BY$6,2) -> 0.28 | CC64: =ROUND(LOOKUP(Y64,'OSM - Rating and Score'!$G$85:$I$90,'OSM - Rating and Score'!$D$85:$D$90)*CC$6,2) -> 0.2 | CE64: =ROUND(LOOKUP(AA64,'OSM - Rating and Score'!$G$113:$I$118,'OSM - Rating and Score'!$D$113:$D$118)*CE$6,2) -> 0.16 | CG64: =ROUND(LOOKUP(AC64,'OSM - Rating and Score'!$G$94:$I$99,'OSM - Rating and Score'!$D$85:$D$90)*CG$6,2) -> 0.1 | CI64: =ROUND(VLOOKUP(AE64,'OSM - Rating and Score'!$C$8:$D$13,2,0)*CI$6,2) -> 0.4 | CK64: =ROUND(VLOOKUP(AG64,'OSM - Rating and Score'!$C$8:$D$13,2,0)*CK$6,2) -> 0.04 | CM64: 0 | CO64: =ROUND(VLOOKUP(AK64,'OSM - Rating and Score'!$C$8:$D$13,2,0)*CO$6,2) -> 0.21 | CQ64: =ROUND(VLOOKUP(AM64,'OSM - Rating and Score'!$C$47:$D$52,2,0)*CQ$6,2) -> 0.15 | CS64: =ROUND(VLOOKUP(AO64,'OSM - Rating and Score'!$C$47:$D$52,2,0)*CS$6,2) -> 0.15 | CU64: =ROUND(VLOOKUP(AQ64,'OSM - Rating and Score'!$C$47:$D$52,2,0)*CU$6,2) -> 0.1 | CW64: =ROUND(VLOOKUP(AS64,'OSM - Rating and Score'!$C$47:$D$52,2,0)*CW$6,2) -> 0.21 | CY64: =ROUND(VLOOKUP(AU64,'OSM - Rating and Score'!$C$65:$D$70,2,0)*CY$6,2) -> 0.1 | DA64: =ROUND(VLOOKUP(AW64,'OSM - Rating and Score'!$C$8:$D$13,2,0)*DA$6,2) -> 0 | DC64: =ROUND(VLOOKUP(AY64,'OSM - Rating and Score'!$C$75:$D$80,2,0)*DC$6,2) -> 0.2
C65: 31 | G65: Robotic Surgery | I65: Low | K65: High | O65: High Barriers | Q65: Strong Fit | S65: Limited Readiness | U65: Minor Additions | W65: 150 | Y65: 3 | AA65: 0.4 | AC65: =ROUND(Y65*(1+AA65)^5,0) -> 16 | AE65: Very High | AG65: Minimal | AI65: 2 | AK65: Low | AM65: Moderate | AO65: Difficult | AQ65: Easy | AS65: Difficult | AU65: Moderate | AW65: Minimal | AY65: Very Slow | BA65: =IF(COUNTA(AY65,AW65,AU65,AS65,AQ65,AO65,AM65,AK65,AI65,AG65,AE65,AC65,AA65,Y65,W65,U65,S65,Q65,O65,K65,I65)=21,"✓","✗") -> ✓ | BC65: =IFERROR(SUM(BM65:DC65),"") -> 3.15 | BE65: =IFERROR(LOOKUP(BC65,'OSM - Rating and Score'!$G$103:$I$108,'OSM - Rating and Score'!$C$103:$C$108),"") -> Moderate | BG65: KANGII | BM65: =ROUND(VLOOKUP(I65,'OSM - Rating and Score'!$C$8:$D$13,2,0)*BM$6,2) -> 0 | BO65: =ROUND(VLOOKUP(K65,'OSM - Rating and Score'!$C$8:$D$13,2,0)*BO$6,2) -> 0.2 | BS65: =ROUND(VLOOKUP(O65,'OSM - Rating and Score'!$C$17:$D$22,2,0)*BS$6,2) -> 0.1 | BU65: =ROUND(VLOOKUP(Q65,'OSM - Rating and Score'!$C$56:$D$61,2,0)*BU$6,2) -> 0.28 | BW65: =ROUND(VLOOKUP(S65,'OSM - Rating and Score'!$C$26:$D$31,2,0)*BW$6,2) -> 0.1 | BY65: =ROUND(VLOOKUP(U65,'OSM - Rating and Score'!$C$35:$D$40,2,0)*BY$6,2) -> 0.28 | CC65: =ROUND(LOOKUP(Y65,'OSM - Rating and Score'!$G$85:$I$90,'OSM - Rating and Score'!$D$85:$D$90)*CC$6,2) -> 0.2 | CE65: =ROUND(LOOKUP(AA65,'OSM - Rating and Score'!$G$113:$I$118,'OSM - Rating and Score'!$D$113:$D$118)*CE$6,2) -> 0.32 | CG65: =ROUND(LOOKUP(AC65,'OSM - Rating and Score'!$G$94:$I$99,'OSM - Rating and Score'!$D$85:$D$90)*CG$6,2) -> 0.2 | CI65: =ROUND(VLOOKUP(AE65,'OSM - Rating and Score'!$C$8:$D$13,2,0)*CI$6,2) -> 0.5 | CK65: =ROUND(VLOOKUP(AG65,'OSM - Rating and Score'!$C$8:$D$13,2,0)*CK$6,2) -> 0.04 | CM65: 0 | CO65: =ROUND(VLOOKUP(AK65,'OSM - Rating and Score'!$C$8:$D$13,2,0)*CO$6,2) -> 0.14 | CQ65: =ROUND(VLOOKUP(AM65,'OSM - Rating and Score'!$C$47:$D$52,2,0)*CQ$6,2) -> 0.15 | CS65: =ROUND(VLOOKUP(AO65,'OSM - Rating and Score'!$C$47:$D$52,2,0)*CS$6,2) -> 0.1 | CU65: =ROUND(VLOOKUP(AQ65,'OSM - Rating and Score'!$C$47:$D$52,2,0)*CU$6,2) -> 0.2 | CW65: =ROUND(VLOOKUP(AS65,'OSM - Rating and Score'!$C$47:$D$52,2,0)*CW$6,2) -> 0.14 | CY65: =ROUND(VLOOKUP(AU65,'OSM - Rating and Score'!$C$65:$D$70,2,0)*CY$6,2) -> 0.15 | DA65: =ROUND(VLOOKUP(AW65,'OSM - Rating and Score'!$C$8:$D$13,2,0)*DA$6,2) -> 0 | DC65: =ROUND(VLOOKUP(AY65,'OSM - Rating and Score'!$C$75:$D$80,2,0)*DC$6,2) -> 0.05
G66: Endoscopic Instruments | I66: Low | K66: High | O66: High Barriers | Q66: Strong Fit | S66: Limited Readiness | U66: Major New Team | W66: 200 | Y66: 3 | AA66: 0.25 | AC66: =ROUND(Y66*(1+AA66)^5,0) -> 9 | AE66: Medium | AG66: Minimal | AK66: Medium | AM66: Easy | AO66: Moderate | AQ66: Moderate | AS66: Difficult | AU66: Complex | AW66: Minimal | AY66: Fast | BA66: =IF(COUNTA(AY66,AW66,AU66,AS66,AQ66,AO66,AM66,AK66,AI66,AG66,AE66,AC66,AA66,Y66,W66,U66,S66,Q66,O66,K66,I66)=21,"✓","✗") -> ✗ | BC66: =IFERROR(SUM(BM66:DC66),"") -> 2.77 | BE66: =IFERROR(LOOKUP(BC66,'OSM - Rating and Score'!$G$103:$I$108,'OSM - Rating and Score'!$C$103:$C$108),"") -> Moderate | BM66: =ROUND(VLOOKUP(I66,'OSM - Rating and Score'!$C$8:$D$13,2,0)*BM$6,2) -> 0 | BO66: =ROUND(VLOOKUP(K66,'OSM - Rating and Score'!$C$8:$D$13,2,0)*BO$6,2) -> 0.2 | BS66: =ROUND(VLOOKUP(O66,'OSM - Rating and Score'!$C$17:$D$22,2,0)*BS$6,2) -> 0.1 | BU66: =ROUND(VLOOKUP(Q66,'OSM - Rating and Score'!$C$56:$D$61,2,0)*BU$6,2) -> 0.28 | BW66: =ROUND(VLOOKUP(S66,'OSM - Rating and Score'!$C$26:$D$31,2,0)*BW$6,2) -> 0.1 | BY66: =ROUND(VLOOKUP(U66,'OSM - Rating and Score'!$C$35:$D$40,2,0)*BY$6,2) -> 0.14 | CC66: =ROUND(LOOKUP(Y66,'OSM - Rating and Score'!$G$85:$I$90,'OSM - Rating and Score'!$D$85:$D$90)*CC$6,2) -> 0.2 | CE66: =ROUND(LOOKUP(AA66,'OSM - Rating and Score'!$G$113:$I$118,'OSM - Rating and Score'!$D$113:$D$118)*CE$6,2) -> 0.16 | CG66: =ROUND(LOOKUP(AC66,'OSM - Rating and Score'!$G$94:$I$99,'OSM - Rating and Score'!$D$85:$D$90)*CG$6,2) -> 0.1 | CI66: =ROUND(VLOOKUP(AE66,'OSM - Rating and Score'!$C$8:$D$13,2,0)*CI$6,2) -> 0.3 | CK66: =ROUND(VLOOKUP(AG66,'OSM - Rating and Score'!$C$8:$D$13,2,0)*CK$6,2) -> 0.04 | CM66: 0 | CO66: =ROUND(VLOOKUP(AK66,'OSM - Rating and Score'!$C$8:$D$13,2,0)*CO$6,2) -> 0.21 | CQ66: =ROUND(VLOOKUP(AM66,'OSM - Rating and Score'!$C$47:$D$52,2,0)*CQ$6,2) -> 0.2 | CS66: =ROUND(VLOOKUP(AO66,'OSM - Rating and Score'!$C$47:$D$52,2,0)*CS$6,2) -> 0.15 | CU66: =ROUND(VLOOKUP(AQ66,'OSM - Rating and Score'!$C$47:$D$52,2,0)*CU$6,2) -> 0.15 | CW66: =ROUND(VLOOKUP(AS66,'OSM - Rating and Score'!$C$47:$D$52,2,0)*CW$6,2) -> 0.14 | CY66: =ROUND(VLOOKUP(AU66,'OSM - Rating and Score'!$C$65:$D$70,2,0)*CY$6,2) -> 0.1 | DA66: =ROUND(VLOOKUP(AW66,'OSM - Rating and Score'!$C$8:$D$13,2,0)*DA$6,2) -> 0 | DC66: =ROUND(VLOOKUP(AY66,'OSM - Rating and Score'!$C$75:$D$80,2,0)*DC$6,2) -> 0.2
C67: 32 | G67: C-ARM | I67: Medium | K67: Low | O67: Medium Barriers | Q67: Moderate Fit | S67: Partially Ready | U67: Some New Staff | W67: 100 | Y67: 3 | AA67: 0.29 | AC67: =ROUND(Y67*(1+AA67)^5,0) -> 11 | AE67: Medium | AG67: Minimal | AI67: 0.4 | AK67: Medium | AM67: Moderate | AO67: Moderate | AQ67: Moderate | AS67: Difficult | AU67: Low Complex | AW67: Minimal | AY67: Medium | BA67: =IF(COUNTA(AY67,AW67,AU67,AS67,AQ67,AO67,AM67,AK67,AI67,AG67,AE67,AC67,AA67,Y67,W67,U67,S67,Q67,O67,K67,I67)=21,"✓","✗") -> ✓ | BC67: =IFERROR(SUM(BM67:DC67),"") -> 2.85 | BE67: =IFERROR(LOOKUP(BC67,'OSM - Rating and Score'!$G$103:$I$108,'OSM - Rating and Score'!$C$103:$C$108),"") -> Moderate | BG67: ECTRON/GMM | BM67: =ROUND(VLOOKUP(I67,'OSM - Rating and Score'!$C$8:$D$13,2,0)*BM$6,2) -> 0 | BO67: =ROUND(VLOOKUP(K67,'OSM - Rating and Score'!$C$8:$D$13,2,0)*BO$6,2) -> 0.1 | BS67: =ROUND(VLOOKUP(O67,'OSM - Rating and Score'!$C$17:$D$22,2,0)*BS$6,2) -> 0.15 | BU67: =ROUND(VLOOKUP(Q67,'OSM - Rating and Score'!$C$56:$D$61,2,0)*BU$6,2) -> 0.21 | BW67: =ROUND(VLOOKUP(S67,'OSM - Rating and Score'!$C$26:$D$31,2,0)*BW$6,2) -> 0.15 | BY67: =ROUND(VLOOKUP(U67,'OSM - Rating and Score'!$C$35:$D$40,2,0)*BY$6,2) -> 0.21 | CC67: =ROUND(LOOKUP(Y67,'OSM - Rating and Score'!$G$85:$I$90,'OSM - Rating and Score'!$D$85:$D$90)*CC$6,2) -> 0.2 | CE67: =ROUND(LOOKUP(AA67,'OSM - Rating and Score'!$G$113:$I$118,'OSM - Rating and Score'!$D$113:$D$118)*CE$6,2) -> 0.24 | CG67: =ROUND(LOOKUP(AC67,'OSM - Rating and Score'!$G$94:$I$99,'OSM - Rating and Score'!$D$85:$D$90)*CG$6,2) -> 0.1 | CI67: =ROUND(VLOOKUP(AE67,'OSM - Rating and Score'!$C$8:$D$13,2,0)*CI$6,2) -> 0.3 | CK67: =ROUND(VLOOKUP(AG67,'OSM - Rating and Score'!$C$8:$D$13,2,0)*CK$6,2) -> 0.04 | CM67: 0 | CO67: =ROUND(VLOOKUP(AK67,'OSM - Rating and Score'!$C$8:$D$13,2,0)*CO$6,2) -> 0.21 | CQ67: =ROUND(VLOOKUP(AM67,'OSM - Rating and Score'!$C$47:$D$52,2,0)*CQ$6,2) -> 0.15 | CS67: =ROUND(VLOOKUP(AO67,'OSM - Rating and Score'!$C$47:$D$52,2,0)*CS$6,2) -> 0.15 | CU67: =ROUND(VLOOKUP(AQ67,'OSM - Rating and Score'!$C$47:$D$52,2,0)*CU$6,2) -> 0.15 | CW67: =ROUND(VLOOKUP(AS67,'OSM - Rating and Score'!$C$47:$D$52,2,0)*CW$6,2) -> 0.14 | CY67: =ROUND(VLOOKUP(AU67,'OSM - Rating and Score'!$C$65:$D$70,2,0)*CY$6,2) -> 0.2 | DA67: =ROUND(VLOOKUP(AW67,'OSM - Rating and Score'!$C$8:$D$13,2,0)*DA$6,2) -> 0 | DC67: =ROUND(VLOOKUP(AY67,'OSM - Rating and Score'!$C$75:$D$80,2,0)*DC$6,2) -> 0.15
G68: CSSD | I68: Medium | K68: Low | O68: High Barriers | Q68: Moderate Fit | S68: Partially Ready | U68: Major New Team | W68: 150 | Y68: 1.5 | AA68: 0.45 | AC68: =ROUND(Y68*(1+AA68)^5,0) -> 10 | AE68: Medium | AG68: Minimal | AI68: 0.4 | AK68: Medium | AM68: Easy | AO68: Moderate | AQ68: Moderate | AS68: Difficult | AU68: Moderate | AW68: Minimal | AY68: Medium | BA68: =IF(COUNTA(AY68,AW68,AU68,AS68,AQ68,AO68,AM68,AK68,AI68,AG68,AE68,AC68,AA68,Y68,W68,U68,S68,Q68,O68,K68,I68)=21,"✓","✗") -> ✓ | BC68: =IFERROR(SUM(BM68:DC68),"") -> 2.81 | BE68: =IFERROR(LOOKUP(BC68,'OSM - Rating and Score'!$G$103:$I$108,'OSM - Rating and Score'!$C$103:$C$108),"") -> Moderate | BG68: Shinva | BM68: =ROUND(VLOOKUP(I68,'OSM - Rating and Score'!$C$8:$D$13,2,0)*BM$6,2) -> 0 | BO68: =ROUND(VLOOKUP(K68,'OSM - Rating and Score'!$C$8:$D$13,2,0)*BO$6,2) -> 0.1 | BS68: =ROUND(VLOOKUP(O68,'OSM - Rating and Score'!$C$17:$D$22,2,0)*BS$6,2) -> 0.1 | BU68: =ROUND(VLOOKUP(Q68,'OSM - Rating and Score'!$C$56:$D$61,2,0)*BU$6,2) -> 0.21 | BW68: =ROUND(VLOOKUP(S68,'OSM - Rating and Score'!$C$26:$D$31,2,0)*BW$6,2) -> 0.15 | BY68: =ROUND(VLOOKUP(U68,'OSM - Rating and Score'!$C$35:$D$40,2,0)*BY$6,2) -> 0.14 | CC68: =ROUND(LOOKUP(Y68,'OSM - Rating and Score'!$G$85:$I$90,'OSM - Rating and Score'!$D$85:$D$90)*CC$6,2) -> 0.2 | CE68: =ROUND(LOOKUP(AA68,'OSM - Rating and Score'!$G$113:$I$118,'OSM - Rating and Score'!$D$113:$D$118)*CE$6,2) -> 0.32 | CG68: =ROUND(LOOKUP(AC68,'OSM - Rating and Score'!$G$94:$I$99,'OSM - Rating and Score'!$D$85:$D$90)*CG$6,2) -> 0.1 | CI68: =ROUND(VLOOKUP(AE68,'OSM - Rating and Score'!$C$8:$D$13,2,0)*CI$6,2) -> 0.3 | CK68: =ROUND(VLOOKUP(AG68,'OSM - Rating and Score'!$C$8:$D$13,2,0)*CK$6,2) -> 0.04 | CM68: 0 | CO68: =ROUND(VLOOKUP(AK68,'OSM - Rating and Score'!$C$8:$D$13,2,0)*CO$6,2) -> 0.21 | CQ68: =ROUND(VLOOKUP(AM68,'OSM - Rating and Score'!$C$47:$D$52,2,0)*CQ$6,2) -> 0.2 | CS68: =ROUND(VLOOKUP(AO68,'OSM - Rating and Score'!$C$47:$D$52,2,0)*CS$6,2) -> 0.15 | CU68: =ROUND(VLOOKUP(AQ68,'OSM - Rating and Score'!$C$47:$D$52,2,0)*CU$6,2) -> 0.15 | CW68: =ROUND(VLOOKUP(AS68,'OSM - Rating and Score'!$C$47:$D$52,2,0)*CW$6,2) -> 0.14 | CY68: =ROUND(VLOOKUP(AU68,'OSM - Rating and Score'!$C$65:$D$70,2,0)*CY$6,2) -> 0.15 | DA68: =ROUND(VLOOKUP(AW68,'OSM - Rating and Score'!$C$8:$D$13,2,0)*DA$6,2) -> 0 | DC68: =ROUND(VLOOKUP(AY68,'OSM - Rating and Score'!$C$75:$D$80,2,0)*DC$6,2) -> 0.15
C69: 33 | E69: Wound care | G69: Chitosan Dressing | I69: Medium | K69: High | O69: Low Barriers | Q69: Strong Fit | S69: Partially Ready | U69: Some New Staff | W69: 9 | Y69: 2 | AA69: 0.3 | AC69: =ROUND(Y69*(1+AA69)^5,0) -> 7 | AE69: High | AG69: Minimal | AI69: 0 | AK69: High | AM69: Difficult | AO69: Easy | AQ69: Moderate | AS69: Very Easy | AU69: Moderate | AW69: Minimal | AY69: Fast | BA69: =IF(COUNTA(AY69,AW69,AU69,AS69,AQ69,AO69,AM69,AK69,AI69,AG69,AE69,AC69,AA69,Y69,W69,U69,S69,Q69,O69,K69,I69)=21,"✓","✗") -> ✓ | BC69: =IFERROR(SUM(BM69:DC69),"") -> 3.45 | BE69: =IFERROR(LOOKUP(BC69,'OSM - Rating and Score'!$G$103:$I$108,'OSM - Rating and Score'!$C$103:$C$108),"") -> Moderate | BG69: Contacted with UMT and registeration ahd been started | BH69: we can catch June tender | BM69: =ROUND(VLOOKUP(I69,'OSM - Rating and Score'!$C$8:$D$13,2,0)*BM$6,2) -> 0 | BO69: =ROUND(VLOOKUP(K69,'OSM - Rating and Score'!$C$8:$D$13,2,0)*BO$6,2) -> 0.2 | BS69: =ROUND(VLOOKUP(O69,'OSM - Rating and Score'!$C$17:$D$22,2,0)*BS$6,2) -> 0.2 | BU69: =ROUND(VLOOKUP(Q69,'OSM - Rating and Score'!$C$56:$D$61,2,0)*BU$6,2) -> 0.28 | BW69: =ROUND(VLOOKUP(S69,'OSM - Rating and Score'!$C$26:$D$31,2,0)*BW$6,2) -> 0.15 | BY69: =ROUND(VLOOKUP(U69,'OSM - Rating and Score'!$C$35:$D$40,2,0)*BY$6,2) -> 0.21 | CC69: =ROUND(LOOKUP(Y69,'OSM - Rating and Score'!$G$85:$I$90,'OSM - Rating and Score'!$D$85:$D$90)*CC$6,2) -> 0.2 | CE69: =ROUND(LOOKUP(AA69,'OSM - Rating and Score'!$G$113:$I$118,'OSM - Rating and Score'!$D$113:$D$118)*CE$6,2) -> 0.24 | CG69: =ROUND(LOOKUP(AC69,'OSM - Rating and Score'!$G$94:$I$99,'OSM - Rating and Score'!$D$85:$D$90)*CG$6,2) -> 0.1 | CI69: =ROUND(VLOOKUP(AE69,'OSM - Rating and Score'!$C$8:$D$13,2,0)*CI$6,2) -> 0.4 | CK69: =ROUND(VLOOKUP(AG69,'OSM - Rating and Score'!$C$8:$D$13,2,0)*CK$6,2) -> 0.04 | CM69: 0 | CO69: =ROUND(VLOOKUP(AK69,'OSM - Rating and Score'!$C$8:$D$13,2,0)*CO$6,2) -> 0.28 | CQ69: =ROUND(VLOOKUP(AM69,'OSM - Rating and Score'!$C$47:$D$52,2,0)*CQ$6,2) -> 0.1 | CS69: =ROUND(VLOOKUP(AO69,'OSM - Rating and Score'!$C$47:$D$52,2,0)*CS$6,2) -> 0.2 | CU69: =ROUND(VLOOKUP(AQ69,'OSM - Rating and Score'!$C$47:$D$52,2,0)*CU$6,2) -> 0.15 | CW69: =ROUND(VLOOKUP(AS69,'OSM - Rating and Score'!$C$47:$D$52,2,0)*CW$6,2) -> 0.35 | CY69: =ROUND(VLOOKUP(AU69,'OSM - Rating and Score'!$C$65:$D$70,2,0)*CY$6,2) -> 0.15 | DA69: =ROUND(VLOOKUP(AW69,'OSM - Rating and Score'!$C$8:$D$13,2,0)*DA$6,2) -> 0 | DC69: =ROUND(VLOOKUP(AY69,'OSM - Rating and Score'!$C$75:$D$80,2,0)*DC$6,2) -> 0.2
AC70: =ROUND(Y70*(1+AA70)^5,0) -> 0 | BA70: =IF(COUNTA(AY70,AW70,AU70,AS70,AQ70,AO70,AM70,AK70,AI70,AG70,AE70,AC70,AA70,Y70,W70,U70,S70,Q70,O70,K70,I70)=21,"✓","✗") -> ✗ | BC70: =IFERROR(SUM(BM70:DC70),"") | BE70: =IFERROR(LOOKUP(BC70,'OSM - Rating and Score'!$G$103:$I$108,'OSM - Rating and Score'!$C$103:$C$108),"") | BM70: =ROUND(VLOOKUP(I70,'OSM - Rating and Score'!$C$8:$D$13,2,0)*BM$6,2) -> #N/A | BO70: =ROUND(VLOOKUP(K70,'OSM - Rating and Score'!$C$8:$D$13,2,0)*BO$6,2) -> #N/A | BS70: =ROUND(VLOOKUP(O70,'OSM - Rating and Score'!$C$17:$D$22,2,0)*BS$6,2) -> #N/A | BU70: =ROUND(VLOOKUP(Q70,'OSM - Rating and Score'!$C$56:$D$61,2,0)*BU$6,2) -> #N/A | BW70: =ROUND(VLOOKUP(S70,'OSM - Rating and Score'!$C$26:$D$31,2,0)*BW$6,2) -> #N/A | BY70: =ROUND(VLOOKUP(U70,'OSM - Rating and Score'!$C$35:$D$40,2,0)*BY$6,2) -> #N/A | CC70: =ROUND(LOOKUP(Y70,'OSM - Rating and Score'!$G$85:$I$90,'OSM - Rating and Score'!$D$85:$D$90)*CC$6,2) -> 0 | CE70: =ROUND(LOOKUP(AA70,'OSM - Rating and Score'!$G$113:$I$118,'OSM - Rating and Score'!$D$113:$D$118)*CE$6,2) -> 0 | CG70: =ROUND(LOOKUP(AC70,'OSM - Rating and Score'!$G$94:$I$99,'OSM - Rating and Score'!$D$85:$D$90)*CG$6,2) -> 0 | CI70: =ROUND(VLOOKUP(AE70,'OSM - Rating and Score'!$C$8:$D$13,2,0)*CI$6,2) -> #N/A | CK70: =ROUND(VLOOKUP(AG70,'OSM - Rating and Score'!$C$8:$D$13,2,0)*CK$6,2) -> #N/A | CM70: 0 | CO70: =ROUND(VLOOKUP(AK70,'OSM - Rating and Score'!$C$8:$D$13,2,0)*CO$6,2) -> #N/A | CQ70: =ROUND(VLOOKUP(AM70,'OSM - Rating and Score'!$C$47:$D$52,2,0)*CQ$6,2) -> #N/A | CS70: =ROUND(VLOOKUP(AO70,'OSM - Rating and Score'!$C$47:$D$52,2,0)*CS$6,2) -> #N/A | CU70: =ROUND(VLOOKUP(AQ70,'OSM - Rating and Score'!$C$47:$D$52,2,0)*CU$6,2) -> #N/A | CW70: =ROUND(VLOOKUP(AS70,'OSM - Rating and Score'!$C$47:$D$52,2,0)*CW$6,2) -> #N/A | CY70: =ROUND(VLOOKUP(AU70,'OSM - Rating and Score'!$C$65:$D$70,2,0)*CY$6,2) -> #N/A | DA70: =ROUND(VLOOKUP(AW70,'OSM - Rating and Score'!$C$8:$D$13,2,0)*DA$6,2) -> #N/A | DC70: =ROUND(VLOOKUP(AY70,'OSM - Rating and Score'!$C$75:$D$80,2,0)*DC$6,2) -> #N/A
C71: 34 | E71: CVS / Wound care | G71: Geko - Tens disposable patch | I71: High | K71: High | O71: Low Barriers | Q71: Moderate Fit | S71: Partially Ready | U71: Some New Staff | W71: 8 | Y71: 8 | AA71: 0.3 | AC71: =ROUND(Y71*(1+AA71)^5,0) -> 30 | AE71: High | AG71: Minimal | AI71: 0 | AK71: High | AM71: Difficult | AO71: Easy | AQ71: Moderate | AS71: Very Easy | AU71: Moderate | AW71: High | AY71: Fast | BA71: =IF(COUNTA(AY71,AW71,AU71,AS71,AQ71,AO71,AM71,AK71,AI71,AG71,AE71,AC71,AA71,Y71,W71,U71,S71,Q71,O71,K71,I71)=21,"✓","✗") -> ✓ | BC71: =IFERROR(SUM(BM71:DC71),"") -> 3.78 | BE71: =IFERROR(LOOKUP(BC71,'OSM - Rating and Score'!$G$103:$I$108,'OSM - Rating and Score'!$C$103:$C$108),"") -> Attractive | BG71: Negotiaon started with FirstKind (currently awarded on NUPCO) | BH71: We can partciapte in the coming tender | BM71: =ROUND(VLOOKUP(I71,'OSM - Rating and Score'!$C$8:$D$13,2,0)*BM$6,2) -> 0 | BO71: =ROUND(VLOOKUP(K71,'OSM - Rating and Score'!$C$8:$D$13,2,0)*BO$6,2) -> 0.2 | BS71: =ROUND(VLOOKUP(O71,'OSM - Rating and Score'!$C$17:$D$22,2,0)*BS$6,2) -> 0.2 | BU71: =ROUND(VLOOKUP(Q71,'OSM - Rating and Score'!$C$56:$D$61,2,0)*BU$6,2) -> 0.21 | BW71: =ROUND(VLOOKUP(S71,'OSM - Rating and Score'!$C$26:$D$31,2,0)*BW$6,2) -> 0.15 | BY71: =ROUND(VLOOKUP(U71,'OSM - Rating and Score'!$C$35:$D$40,2,0)*BY$6,2) -> 0.21 | CC71: =ROUND(LOOKUP(Y71,'OSM - Rating and Score'!$G$85:$I$90,'OSM - Rating and Score'!$D$85:$D$90)*CC$6,2) -> 0.3 | CE71: =ROUND(LOOKUP(AA71,'OSM - Rating and Score'!$G$113:$I$118,'OSM - Rating and Score'!$D$113:$D$118)*CE$6,2) -> 0.24 | CG71: =ROUND(LOOKUP(AC71,'OSM - Rating and Score'!$G$94:$I$99,'OSM - Rating and Score'!$D$85:$D$90)*CG$6,2) -> 0.4 | CI71: =ROUND(VLOOKUP(AE71,'OSM - Rating and Score'!$C$8:$D$13,2,0)*CI$6,2) -> 0.4 | CK71: =ROUND(VLOOKUP(AG71,'OSM - Rating and Score'!$C$8:$D$13,2,0)*CK$6,2) -> 0.04 | CM71: 0 | CO71: =ROUND(VLOOKUP(AK71,'OSM - Rating and Score'!$C$8:$D$13,2,0)*CO$6,2) -> 0.28 | CQ71: =ROUND(VLOOKUP(AM71,'OSM - Rating and Score'!$C$47:$D$52,2,0)*CQ$6,2) -> 0.1 | CS71: =ROUND(VLOOKUP(AO71,'OSM - Rating and Score'!$C$47:$D$52,2,0)*CS$6,2) -> 0.2 | CU71: =ROUND(VLOOKUP(AQ71,'OSM - Rating and Score'!$C$47:$D$52,2,0)*CU$6,2) -> 0.15 | CW71: =ROUND(VLOOKUP(AS71,'OSM - Rating and Score'!$C$47:$D$52,2,0)*CW$6,2) -> 0.35 | CY71: =ROUND(VLOOKUP(AU71,'OSM - Rating and Score'!$C$65:$D$70,2,0)*CY$6,2) -> 0.15 | DA71: =ROUND(VLOOKUP(AW71,'OSM - Rating and Score'!$C$8:$D$13,2,0)*DA$6,2) -> 0 | DC71: =ROUND(VLOOKUP(AY71,'OSM - Rating and Score'!$C$75:$D$80,2,0)*DC$6,2) -> 0.2
C72: 35 | E72: Surgical Sutures | G72: Demitech | I72: High | K72: Medium | O72: High Barriers | Q72: Moderate Fit | S72: Partially Ready | U72: Some New Staff | W72: 200 | Y72: 8 | AA72: 0.2 | AC72: =ROUND(Y72*(1+AA72)^5,0) -> 20 | AE72: Low | AG72: Minimal | AI72: 0 | AK72: High | AM72: Easy | AO72: Easy | AQ72: Difficult | AS72: Difficult | AU72: Moderate | AW72: Medium | AY72: Fast | BA72: =IF(COUNTA(AY72,AW72,AU72,AS72,AQ72,AO72,AM72,AK72,AI72,AG72,AE72,AC72,AA72,Y72,W72,U72,S72,Q72,O72,K72,I72)=21,"✓","✗") -> ✓ | BC72: =IFERROR(SUM(BM72:DC72),"") -> 2.99 | BE72: =IFERROR(LOOKUP(BC72,'OSM - Rating and Score'!$G$103:$I$108,'OSM - Rating and Score'!$C$103:$C$108),"") -> Moderate | BM72: =ROUND(VLOOKUP(I72,'OSM - Rating and Score'!$C$8:$D$13,2,0)*BM$6,2) -> 0 | BO72: =ROUND(VLOOKUP(K72,'OSM - Rating and Score'!$C$8:$D$13,2,0)*BO$6,2) -> 0.15 | BS72: =ROUND(VLOOKUP(O72,'OSM - Rating and Score'!$C$17:$D$22,2,0)*BS$6,2) -> 0.1 | BU72: =ROUND(VLOOKUP(Q72,'OSM - Rating and Score'!$C$56:$D$61,2,0)*BU$6,2) -> 0.21 | BW72: =ROUND(VLOOKUP(S72,'OSM - Rating and Score'!$C$26:$D$31,2,0)*BW$6,2) -> 0.15 | BY72: =ROUND(VLOOKUP(U72,'OSM - Rating and Score'!$C$35:$D$40,2,0)*BY$6,2) -> 0.21 | CC72: =ROUND(LOOKUP(Y72,'OSM - Rating and Score'!$G$85:$I$90,'OSM - Rating and Score'!$D$85:$D$90)*CC$6,2) -> 0.3 | CE72: =ROUND(LOOKUP(AA72,'OSM - Rating and Score'!$G$113:$I$118,'OSM - Rating and Score'!$D$113:$D$118)*CE$6,2) -> 0.16 | CG72: =ROUND(LOOKUP(AC72,'OSM - Rating and Score'!$G$94:$I$99,'OSM - Rating and Score'!$D$85:$D$90)*CG$6,2) -> 0.2 | CI72: =ROUND(VLOOKUP(AE72,'OSM - Rating and Score'!$C$8:$D$13,2,0)*CI$6,2) -> 0.2 | CK72: =ROUND(VLOOKUP(AG72,'OSM - Rating and Score'!$C$8:$D$13,2,0)*CK$6,2) -> 0.04 | CM72: 0 | CO72: =ROUND(VLOOKUP(AK72,'OSM - Rating and Score'!$C$8:$D$13,2,0)*CO$6,2) -> 0.28 | CQ72: =ROUND(VLOOKUP(AM72,'OSM - Rating and Score'!$C$47:$D$52,2,0)*CQ$6,2) -> 0.2 | CS72: =ROUND(VLOOKUP(AO72,'OSM - Rating and Score'!$C$47:$D$52,2,0)*CS$6,2) -> 0.2 | CU72: =ROUND(VLOOKUP(AQ72,'OSM - Rating and Score'!$C$47:$D$52,2,0)*CU$6,2) -> 0.1 | CW72: =ROUND(VLOOKUP(AS72,'OSM - Rating and Score'!$C$47:$D$52,2,0)*CW$6,2) -> 0.14 | CY72: =ROUND(VLOOKUP(AU72,'OSM - Rating and Score'!$C$65:$D$70,2,0)*CY$6,2) -> 0.15 | DA72: =ROUND(VLOOKUP(AW72,'OSM - Rating and Score'!$C$8:$D$13,2,0)*DA$6,2) -> 0 | DC72: =ROUND(VLOOKUP(AY72,'OSM - Rating and Score'!$C$75:$D$80,2,0)*DC$6,2) -> 0.2
AC73: =ROUND(Y73*(1+AA73)^5,0) -> 0 | BA73: =IF(COUNTA(AY73,AW73,AU73,AS73,AQ73,AO73,AM73,AK73,AI73,AG73,AE73,AC73,AA73,Y73,W73,U73,S73,Q73,O73,K73,I73)=21,"✓","✗") -> ✗ | BC73: =IFERROR(SUM(BM73:DC73),"") | BE73: =IFERROR(LOOKUP(BC73,'OSM - Rating and Score'!$G$103:$I$108,'OSM - Rating and Score'!$C$103:$C$108),"") | BM73: =ROUND(VLOOKUP(I73,'OSM - Rating and Score'!$C$8:$D$13,2,0)*BM$6,2) -> #N/A | BO73: =ROUND(VLOOKUP(K73,'OSM - Rating and Score'!$C$8:$D$13,2,0)*BO$6,2) -> #N/A | BS73: =ROUND(VLOOKUP(O73,'OSM - Rating and Score'!$C$17:$D$22,2,0)*BS$6,2) -> #N/A | BU73: =ROUND(VLOOKUP(Q73,'OSM - Rating and Score'!$C$56:$D$61,2,0)*BU$6,2) -> #N/A | BW73: =ROUND(VLOOKUP(S73,'OSM - Rating and Score'!$C$26:$D$31,2,0)*BW$6,2) -> #N/A | BY73: =ROUND(VLOOKUP(U73,'OSM - Rating and Score'!$C$35:$D$40,2,0)*BY$6,2) -> #N/A | CC73: =ROUND(LOOKUP(Y73,'OSM - Rating and Score'!$G$85:$I$90,'OSM - Rating and Score'!$D$85:$D$90)*CC$6,2) -> 0 | CE73: =ROUND(LOOKUP(AA73,'OSM - Rating and Score'!$G$113:$I$118,'OSM - Rating and Score'!$D$113:$D$118)*CE$6,2) -> 0 | CG73: =ROUND(LOOKUP(AC73,'OSM - Rating and Score'!$G$94:$I$99,'OSM - Rating and Score'!$D$85:$D$90)*CG$6,2) -> 0 | CI73: =ROUND(VLOOKUP(AE73,'OSM - Rating and Score'!$C$8:$D$13,2,0)*CI$6,2) -> #N/A | CK73: =ROUND(VLOOKUP(AG73,'OSM - Rating and Score'!$C$8:$D$13,2,0)*CK$6,2) -> #N/A | CM73: 0 | CO73: =ROUND(VLOOKUP(AK73,'OSM - Rating and Score'!$C$8:$D$13,2,0)*CO$6,2) -> #N/A | CQ73: =ROUND(VLOOKUP(AM73,'OSM - Rating and Score'!$C$47:$D$52,2,0)*CQ$6,2) -> #N/A | CS73: =ROUND(VLOOKUP(AO73,'OSM - Rating and Score'!$C$47:$D$52,2,0)*CS$6,2) -> #N/A | CU73: =ROUND(VLOOKUP(AQ73,'OSM - Rating and Score'!$C$47:$D$52,2,0)*CU$6,2) -> #N/A | CW73: =ROUND(VLOOKUP(AS73,'OSM - Rating and Score'!$C$47:$D$52,2,0)*CW$6,2) -> #N/A | CY73: =ROUND(VLOOKUP(AU73,'OSM - Rating and Score'!$C$65:$D$70,2,0)*CY$6,2) -> #N/A | DA73: =ROUND(VLOOKUP(AW73,'OSM - Rating and Score'!$C$8:$D$13,2,0)*DA$6,2) -> #N/A | DC73: =ROUND(VLOOKUP(AY73,'OSM - Rating and Score'!$C$75:$D$80,2,0)*DC$6,2) -> #N/A
C74: 36 | AC74: =ROUND(Y74*(1+AA74)^5,0) -> 0 | BA74: =IF(COUNTA(AY74,AW74,AU74,AS74,AQ74,AO74,AM74,AK74,AI74,AG74,AE74,AC74,AA74,Y74,W74,U74,S74,Q74,O74,K74,I74)=21,"✓","✗") -> ✗ | BC74: =IFERROR(SUM(BM74:DC74),"") | BE74: =IFERROR(LOOKUP(BC74,'OSM - Rating and Score'!$G$103:$I$108,'OSM - Rating and Score'!$C$103:$C$108),"") | BM74: =ROUND(VLOOKUP(I74,'OSM - Rating and Score'!$C$8:$D$13,2,0)*BM$6,2) -> #N/A | BO74: =ROUND(VLOOKUP(K74,'OSM - Rating and Score'!$C$8:$D$13,2,0)*BO$6,2) -> #N/A | BS74: =ROUND(VLOOKUP(O74,'OSM - Rating and Score'!$C$17:$D$22,2,0)*BS$6,2) -> #N/A | BU74: =ROUND(VLOOKUP(Q74,'OSM - Rating and Score'!$C$56:$D$61,2,0)*BU$6,2) -> #N/A | BW74: =ROUND(VLOOKUP(S74,'OSM - Rating and Score'!$C$26:$D$31,2,0)*BW$6,2) -> #N/A | BY74: =ROUND(VLOOKUP(U74,'OSM - Rating and Score'!$C$35:$D$40,2,0)*BY$6,2) -> #N/A | CC74: =ROUND(LOOKUP(Y74,'OSM - Rating and Score'!$G$85:$I$90,'OSM - Rating and Score'!$D$85:$D$90)*CC$6,2) -> 0 | CE74: =ROUND(LOOKUP(AA74,'OSM - Rating and Score'!$G$113:$I$118,'OSM - Rating and Score'!$D$113:$D$118)*CE$6,2) -> 0 | CG74: =ROUND(LOOKUP(AC74,'OSM - Rating and Score'!$G$94:$I$99,'OSM - Rating and Score'!$D$85:$D$90)*CG$6,2) -> 0 | CI74: =ROUND(VLOOKUP(AE74,'OSM - Rating and Score'!$C$8:$D$13,2,0)*CI$6,2) -> #N/A | CK74: =ROUND(VLOOKUP(AG74,'OSM - Rating and Score'!$C$8:$D$13,2,0)*CK$6,2) -> #N/A | CM74: 0 | CO74: =ROUND(VLOOKUP(AK74,'OSM - Rating and Score'!$C$8:$D$13,2,0)*CO$6,2) -> #N/A | CQ74: =ROUND(VLOOKUP(AM74,'OSM - Rating and Score'!$C$47:$D$52,2,0)*CQ$6,2) -> #N/A | CS74: =ROUND(VLOOKUP(AO74,'OSM - Rating and Score'!$C$47:$D$52,2,0)*CS$6,2) -> #N/A | CU74: =ROUND(VLOOKUP(AQ74,'OSM - Rating and Score'!$C$47:$D$52,2,0)*CU$6,2) -> #N/A | CW74: =ROUND(VLOOKUP(AS74,'OSM - Rating and Score'!$C$47:$D$52,2,0)*CW$6,2) -> #N/A | CY74: =ROUND(VLOOKUP(AU74,'OSM - Rating and Score'!$C$65:$D$70,2,0)*CY$6,2) -> #N/A | DA74: =ROUND(VLOOKUP(AW74,'OSM - Rating and Score'!$C$8:$D$13,2,0)*DA$6,2) -> #N/A | DC74: =ROUND(VLOOKUP(AY74,'OSM - Rating and Score'!$C$75:$D$80,2,0)*DC$6,2) -> #N/A
AC75: =ROUND(Y75*(1+AA75)^5,0) -> 0 | BA75: =IF(COUNTA(AY75,AW75,AU75,AS75,AQ75,AO75,AM75,AK75,AI75,AG75,AE75,AC75,AA75,Y75,W75,U75,S75,Q75,O75,K75,I75)=21,"✓","✗") -> ✗ | BC75: =IFERROR(SUM(BM75:DC75),"") | BE75: =IFERROR(LOOKUP(BC75,'OSM - Rating and Score'!$G$103:$I$108,'OSM - Rating and Score'!$C$103:$C$108),"") | BM75: =ROUND(VLOOKUP(I75,'OSM - Rating and Score'!$C$8:$D$13,2,0)*BM$6,2) -> #N/A | BO75: =ROUND(VLOOKUP(K75,'OSM - Rating and Score'!$C$8:$D$13,2,0)*BO$6,2) -> #N/A | BS75: =ROUND(VLOOKUP(O75,'OSM - Rating and Score'!$C$17:$D$22,2,0)*BS$6,2) -> #N/A | BU75: =ROUND(VLOOKUP(Q75,'OSM - Rating and Score'!$C$56:$D$61,2,0)*BU$6,2) -> #N/A | BW75: =ROUND(VLOOKUP(S75,'OSM - Rating and Score'!$C$26:$D$31,2,0)*BW$6,2) -> #N/A | BY75: =ROUND(VLOOKUP(U75,'OSM - Rating and Score'!$C$35:$D$40,2,0)*BY$6,2) -> #N/A | CC75: =ROUND(LOOKUP(Y75,'OSM - Rating and Score'!$G$85:$I$90,'OSM - Rating and Score'!$D$85:$D$90)*CC$6,2) -> 0 | CE75: =ROUND(LOOKUP(AA75,'OSM - Rating and Score'!$G$113:$I$118,'OSM - Rating and Score'!$D$113:$D$118)*CE$6,2) -> 0 | CG75: =ROUND(LOOKUP(AC75,'OSM - Rating and Score'!$G$94:$I$99,'OSM - Rating and Score'!$D$85:$D$90)*CG$6,2) -> 0 | CI75: =ROUND(VLOOKUP(AE75,'OSM - Rating and Score'!$C$8:$D$13,2,0)*CI$6,2) -> #N/A | CK75: =ROUND(VLOOKUP(AG75,'OSM - Rating and Score'!$C$8:$D$13,2,0)*CK$6,2) -> #N/A | CM75: 0 | CO75: =ROUND(VLOOKUP(AK75,'OSM - Rating and Score'!$C$8:$D$13,2,0)*CO$6,2) -> #N/A | CQ75: =ROUND(VLOOKUP(AM75,'OSM - Rating and Score'!$C$47:$D$52,2,0)*CQ$6,2) -> #N/A | CS75: =ROUND(VLOOKUP(AO75,'OSM - Rating and Score'!$C$47:$D$52,2,0)*CS$6,2) -> #N/A | CU75: =ROUND(VLOOKUP(AQ75,'OSM - Rating and Score'!$C$47:$D$52,2,0)*CU$6,2) -> #N/A | CW75: =ROUND(VLOOKUP(AS75,'OSM - Rating and Score'!$C$47:$D$52,2,0)*CW$6,2) -> #N/A | CY75: =ROUND(VLOOKUP(AU75,'OSM - Rating and Score'!$C$65:$D$70,2,0)*CY$6,2) -> #N/A | DA75: =ROUND(VLOOKUP(AW75,'OSM - Rating and Score'!$C$8:$D$13,2,0)*DA$6,2) -> #N/A | DC75: =ROUND(VLOOKUP(AY75,'OSM - Rating and Score'!$C$75:$D$80,2,0)*DC$6,2) -> #N/A
C76: 37

Sheet OSM Field
E2: =SUM(E4:E26) -> 1
B3: SN | C3: Field Description | D3: JMI Critical (Yes/No) | E3: Weight %
C4: Market | J4: 290 | K4: 2025
B5: 1 | C5: Opportunity | D5: No | E5: 0 | J5: 380 | K5: =K4+1 -> 2026
B6: =B5+1 -> 2 | C6: Awareness & Capability | D6: Yes | E6: 0.05 | J6: 500 | K6: =K5+1 -> 2027
B7: =B6+1 -> 3 | C7: Entry Barriers | D7: Yes | E7: 0.05 | J7: 620 | K7: =K6+1 -> 2028
B8: =B7+1 -> 4 | C8: Strategic Fit With JMI Portfolio | D8: Yes | E8: 0.07 | J8: 750 | K8: =K7+1 -> 2029
B9: =B8+1 -> 5 | C9: Commercial Readiness | D9: Yes | E9: 0.05 | J9: 880 | K9: =K8+1 -> 2030
B10: =B9+1 -> 6 | C10: Sales Force Readiness | D10: Yes | E10: 0.07
C11: Financial
B12: =B10 -> 6 | C12: Total Market Size (in SAR Millions) | D12: No | E12: 0
B13: =B12+1 -> 7 | C13: JMI Target (In SAR Millions) | D13: Yes | E13: 0.1
B14: =B13+1 -> 8 | C14: JMI Growth (In SAR Millions) | D14: Yes | E14: 0.08
B15: =B14+1 -> 9 | C15: Gross Margin Potential | D15: Yes | E15: 0.1
B16: =B15+1 -> 10 | C16: Export Potential | D16: Yes | E16: 0.04
B17: =B16+1 -> 11 | C17: Capital Requirement | D17: No | E17: 0
C18: Ease of Entry
B19: =B17+1 -> 12 | C19: Tender Feasibility (NUPCO likelihood) | D19: Yes | E19: 0.07
B20: =B19+1 -> 13 | C20: Private Market | D20: Yes | E20: 0.05
B21: =B20+1 -> 14 | C21: Business Development | D21: Yes | E21: 0.05
B22: =B21+1 -> 15 | C22: Regulatory Complexity | D22: Yes | E22: 0.05
B23: =B22+1 -> 16 | C23: Product Complexity | D23: Yes | E23: 0.07
B24: =B23+1 -> 17 | C24: Operational Complexity | D24: Yes | E24: 0.05
B25: =B24+1 -> 18 | C25: Localization Opportunities | D25: No | E25: 0
B26: =B25+1 -> 19 | C26: Time To Market | D26: Yes | E26: 0.05

Sheet OSM - Rating and Score
B2: =M7 -> Tender Feasibility (NUPCO likelihood)
B3: =K7 -> Awareness & Capability
B4: =I7 -> Localization Opportunities
B5: =G7 -> Gross Margin Potential
B6: =E7 -> Opportunity
C7: Rating | D7: Score | E7: Opportunity | G7: Gross Margin Potential | I7: Localization Opportunities | K7: Awareness & Capability | M7: Tender Feasibility (NUPCO likelihood) | O7: Export Potential
C8: Very High | D8: 5 | E8: Clear and strong opportunity. Big demand, high growth, and fast impact. | G8: Strong margins; excellent profitability with room for future improvement. | I8: Strong potential for local assembly or full manufacturing; clear feasibility and incentives. | K8: Market fully knows the product; adoption is easy | M8: Product is very simple; minimal training; quick to introduce and support. | O8: Strong international demand; easy to export; high margin.
C9: High | D9: 4 | E9: Good opportunity with strong potential. Some work needed but promising. | G9: Good margin level; attractive and healthy for business. | I9: Good potential for partial localization (assembly, packaging, kitting). | K9: Market understands well; small education effort | M9: Product is simple; requires light training; manageable by sales and ops. | O9: Good export demand; feasible with moderate effort.
C10: Medium | D10: 3 | E10: Opportunity exists, but not fully clear. Moderate potential. | G10: Acceptable margin; workable but needs volume or efficiency to improve. | I10: Some localization possible but limited to minor value-added steps. | K10: Market is mixed; some know it, some don’t | M10: Product has some technical requirements; training and coordination needed. | O10: Some export demand; possible but needs work.
C11: Low | D11: 2 | E11: Weak opportunity. Small impact or limited demand. | G11: Weak margin; profitability is limited unless volume is high. | I11: Localization is difficult; minimal value-add possible. | K11: Market has limited understanding; heavy effort needed | M11: Product is complex; requires strong technical support and structured onboarding. | O11: Limited export opportunities; not attractive now.
C12: Minimal | D12: 1 | E12: Very small or unclear opportunity. Not worth focus now. | G12: Very low margin; unattractive and difficult to sustain. | I12: No realistic localization options for this category. | K12: Market does not know this product at all | M12: Product is highly technical; long learning curve; heavy operational burden. | O12: No meaningful export demand; not suitable.
C13: To Be Assessed | D13: 0 | E13: Not enough information yet to judge. | G13: Margin information not available yet. | I13: Localization feasibility not evaluated yet. | K13: Information not available yet | M13: Complexity not evaluated yet. | O13: Information missing or unclear.
B15: =E16 -> Entry Barriers
C16: Rating | D16: Score | E16: Entry Barriers
C17: Very Low Barriers | D17: 5 | E17: Easy to enter. No major regulatory, technical, or capital obstacles.
C18: Low Barriers | D18: 4 | E18: Manageable entry. Some work needed but not difficult.
C19: Medium Barriers | D19: 3 | E19: Moderate challenges. JMI can enter but needs planning.
C20: High Barriers | D20: 2 | E20: Hard to enter. Heavy approvals, strong competitors, or technical hurdles.
C21: Very High Barriers | D21: 1 | E21: Very difficult entry. Not suitable unless strategic.
C22: To Be Assessed | D22: 0 | E22: Not enough information yet.
B24: =E25 -> Commercial Readiness
C25: Rating | D25: Score | E25: Commercial Readiness
C26: Fully Ready | D26: 5 | E26: Multiple strong suppliers available; partnership can start immediately.
C27: Ready | D27: 4 | E27: Good suppliers available; onboarding is simple with minor effort.
C28: Partially Ready | D28: 3 | E28: Some supplier options but need evaluation or development.
C29: Limited Readiness | D29: 2 | E29: Very few supplier options; long qualification or negotiation required.
C30: Not Ready | D30: 1 | E30: No reliable suppliers available; partnership must be built from zero.
C31: To Be Assessed | D31: 0 | E31: Information not available yet.
B33: =E34 -> Sales Force Readiness
C34: Rating | D34: Score | E34: Sales Force Readiness
C35: No New Team | D35: 5 | E35: Current team can fully manage this opportunity. No new hiring or structure change. Smooth fit.
C36: Minor Additions | D36: 4 | E36: Mostly handled by current team, but 1–2 new roles or skills may be needed. Low effort.
C37: Some New Staff | D37: 3 | E37: Some parts can be handled internally, but multiple additional roles or a small new sub-team is required. Medium effort.
C38: Major New Team | D38: 2 | E38: Cannot be managed by current structure. Needs building a new team with several hires. High effort.
C39: Full New Setup | D39: 1 | E39: Completely new business setup. No alignment with current structure. Requires new department or BU. Very high effort.
C40: To Be Assessed | D40: 0 | E40: Not enough information to judge team requirement.
B42: =K46 -> Private Market
B43: =I46 -> Product Complexity
B44: =G46 -> Regulatory
B45: =E46 -> Business Development
C46: Rating | D46: Score | E46: Business Development | G46: Regulatory | I46: Product Complexity | K46: Private Market
C47: Very Easy | D47: 5 | E47: Product easy to launch, Team & customers already familiar. | G47: Registration simple; SFDA requirements clear; fast approval expected. | I47: Product is very simple; minimal training; quick to introduce and support. | K47: Market accepts new products quickly; fast onboarding and minimal barriers.
C48: Easy | D48: 4 | E48: Some BD required, but manageable. | G48: Mostly straightforward; some documents needed but no major barriers. | I48: Product is simple; requires light training; manageable by sales and ops. | K48: Good potential; customers open to adoption with moderate effort.
C49: Moderate | D49: 3 | E49: Needs demos, trials, some market education. | G49: Registration possible but requires time, data, or additional compliance steps. | I49: Product has some technical requirements; training and coordination needed. | K49: Entry possible but requires sales effort, education, or relationship building.
C50: Difficult | D50: 2 | E50: Heavy BD required; slow adoption expected. | G50: Heavy documentation; complex approval path; long registration timeline. | I50: Product is complex; requires strong technical support and structured onboarding. | K50: Hard to penetrate; strong competitors or slow adoption.
C51: Very Difficult | D51: 1 | E51: Requires full-scale BD push; long adoption period. | G51: Major regulatory hurdles; long approval or low chance of acceptance. | I51: Product is highly technical; long learning curve; heavy operational burden. | K51: Market resistant; high effort with low chance of success.
C52: To Be Assessed | D52: 0 | E52: Not enough info. | G52: Regulatory information not available yet. | I52: Complexity not evaluated yet. | K52: Information not yet available.
B54: =E55 -> Strategic Fit With JMI Portfolio
C55: Rating | D55: Score | E55: Strategic Fit With JMI Portfolio
C56: Very Strong Fit | D56: 5 | E56: Fits perfectly with current business. Uses same customers, same sales team, same suppliers. Easy to sell. Creates strong synergy and fast results.
C57: Strong Fit | D57: 4 | E57: Matches most of the current portfolio. Good overlap with customers or channels. Easy for sales team to adopt.
C58: Moderate Fit | D58: 3 | E58: Some overlap exists but still needs effort. New skills or new suppliers may be required.
C59: Low Fit | D59: 2 | E59: Not well connected to current business. Limited overlap. Harder to sell with current structure.
C60: Very Low Fit | D60: 1 | E60: Almost no link with current portfolio. Very new area for JMI. High learning curve.
C61: No Information Yet | D61: 0 | E61: Not enough data to judge. Needs more study.
B63: =E64 -> Operational Complexity
C64: Rating | D64: Score | E64: Operational Complexity
C65: Very Complex | D65: 1 | E65: No operational capability for this category; must build from scratch.
C66: Complex | D66: 2 | E66: Limited operational readiness; significant setup or process changes needed.
C67: Moderate | D67: 3 | E67: Some capability exists but requires planning, training, or process support to handle this product.
C68: Low Complex | D68: 4 | E68: Good operational capability; only minor adjustments or setup needed.
C69: No Complex | D69: 5 | E69: Operations can fully support this product today; strong processes, capacity, and experience already exist.
C70: To Be Assessed | D70: 0 | E70: Capability not evaluated yet.
B73: =E74 -> Time To Market
C74: Rating | D74: Score | E74: Time To Market
C75: Very Fast | D75: 5 | E75: = < 12 months
C76: Fast | D76: 4 | E76: Btw 12–24 months
C77: Medium | D77: 3 | E77: Btw 24–36 months
C78: Slow | D78: 2 | E78: = > 36 months
C79: Very Slow | D79: 1 | E79: Above
C80: To Be Assessed | D80: 0 | E80: TBA
B83: =E84 -> Y01 Revenues (SAR in Millions)
C84: Rating | D84: Score | E84: Y01 Revenues (SAR in Millions) | G84: Low | I84: High
C85: To Be Assessed | D85: 0 | E85: Revenue data not available | G85: =IF(ISNUMBER(SEARCH("not available",E85)),0, IF(LEFT(E85,1)="≥",25, VALUE(SUBSTITUTE(LEFT(E85,FIND("–",E85)-1),"M","")))) -> 0 | I85: =IF(ISNUMBER(SEARCH("not available",E85)),0, IF(LEFT(E85,1)="≥",10000, VALUE(SUBSTITUTE(MID(E85,FIND("–",E85)+1,50),"M","")))) -> 0
C86: Minimal | D86: 1 | E86: 0.1M – 0.99M | G86: =IF(ISNUMBER(SEARCH("not available",E86)),0, IF(LEFT(E86,1)="≥",25, VALUE(SUBSTITUTE(LEFT(E86,FIND("–",E86)-1),"M","")))) -> 0.1 | I86: =IF(ISNUMBER(SEARCH("not available",E86)),0, IF(LEFT(E86,1)="≥",10000, VALUE(SUBSTITUTE(MID(E86,FIND("–",E86)+1,50),"M","")))) -> 0.99
C87: Low | D87: 2 | E87: 1M – 4.9M | G87: =IF(ISNUMBER(SEARCH("not available",E87)),0, IF(LEFT(E87,1)="≥",25, VALUE(SUBSTITUTE(LEFT(E87,FIND("–",E87)-1),"M","")))) -> 1 | I87: =IF(ISNUMBER(SEARCH("not available",E87)),0, IF(LEFT(E87,1)="≥",10000, VALUE(SUBSTITUTE(MID(E87,FIND("–",E87)+1,50),"M","")))) -> 4.9
C88: Medium | D88: 3 | E88: 5M – 14.9M | G88: =IF(ISNUMBER(SEARCH("not available",E88)),0, IF(LEFT(E88,1)="≥",25, VALUE(SUBSTITUTE(LEFT(E88,FIND("–",E88)-1),"M","")))) -> 5 | I88: =IF(ISNUMBER(SEARCH("not available",E88)),0, IF(LEFT(E88,1)="≥",10000, VALUE(SUBSTITUTE(MID(E88,FIND("–",E88)+1,50),"M","")))) -> 14.9
C89: High | D89: 4 | E89: 15M – 24.9M | G89: =IF(ISNUMBER(SEARCH("not available",E89)),0, IF(LEFT(E89,1)="≥",25, VALUE(SUBSTITUTE(LEFT(E89,FIND("–",E89)-1),"M","")))) -> 15 | I89: =IF(ISNUMBER(SEARCH("not available",E89)),0, IF(LEFT(E89,1)="≥",10000, VALUE(SUBSTITUTE(MID(E89,FIND("–",E89)+1,50),"M","")))) -> 24.9
C90: Very High | D90: 5 | E90: ≥ 25M | G90: =IF(ISNUMBER(SEARCH("not available",E90)),0, IF(LEFT(E90,1)="≥",25, VALUE(SUBSTITUTE(LEFT(E90,FIND("–",E90)-1),"M","")))) -> 25 | I90: =IF(ISNUMBER(SEARCH("not available",E90)),0, IF(LEFT(E90,1)="≥",10000, VALUE(SUBSTITUTE(MID(E90,FIND("–",E90)+1,50),"M","")))) -> 10000
B92: =E93 -> Y05 Revenues (SAR in Millions)
C93: Rating | D93: Score | E93: Y05 Revenues (SAR in Millions) | G93: Low | I93: High
C94: To Be Assessed | D94: 0 | E94: Revenue data not available | G94: =IF(ISNUMBER(SEARCH("not available",E94)),0, IF(LEFT(E94,1)="≥",25, VALUE(SUBSTITUTE(LEFT(E94,FIND("–",E94)-1),"M","")))) -> 0 | I94: =IF(ISNUMBER(SEARCH("not available",E94)),0, IF(LEFT(E94,1)="≥",10000, VALUE(SUBSTITUTE(MID(E94,FIND("–",E94)+1,50),"M","")))) -> 0
C95: Minimal | D95: 1 | E95: 5M – 14.9M | G95: =IF(ISNUMBER(SEARCH("not available",E95)),0, IF(LEFT(E95,1)="≥",25, VALUE(SUBSTITUTE(LEFT(E95,FIND("–",E95)-1),"M","")))) -> 5 | I95: =IF(ISNUMBER(SEARCH("not available",E95)),0, IF(LEFT(E95,1)="≥",10000, VALUE(SUBSTITUTE(MID(E95,FIND("–",E95)+1,50),"M","")))) -> 14.9
C96: Low | D96: 2 | E96: 15M – 24.9M | G96: =IF(ISNUMBER(SEARCH("not available",E96)),0, IF(LEFT(E96,1)="≥",25, VALUE(SUBSTITUTE(LEFT(E96,FIND("–",E96)-1),"M","")))) -> 15 | I96: =IF(ISNUMBER(SEARCH("not available",E96)),0, IF(LEFT(E96,1)="≥",10000, VALUE(SUBSTITUTE(MID(E96,FIND("–",E96)+1,50),"M","")))) -> 24.9
C97: Medium | D97: 3 | E97: 25M – 29.9M | G97: =IF(ISNUMBER(SEARCH("not available",E97)),0, IF(LEFT(E97,1)="≥",25, VALUE(SUBSTITUTE(LEFT(E97,FIND("–",E97)-1),"M","")))) -> 25 | I97: =IF(ISNUMBER(SEARCH("not available",E97)),0, IF(LEFT(E97,1)="≥",10000, VALUE(SUBSTITUTE(MID(E97,FIND("–",E97)+1,50),"M","")))) -> 29.9
C98: High | D98: 4 | E98: 30M – 34.9M | G98: =IF(ISNUMBER(SEARCH("not available",E98)),0, IF(LEFT(E98,1)="≥",25, VALUE(SUBSTITUTE(LEFT(E98,FIND("–",E98)-1),"M","")))) -> 30 | I98: =IF(ISNUMBER(SEARCH("not available",E98)),0, IF(LEFT(E98,1)="≥",10000, VALUE(SUBSTITUTE(MID(E98,FIND("–",E98)+1,50),"M","")))) -> 34.9
C99: Very High | D99: 5 | E99: ≥ 35M | G99: =IF(ISNUMBER(SEARCH("not available",E99)),0, IF(LEFT(E99,1)="≥",35, VALUE(SUBSTITUTE(LEFT(E99,FIND("–",E99)-1),"M","")))) -> 35 | I99: =IF(ISNUMBER(SEARCH("not available",E99)),0, IF(LEFT(E99,1)="≥",10000, VALUE(SUBSTITUTE(MID(E99,FIND("–",E99)+1,50),"M","")))) -> 10000
B101: =E102 -> Project Score
C102: Rating | D102: Score | E102: Project Score | G102: Low | I102: High
C103: To Be Assessed | D103: 0 | E103: Not enough inputs to score | G103: 0 | I103: 0.49
C104: Very Weak | D104: 1 | E104: Very poor opportunity; avoid | G104: =I103+0.01 -> 0.5 | I104: 1.49
C105: Weak | D105: 2 | E105: Low attractiveness; not recommended now | G105: =I104+0.01 -> 1.5 | I105: =G105+0.99 -> 2.49
C106: Moderate | D106: 3 | E106: Possible opportunity; needs validation or support | G106: =I105+0.01 -> 2.5 | I106: =G106+0.99 -> 3.49
C107: Attractive | D107: 4 | E107: Good opportunity; feasible and valuable | G107: =I106+0.01 -> 3.5 | I107: =G107+0.99 -> 4.49
C108: Very Attractive | D108: 5 | E108: Strong opportunity; high potential; must pursue | G108: =I107+0.01 -> 4.5 | I108: 5
B111: =E112 -> Gross Margin Potential
C112: Rating | D112: Score | E112: Gross Margin Potential | G112: Low | I112: High
C113: To Be Assessed | D113: 0 | E113: Revenue data not available | G113: =IF(ISNUMBER(SEARCH("not available",E113)),0, IF(LEFT(E113,1)="≥",25, VALUE(SUBSTITUTE(LEFT(E113,FIND("–",E113)-1),"M","")))) -> 0 | I113: =IF(ISNUMBER(SEARCH("not available",E113)),0, IF(LEFT(E113,1)="≥",10000, VALUE(SUBSTITUTE(MID(E113,FIND("–",E113)+1,50),"M","")))) -> 0
C114: Very Low Margin | D114: 1 | E114: < 15% | G114: =I113+0.001 -> 0.001 | I114: =MID(E114,3,2)/100 -> 0.15
C115: Low Margin | D115: 2 | E115: 15% – 25% | G115: =I114+0.001 -> 0.151 | I115: =IF(ISNUMBER(SEARCH("not available",E115)),0, IF(LEFT(E115,1)="≥",10000, VALUE(SUBSTITUTE(MID(E115,FIND("–",E115)+1,50),"M","")))) -> 0.25
...

Sheet Progress Dashboard
B3: DashBoard - 01
B4: Opportunity | C4: SBU | D4: Owner | E4: Score | F4: Stage | G4: On Track (Yes/Delay/Hold) | H4: Comment
B5: Surgical instruments | C5: Classic | D5: Mr. Samir | E5: 3.5 | G5: Yes/Delay/Hold
B6: Cardiology intervention | C6: Cardiology | D6: Ayman Kaddah | E6: 3.2
B7: CGM | C7: Wound-Care | D7: Mahmoud Younis | E7: 4.1
B9: DashBoard - 02
B10: Opportunity | C10: SBU | D10: Owner | E10: Action | F10: Due Date | G10: Status | H10: Comment
B15: DashBoard - 03
B16: Risk | C16: Impact (High/Med/Low) | D16: Likelihood (High/Med/Low) | E16: Owner | F16: Mitigation
